Workbook

Sheet Decision summary
A1: Decision summary
A2: Upshift — Business Plan · Main Scenario
A4: Variable / dimension | B4: Value
A5: Operating break-even month | B5: =MIN('Model inputs'!D48,'Model inputs'!E48,'Model inputs'!F48,'Model inputs'!G48,'Model inputs'!H48,'Model inputs'!I48,'Model inputs'!J48,'Model inputs'!K48,'Model inputs'!L48,'Model inputs'!M48,'Model inputs'!N48,'Model inputs'!O48,'Model inputs'!P48,'Model inputs'!Q48,'Model inputs'!R48,'Model inputs'!S48,'Model inputs'!T48,'Model inputs'!U48,'Model inputs'!V48,'Model inputs'!W48,'Model inputs'!X48,'Model inputs'!Y48,'Model inputs'!Z48,'Model inputs'!B48) -> 46327
A6: Cash break-even month | B6: =MIN('Model inputs'!D13,'Model inputs'!E13,'Model inputs'!F13,'Model inputs'!G13,'Model inputs'!H13,'Model inputs'!I13,'Model inputs'!J13,'Model inputs'!K13,'Model inputs'!L13,'Model inputs'!M13,'Model inputs'!N13,'Model inputs'!O13,'Model inputs'!P13,'Model inputs'!Q13,'Model inputs'!R13,'Model inputs'!S13,'Model inputs'!T13,'Model inputs'!U13,'Model inputs'!V13,'Model inputs'!W13,'Model inputs'!X13,'Model inputs'!Y13,'Model inputs'!Z13,'Model inputs'!B13) -> 46327
A7: Founder investment recovered month | B7: =MIN('Model inputs'!D35,'Model inputs'!E35,'Model inputs'!F35,'Model inputs'!G35,'Model inputs'!H35,'Model inputs'!I35,'Model inputs'!J35,'Model inputs'!K35,'Model inputs'!L35,'Model inputs'!M35,'Model inputs'!N35,'Model inputs'!O35,'Model inputs'!P35,'Model inputs'!Q35,'Model inputs'!R35,'Model inputs'!S35,'Model inputs'!T35,'Model inputs'!U35,'Model inputs'!V35,'Model inputs'!W35,'Model inputs'!X35,'Model inputs'!Y35,'Model inputs'!Z35,'Model inputs'!B35) -> 46357
A8: Peak founder funding | B8: =MAX('Base and upside comparison'!B13,'Base and upside comparison'!D13,'Base and upside comparison'!F13,'Base and upside comparison'!H13,'Base and upside comparison'!J13,'Base and upside comparison'!L13,'Base and upside comparison'!N13,'Base and upside comparison'!P13,'Base and upside comparison'!R13,'Base and upside comparison'!T13,'Base and upside comparison'!V13,'Base and upside comparison'!X13,'Base and upside comparison'!Z13,'Base and upside comparison'!AB13,'Base and upside comparison'!AD13,'Base and upside comparison'!AF13,'Base and upside comparison'!AH13,'Base and upside comparison'!AJ13,'Base and upside comparison'!AL13,'Base and upside comparison'!AN13,'Base and upside comparison'!AP13,'Base and upside comparison'!AR13,'Base and upside comparison'!AT13,'Base and upside comparison'!AV13) -> 144
A9: Cumulative cash low point | B9: =MIN('Base and upside comparison'!B12,'Base and upside comparison'!D12,'Base and upside comparison'!F12,'Base and upside comparison'!H12,'Base and upside comparison'!J12,'Base and upside comparison'!L12,'Base and upside comparison'!N12,'Base and upside comparison'!P12,'Base and upside comparison'!R12,'Base and upside comparison'!T12,'Base and upside comparison'!V12,'Base and upside comparison'!X12,'Base and upside comparison'!Z12,'Base and upside comparison'!AB12,'Base and upside comparison'!AD12,'Base and upside comparison'!AF12,'Base and upside comparison'!AH12,'Base and upside comparison'!AJ12,'Base and upside comparison'!AL12,'Base and upside comparison'!AN12,'Base and upside comparison'!AP12,'Base and upside comparison'!AR12,'Base and upside comparison'!AT12,'Base and upside comparison'!AV12) -> -144
A10: Month-24 paid repositories | B10: =IF('Base and upside comparison'!AV5="","",'Base and upside comparison'!AV5) -> 108.03848
A11: Month-24 monthly revenue | B11: =IF('Base and upside comparison'!AV6="","",'Base and upside comparison'!AV6) -> 5293.8856
A12: Month-24 ARR | B12: =IF('Model inputs'!B6="","",'Model inputs'!B6) -> 63526.628
A13: Month-24 unfunded cash | B13: =IF('Base and upside comparison'!AV12="","",'Base and upside comparison'!AV12) -> 36559.209
A14: Baseline Team gross margin | B14: =1-('Model inputs'!C63*'Model inputs'!C62+'Model inputs'!C8*('Model inputs'!C9+'Model inputs'!C7)+'Model inputs'!C56)/'Model inputs'!C59-'Model inputs'!C54 -> 0.95510204
A15: Team break-even repositories | B15: =CEILING((SUM('Model inputs'!C28)*(1+'Model inputs'!C55)+SUM('Model inputs'!C39,'Model inputs'!C40,'Model inputs'!C41)+'Model inputs'!C37)/('Model inputs'!C59*(1-'Model inputs'!C54)-('Model inputs'!C63*'Model inputs'!C62+'Model inputs'!C8*('Model inputs'!C9+'Model inputs'!C7)+'Model inputs'!C56)),1) -> 7

Sheet Base and upside comparison
A1: Base and upside comparison
A2: Upshift — Business Plan · Main Scenario
A4: Variable / dimension | B4: 2026-10 | C4: 2026-10 > Upshift — Upside | D4: 2026-11 | E4: 2026-11 > Upshift — Upside | F4: 2026-12 | G4: 2026-12 > Upshift — Upside | H4: 2027-01 | I4: 2027-01 > Upshift — Upside | J4: 2027-02 | K4: 2027-02 > Upshift — Upside | L4: 2027-03 | M4: 2027-03 > Upshift — Upside | N4: 2027-04 | O4: 2027-04 > Upshift — Upside | P4: 2027-05 | Q4: 2027-05 > Upshift — Upside | R4: 2027-06 | S4: 2027-06 > Upshift — Upside | T4: 2027-07 | U4: 2027-07 > Upshift — Upside | V4: 2027-08 | W4: 2027-08 > Upshift — Upside | X4: 2027-09 | Y4: 2027-09 > Upshift — Upside | Z4: 2027-10 | AA4: 2027-10 > Upshift — Upside | AB4: 2027-11 | AC4: 2027-11 > Upshift — Upside | AD4: 2027-12 | AE4: 2027-12 > Upshift — Upside | AF4: 2028-01 | AG4: 2028-01 > Upshift — Upside | AH4: 2028-02 | AI4: 2028-02 > Upshift — Upside | AJ4: 2028-03 | AK4: 2028-03 > Upshift — Upside | AL4: 2028-04 | AM4: 2028-04 > Upshift — Upside | AN4: 2028-05 | AO4: 2028-05 > Upshift — Upside | AP4: 2028-06 | AQ4: 2028-06 > Upshift — Upside | AR4: 2028-07 | AS4: 2028-07 > Upshift — Upside | AT4: 2028-08 | AU4: 2028-08 > Upshift — Upside | AV4: 2028-09 | AW4: 2028-09 > Upshift — Upside
A5: Paid repositories | B5: ='Model inputs'!D46+'Model inputs'!D44-'Model inputs'!D14 -> 3.3333333 | C5: ='Model inputs'!D47+'Model inputs'!D45-'Model inputs'!D15 -> 8.3333333 | D5: ='Model inputs'!E46+'Model inputs'!E44-'Model inputs'!E14 -> 6.6666667 | E5: ='Model inputs'!E47+'Model inputs'!E45-'Model inputs'!E15 -> 16.666667 | F5: ='Model inputs'!F46+'Model inputs'!F44-'Model inputs'!F14 -> 10 | G5: ='Model inputs'!F47+'Model inputs'!F45-'Model inputs'!F15 -> 25 | H5: ='Model inputs'!G46+'Model inputs'!G44-'Model inputs'!G14 -> 11.2 | I5: ='Model inputs'!G47+'Model inputs'!G45-'Model inputs'!G15 -> 30.5 | J5: ='Model inputs'!H46+'Model inputs'!H44-'Model inputs'!H14 -> 12.544 | K5: ='Model inputs'!H47+'Model inputs'!H45-'Model inputs'!H15 -> 37.21 | L5: ='Model inputs'!I46+'Model inputs'!I44-'Model inputs'!I14 -> 14.04928 | M5: ='Model inputs'!I47+'Model inputs'!I45-'Model inputs'!I15 -> 45.3962 | N5: ='Model inputs'!J46+'Model inputs'!J44-'Model inputs'!J14 -> 15.735194 | O5: ='Model inputs'!J47+'Model inputs'!J45-'Model inputs'!J15 -> 55.383364 | P5: ='Model inputs'!K46+'Model inputs'!K44-'Model inputs'!K14 -> 17.623417 | Q5: ='Model inputs'!K47+'Model inputs'!K45-'Model inputs'!K15 -> 67.567704 | R5: ='Model inputs'!L46+'Model inputs'!L44-'Model inputs'!L14 -> 19.738227 | S5: ='Model inputs'!L47+'Model inputs'!L45-'Model inputs'!L15 -> 82.432599 | T5: ='Model inputs'!M46+'Model inputs'!M44-'Model inputs'!M14 -> 22.106814 | U5: ='Model inputs'!M47+'Model inputs'!M45-'Model inputs'!M15 -> 100.56777 | V5: ='Model inputs'!N46+'Model inputs'!N44-'Model inputs'!N14 -> 24.759632 | W5: ='Model inputs'!N47+'Model inputs'!N45-'Model inputs'!N15 -> 122.69268 | X5: ='Model inputs'!O46+'Model inputs'!O44-'Model inputs'!O14 -> 27.730788 | Y5: ='Model inputs'!O47+'Model inputs'!O45-'Model inputs'!O15 -> 149.68507 | Z5: ='Model inputs'!P46+'Model inputs'!P44-'Model inputs'!P14 -> 31.058482 | AA5: ='Model inputs'!P47+'Model inputs'!P45-'Model inputs'!P15 -> 182.61579 | AB5: ='Model inputs'!Q46+'Model inputs'!Q44-'Model inputs'!Q14 -> 34.7855 | AC5: ='Model inputs'!Q47+'Model inputs'!Q45-'Model inputs'!Q15 -> 222.79126 | AD5: ='Model inputs'!R46+'Model inputs'!R44-'Model inputs'!R14 -> 38.95976 | AE5: ='Model inputs'!R47+'Model inputs'!R45-'Model inputs'!R15 -> 271.80533 | AF5: ='Model inputs'!S46+'Model inputs'!S44-'Model inputs'!S14 -> 43.634931 | AG5: ='Model inputs'!S47+'Model inputs'!S45-'Model inputs'!S15 -> 331.60251 | AH5: ='Model inputs'!T46+'Model inputs'!T44-'Model inputs'!T14 -> 48.871123 | AI5: ='Model inputs'!T47+'Model inputs'!T45-'Model inputs'!T15 -> 404.55506 | AJ5: ='Model inputs'!U46+'Model inputs'!U44-'Model inputs'!U14 -> 54.735658 | AK5: ='Model inputs'!U47+'Model inputs'!U45-'Model inputs'!U15 -> 493.55717 | AL5: ='Model inputs'!V46+'Model inputs'!V44-'Model inputs'!V14 -> 61.303937 | AM5: ='Model inputs'!V47+'Model inputs'!V45-'Model inputs'!V15 -> 602.13975 | AN5: ='Model inputs'!W46+'Model inputs'!W44-'Model inputs'!W14 -> 68.660409 | AO5: ='Model inputs'!W47+'Model inputs'!W45-'Model inputs'!W15 -> 734.6105 | AP5: ='Model inputs'!X46+'Model inputs'!X44-'Model inputs'!X14 -> 76.899658 | AQ5: ='Model inputs'!X47+'Model inputs'!X45-'Model inputs'!X15 -> 896.22481 | AR5: ='Model inputs'!Y46+'Model inputs'!Y44-'Model inputs'!Y14 -> 86.127617 | AS5: ='Model inputs'!Y47+'Model inputs'!Y45-'Model inputs'!Y15 -> 1093.3943 | AT5: ='Model inputs'!Z46+'Model inputs'!Z44-'Model inputs'!Z14 -> 96.462931 | AU5: ='Model inputs'!Z47+'Model inputs'!Z45-'Model inputs'!Z15 -> 1333.941 | AV5: ='Model inputs'!B46+'Model inputs'!B44-'Model inputs'!B14 -> 108.03848 | AW5: ='Model inputs'!B47+'Model inputs'!B45-'Model inputs'!B15 -> 1627.408
A6: Revenue | B6: ='Model inputs'!D66+'Model inputs'!D49 -> 163.33333 | C6: ='Model inputs'!D67+'Model inputs'!D50 -> 408.33333 | D6: ='Model inputs'!E66+'Model inputs'!E49 -> 326.66667 | E6: ='Model inputs'!E67+'Model inputs'!E50 -> 816.66667 | F6: ='Model inputs'!F66+'Model inputs'!F49 -> 490 | G6: ='Model inputs'!F67+'Model inputs'!F50 -> 1225 | H6: ='Model inputs'!G66+'Model inputs'!G49 -> 548.8 | I6: ='Model inputs'!G67+'Model inputs'!G50 -> 1494.5 | J6: ='Model inputs'!H66+'Model inputs'!H49 -> 614.656 | K6: ='Model inputs'!H67+'Model inputs'!H50 -> 1823.29 | L6: ='Model inputs'!I66+'Model inputs'!I49 -> 688.41472 | M6: ='Model inputs'!I67+'Model inputs'!I50 -> 2224.4138 | N6: ='Model inputs'!J66+'Model inputs'!J49 -> 771.02449 | O6: ='Model inputs'!J67+'Model inputs'!J50 -> 2713.7848 | P6: ='Model inputs'!K66+'Model inputs'!K49 -> 863.54742 | Q6: ='Model inputs'!K67+'Model inputs'!K50 -> 3310.8175 | R6: ='Model inputs'!L66+'Model inputs'!L49 -> 967.17312 | S6: ='Model inputs'!L67+'Model inputs'!L50 -> 4039.1973 | T6: ='Model inputs'!M66+'Model inputs'!M49 -> 1083.2339 | U6: ='Model inputs'!M67+'Model inputs'!M50 -> 4927.8208 | V6: ='Model inputs'!N66+'Model inputs'!N49 -> 1213.222 | W6: ='Model inputs'!N67+'Model inputs'!N50 -> 6011.9413 | X6: ='Model inputs'!O66+'Model inputs'!O49 -> 1358.8086 | Y6: ='Model inputs'!O67+'Model inputs'!O50 -> 7334.5684 | Z6: ='Model inputs'!P66+'Model inputs'!P49 -> 1521.8656 | AA6: ='Model inputs'!P67+'Model inputs'!P50 -> 8948.1735 | AB6: ='Model inputs'!Q66+'Model inputs'!Q49 -> 1704.4895 | AC6: ='Model inputs'!Q67+'Model inputs'!Q50 -> 10916.772 | AD6: ='Model inputs'!R66+'Model inputs'!R49 -> 1909.0282 | AE6: ='Model inputs'!R67+'Model inputs'!R50 -> 13318.461 | AF6: ='Model inputs'!S66+'Model inputs'!S49 -> 2138.1116 | AG6: ='Model inputs'!S67+'Model inputs'!S50 -> 16248.523 | AH6: ='Model inputs'!T66+'Model inputs'!T49 -> 2394.685 | AI6: ='Model inputs'!T67+'Model inputs'!T50 -> 19823.198 | AJ6: ='Model inputs'!U66+'Model inputs'!U49 -> 2682.0472 | AK6: ='Model inputs'!U67+'Model inputs'!U50 -> 24184.302 | AL6: ='Model inputs'!V66+'Model inputs'!V49 -> 3003.8929 | AM6: ='Model inputs'!V67+'Model inputs'!V50 -> 29504.848 | AN6: ='Model inputs'!W66+'Model inputs'!W49 -> 3364.36 | AO6: ='Model inputs'!W67+'Model inputs'!W50 -> 35995.914 | AP6: ='Model inputs'!X66+'Model inputs'!X49 -> 3768.0832 | AQ6: ='Model inputs'!X67+'Model inputs'!X50 -> 43915.016 | AR6: ='Model inputs'!Y66+'Model inputs'!Y49 -> 4220.2532 | AS6: ='Model inputs'!Y67+'Model inputs'!Y50 -> 53576.319 | AT6: ='Model inputs'!Z66+'Model inputs'!Z49 -> 4726.6836 | AU6: ='Model inputs'!Z67+'Model inputs'!Z50 -> 65363.109 | AV6: ='Model inputs'!B66+'Model inputs'!B49 -> 5293.8856 | AW6: ='Model inputs'!B67+'Model inputs'!B50 -> 79742.993
A7: Cost of revenue | B7: ='Model inputs'!D33+'Model inputs'!D17+'Model inputs'!D19+'Model inputs'!D52 -> 7.3333333 | C7: ='Model inputs'!D34+'Model inputs'!D18+'Model inputs'!D20+'Model inputs'!D53 -> 18.333333 | D7: ='Model inputs'!E33+'Model inputs'!E17+'Model inputs'!E19+'Model inputs'!E52 -> 14.666667 | E7: ='Model inputs'!E34+'Model inputs'!E18+'Model inputs'!E20+'Model inputs'!E53 -> 36.666667 | F7: ='Model inputs'!F33+'Model inputs'!F17+'Model inputs'!F19+'Model inputs'!F52 -> 22 | G7: ='Model inputs'!F34+'Model inputs'!F18+'Model inputs'!F20+'Model inputs'!F53 -> 55 | H7: ='Model inputs'!G33+'Model inputs'!G17+'Model inputs'!G19+'Model inputs'!G52 -> 24.64 | I7: ='Model inputs'!G34+'Model inputs'!G18+'Model inputs'!G20+'Model inputs'!G53 -> 67.1 | J7: ='Model inputs'!H33+'Model inputs'!H17+'Model inputs'!H19+'Model inputs'!H52 -> 27.5968 | K7: ='Model inputs'!H34+'Model inputs'!H18+'Model inputs'!H20+'Model inputs'!H53 -> 81.862 | L7: ='Model inputs'!I33+'Model inputs'!I17+'Model inputs'!I19+'Model inputs'!I52 -> 30.908416 | M7: ='Model inputs'!I34+'Model inputs'!I18+'Model inputs'!I20+'Model inputs'!I53 -> 99.87164 | N7: ='Model inputs'!J33+'Model inputs'!J17+'Model inputs'!J19+'Model inputs'!J52 -> 34.617426 | O7: ='Model inputs'!J34+'Model inputs'!J18+'Model inputs'!J20+'Model inputs'!J53 -> 121.8434 | P7: ='Model inputs'!K33+'Model inputs'!K17+'Model inputs'!K19+'Model inputs'!K52 -> 38.771517 | Q7: ='Model inputs'!K34+'Model inputs'!K18+'Model inputs'!K20+'Model inputs'!K53 -> 148.64895 | R7: ='Model inputs'!L33+'Model inputs'!L17+'Model inputs'!L19+'Model inputs'!L52 -> 43.424099 | S7: ='Model inputs'!L34+'Model inputs'!L18+'Model inputs'!L20+'Model inputs'!L53 -> 181.35172 | T7: ='Model inputs'!M33+'Model inputs'!M17+'Model inputs'!M19+'Model inputs'!M52 -> 48.634991 | U7: ='Model inputs'!M34+'Model inputs'!M18+'Model inputs'!M20+'Model inputs'!M53 -> 221.2491 | V7: ='Model inputs'!N33+'Model inputs'!N17+'Model inputs'!N19+'Model inputs'!N52 -> 54.47119 | W7: ='Model inputs'!N34+'Model inputs'!N18+'Model inputs'!N20+'Model inputs'!N53 -> 269.9239 | X7: ='Model inputs'!O33+'Model inputs'!O17+'Model inputs'!O19+'Model inputs'!O52 -> 61.007733 | Y7: ='Model inputs'!O34+'Model inputs'!O18+'Model inputs'!O20+'Model inputs'!O53 -> 329.30715 | Z7: ='Model inputs'!P33+'Model inputs'!P17+'Model inputs'!P19+'Model inputs'!P52 -> 68.328661 | AA7: ='Model inputs'!P34+'Model inputs'!P18+'Model inputs'!P20+'Model inputs'!P53 -> 401.75473 | AB7: ='Model inputs'!Q33+'Model inputs'!Q17+'Model inputs'!Q19+'Model inputs'!Q52 -> 76.5281 | AC7: ='Model inputs'!Q34+'Model inputs'!Q18+'Model inputs'!Q20+'Model inputs'!Q53 -> 490.14077 | AD7: ='Model inputs'!R33+'Model inputs'!R17+'Model inputs'!R19+'Model inputs'!R52 -> 85.711472 | AE7: ='Model inputs'!R34+'Model inputs'!R18+'Model inputs'!R20+'Model inputs'!R53 -> 597.97174 | AF7: ='Model inputs'!S33+'Model inputs'!S17+'Model inputs'!S19+'Model inputs'!S52 -> 95.996848 | AG7: ='Model inputs'!S34+'Model inputs'!S18+'Model inputs'!S20+'Model inputs'!S53 -> 729.52552 | AH7: ='Model inputs'!T33+'Model inputs'!T17+'Model inputs'!T19+'Model inputs'!T52 -> 107.51647 | AI7: ='Model inputs'!T34+'Model inputs'!T18+'Model inputs'!T20+'Model inputs'!T53 -> 890.02113 | AJ7: ='Model inputs'!U33+'Model inputs'!U17+'Model inputs'!U19+'Model inputs'!U52 -> 120.41845 | AK7: ='Model inputs'!U34+'Model inputs'!U18+'Model inputs'!U20+'Model inputs'!U53 -> 1085.8258 | AL7: ='Model inputs'!V33+'Model inputs'!V17+'Model inputs'!V19+'Model inputs'!V52 -> 134.86866 | AM7: ='Model inputs'!V34+'Model inputs'!V18+'Model inputs'!V20+'Model inputs'!V53 -> 1324.7075 | AN7: ='Model inputs'!W33+'Model inputs'!W17+'Model inputs'!W19+'Model inputs'!W52 -> 151.0529 | AO7: ='Model inputs'!W34+'Model inputs'!W18+'Model inputs'!W20+'Model inputs'!W53 -> 1616.1431 | AP7: ='Model inputs'!X33+'Model inputs'!X17+'Model inputs'!X19+'Model inputs'!X52 -> 169.17925 | AQ7: ='Model inputs'!X34+'Model inputs'!X18+'Model inputs'!X20+'Model inputs'!X53 -> 1971.6946 | AR7: ='Model inputs'!Y33+'Model inputs'!Y17+'Model inputs'!Y19+'Model inputs'!Y52 -> 189.48076 | AS7: ='Model inputs'!Y34+'Model inputs'!Y18+'Model inputs'!Y20+'Model inputs'!Y53 -> 2405.4674 | AT7: ='Model inputs'!Z33+'Model inputs'!Z17+'Model inputs'!Z19+'Model inputs'!Z52 -> 212.21845 | AU7: ='Model inputs'!Z34+'Model inputs'!Z18+'Model inputs'!Z20+'Model inputs'!Z53 -> 2934.6702 | AV7: ='Model inputs'!B33+'Model inputs'!B17+'Model inputs'!B19+'Model inputs'!B52 -> 237.68466 | AW7: ='Model inputs'!B34+'Model inputs'!B18+'Model inputs'!B20+'Model inputs'!B53 -> 3580.2977
A8: Gross margin | B8: =IFERROR('Model inputs'!D31/'Base and upside comparison'!B6,"") -> 0.95510204 | C8: =IFERROR('Model inputs'!D32/'Base and upside comparison'!C6,"") -> 0.95510204 | D8: =IFERROR('Model inputs'!E31/'Base and upside comparison'!D6,"") -> 0.95510204 | E8: =IFERROR('Model inputs'!E32/'Base and upside comparison'!E6,"") -> 0.95510204 | F8: =IFERROR('Model inputs'!F31/'Base and upside comparison'!F6,"") -> 0.95510204 | G8: =IFERROR('Model inputs'!F32/'Base and upside comparison'!G6,"") -> 0.95510204 | H8: =IFERROR('Model inputs'!G31/'Base and upside comparison'!H6,"") -> 0.95510204 | I8: =IFERROR('Model inputs'!G32/'Base and upside comparison'!I6,"") -> 0.95510204 | J8: =IFERROR('Model inputs'!H31/'Base and upside comparison'!J6,"") -> 0.95510204 | K8: =IFERROR('Model inputs'!H32/'Base and upside comparison'!K6,"") -> 0.95510204 | L8: =IFERROR('Model inputs'!I31/'Base and upside comparison'!L6,"") -> 0.95510204 | M8: =IFERROR('Model inputs'!I32/'Base and upside comparison'!M6,"") -> 0.95510204 | N8: =IFERROR('Model inputs'!J31/'Base and upside comparison'!N6,"") -> 0.95510204 | O8: =IFERROR('Model inputs'!J32/'Base and upside comparison'!O6,"") -> 0.95510204 | P8: =IFERROR('Model inputs'!K31/'Base and upside comparison'!P6,"") -> 0.95510204 | Q8: =IFERROR('Model inputs'!K32/'Base and upside comparison'!Q6,"") -> 0.95510204 | R8: =IFERROR('Model inputs'!L31/'Base and upside comparison'!R6,"") -> 0.95510204 | S8: =IFERROR('Model inputs'!L32/'Base and upside comparison'!S6,"") -> 0.95510204 | T8: =IFERROR('Model inputs'!M31/'Base and upside comparison'!T6,"") -> 0.95510204 | U8: =IFERROR('Model inputs'!M32/'Base and upside comparison'!U6,"") -> 0.95510204 | V8: =IFERROR('Model inputs'!N31/'Base and upside comparison'!V6,"") -> 0.95510204 | W8: =IFERROR('Model inputs'!N32/'Base and upside comparison'!W6,"") -> 0.95510204 | X8: =IFERROR('Model inputs'!O31/'Base and upside comparison'!X6,"") -> 0.95510204 | Y8: =IFERROR('Model inputs'!O32/'Base and upside comparison'!Y6,"") -> 0.95510204 | Z8: =IFERROR('Model inputs'!P31/'Base and upside comparison'!Z6,"") -> 0.95510204 | AA8: =IFERROR('Model inputs'!P32/'Base and upside comparison'!AA6,"") -> 0.95510204 | AB8: =IFERROR('Model inputs'!Q31/'Base and upside comparison'!AB6,"") -> 0.95510204 | AC8: =IFERROR('Model inputs'!Q32/'Base and upside comparison'!AC6,"") -> 0.95510204 | AD8: =IFERROR('Model inputs'!R31/'Base and upside comparison'!AD6,"") -> 0.95510204 | AE8: =IFERROR('Model inputs'!R32/'Base and upside comparison'!AE6,"") -> 0.95510204 | AF8: =IFERROR('Model inputs'!S31/'Base and upside comparison'!AF6,"") -> 0.95510204 | AG8: =IFERROR('Model inputs'!S32/'Base and upside comparison'!AG6,"") -> 0.95510204 | AH8: =IFERROR('Model inputs'!T31/'Base and upside comparison'!AH6,"") -> 0.95510204 | AI8: =IFERROR('Model inputs'!T32/'Base and upside comparison'!AI6,"") -> 0.95510204 | AJ8: =IFERROR('Model inputs'!U31/'Base and upside comparison'!AJ6,"") -> 0.95510204 | AK8: =IFERROR('Model inputs'!U32/'Base and upside comparison'!AK6,"") -> 0.95510204 | AL8: =IFERROR('Model inputs'!V31/'Base and upside comparison'!AL6,"") -> 0.95510204 | AM8: =IFERROR('Model inputs'!V32/'Base and upside comparison'!AM6,"") -> 0.95510204 | AN8: =IFERROR('Model inputs'!W31/'Base and upside comparison'!AN6,"") -> 0.95510204 | AO8: =IFERROR('Model inputs'!W32/'Base and upside comparison'!AO6,"") -> 0.95510204 | AP8: =IFERROR('Model inputs'!X31/'Base and upside comparison'!AP6,"") -> 0.95510204 | AQ8: =IFERROR('Model inputs'!X32/'Base and upside comparison'!AQ6,"") -> 0.95510204 | AR8: =IFERROR('Model inputs'!Y31/'Base and upside comparison'!AR6,"") -> 0.95510204 | AS8: =IFERROR('Model inputs'!Y32/'Base and upside comparison'!AS6,"") -> 0.95510204 | AT8: =IFERROR('Model inputs'!Z31/'Base and upside comparison'!AT6,"") -> 0.95510204 | AU8: =IFERROR('Model inputs'!Z32/'Base and upside comparison'!AU6,"") -> 0.95510204 | AV8: =IFERROR('Model inputs'!B31/'Base and upside comparison'!AV6,"") -> 0.95510204 | AW8: =IFERROR('Model inputs'!B32/'Base and upside comparison'!AW6,"") -> 0.95510204
A9: Operating costs | B9: ='Model inputs'!D29+'Model inputs'!D21 -> 300 | C9: ='Model inputs'!D30+'Model inputs'!D22 -> 300 | D9: ='Model inputs'!E29+'Model inputs'!E21 -> 300 | E9: ='Model inputs'!E30+'Model inputs'!E22 -> 300 | F9: ='Model inputs'!F29+'Model inputs'!F21 -> 300 | G9: ='Model inputs'!F30+'Model inputs'!F22 -> 300 | H9: ='Model inputs'!G29+'Model inputs'!G21 -> 300 | I9: ='Model inputs'!G30+'Model inputs'!G22 -> 300 | J9: ='Model inputs'!H29+'Model inputs'!H21 -> 300 | K9: ='Model inputs'!H30+'Model inputs'!H22 -> 300 | L9: ='Model inputs'!I29+'Model inputs'!I21 -> 300 | M9: ='Model inputs'!I30+'Model inputs'!I22 -> 300 | N9: ='Model inputs'!J29+'Model inputs'!J21 -> 300 | O9: ='Model inputs'!J30+'Model inputs'!J22 -> 300 | P9: ='Model inputs'!K29+'Model inputs'!K21 -> 300 | Q9: ='Model inputs'!K30+'Model inputs'!K22 -> 300 | R9: ='Model inputs'!L29+'Model inputs'!L21 -> 300 | S9: ='Model inputs'!L30+'Model inputs'!L22 -> 300 | T9: ='Model inputs'!M29+'Model inputs'!M21 -> 300 | U9: ='Model inputs'!M30+'Model inputs'!M22 -> 300 | V9: ='Model inputs'!N29+'Model inputs'!N21 -> 300 | W9: ='Model inputs'!N30+'Model inputs'!N22 -> 300 | X9: ='Model inputs'!O29+'Model inputs'!O21 -> 300 | Y9: ='Model inputs'!O30+'Model inputs'!O22 -> 300 | Z9: ='Model inputs'!P29+'Model inputs'!P21 -> 300 | AA9: ='Model inputs'!P30+'Model inputs'!P22 -> 300 | AB9: ='Model inputs'!Q29+'Model inputs'!Q21 -> 300 | AC9: ='Model inputs'!Q30+'Model inputs'!Q22 -> 300 | AD9: ='Model inputs'!R29+'Model inputs'!R21 -> 300 | AE9: ='Model inputs'!R30+'Model inputs'!R22 -> 300 | AF9: ='Model inputs'!S29+'Model inputs'!S21 -> 300 | AG9: ='Model inputs'!S30+'Model inputs'!S22 -> 300 | AH9: ='Model inputs'!T29+'Model inputs'!T21 -> 300 | AI9: ='Model inputs'!T30+'Model inputs'!T22 -> 300 | AJ9: ='Model inputs'!U29+'Model inputs'!U21 -> 300 | AK9: ='Model inputs'!U30+'Model inputs'!U22 -> 300 | AL9: ='Model inputs'!V29+'Model inputs'!V21 -> 300 | AM9: ='Model inputs'!V30+'Model inputs'!V22 -> 300 | AN9: ='Model inputs'!W29+'Model inputs'!W21 -> 300 | AO9: ='Model inputs'!W30+'Model inputs'!W22 -> 300 | AP9: ='Model inputs'!X29+'Model inputs'!X21 -> 300 | AQ9: ='Model inputs'!X30+'Model inputs'!X22 -> 300 | AR9: ='Model inputs'!Y29+'Model inputs'!Y21 -> 300 | AS9: ='Model inputs'!Y30+'Model inputs'!Y22 -> 300 | AT9: ='Model inputs'!Z29+'Model inputs'!Z21 -> 300 | AU9: ='Model inputs'!Z30+'Model inputs'!Z22 -> 300 | AV9: ='Model inputs'!B29+'Model inputs'!B21 -> 300 | AW9: ='Model inputs'!B30+'Model inputs'!B22 -> 300
A10: Operating profit | B10: ='Model inputs'!D31-'Base and upside comparison'!B9 -> -144 | C10: ='Model inputs'!D32-'Base and upside comparison'!C9 -> 90 | D10: ='Model inputs'!E31-'Base and upside comparison'!D9 -> 12 | E10: ='Model inputs'!E32-'Base and upside comparison'!E9 -> 480 | F10: ='Model inputs'!F31-'Base and upside comparison'!F9 -> 168 | G10: ='Model inputs'!F32-'Base and upside comparison'!G9 -> 870 | H10: ='Model inputs'!G31-'Base and upside comparison'!H9 -> 224.16 | I10: ='Model inputs'!G32-'Base and upside comparison'!I9 -> 1127.4 | J10: ='Model inputs'!H31-'Base and upside comparison'!J9 -> 287.0592 | K10: ='Model inputs'!H32-'Base and upside comparison'!K9 -> 1441.428 | L10: ='Model inputs'!I31-'Base and upside comparison'!L9 -> 357.5063 | M10: ='Model inputs'!I32-'Base and upside comparison'!M9 -> 1824.5422 | N10: ='Model inputs'!J31-'Base and upside comparison'!N9 -> 436.40706 | O10: ='Model inputs'!J32-'Base and upside comparison'!O9 -> 2291.9414 | P10: ='Model inputs'!K31-'Base and upside comparison'!P9 -> 524.77591 | Q10: ='Model inputs'!K32-'Base and upside comparison'!Q9 -> 2862.1686 | R10: ='Model inputs'!L31-'Base and upside comparison'!R9 -> 623.74902 | S10: ='Model inputs'!L32-'Base and upside comparison'!S9 -> 3557.8456 | T10: ='Model inputs'!M31-'Base and upside comparison'!T9 -> 734.5989 | U10: ='Model inputs'!M32-'Base and upside comparison'!U9 -> 4406.5717 | V10: ='Model inputs'!N31-'Base and upside comparison'!V9 -> 858.75077 | W10: ='Model inputs'!N32-'Base and upside comparison'!W9 -> 5442.0174 | X10: ='Model inputs'!O31-'Base and upside comparison'!X9 -> 997.80086 | Y10: ='Model inputs'!O32-'Base and upside comparison'!Y9 -> 6705.2613 | Z10: ='Model inputs'!P31-'Base and upside comparison'!Z9 -> 1153.537 | AA10: ='Model inputs'!P32-'Base and upside comparison'!AA9 -> 8246.4188 | AB10: ='Model inputs'!Q31-'Base and upside comparison'!AB9 -> 1327.9614 | AC10: ='Model inputs'!Q32-'Base and upside comparison'!AC9 -> 10126.631 | AD10: ='Model inputs'!R31-'Base and upside comparison'!AD9 -> 1523.3168 | AE10: ='Model inputs'!R32-'Base and upside comparison'!AE9 -> 12420.49 | AF10: ='Model inputs'!S31-'Base and upside comparison'!AF9 -> 1742.1148 | AG10: ='Model inputs'!S32-'Base and upside comparison'!AG9 -> 15218.997 | AH10: ='Model inputs'!T31-'Base and upside comparison'!AH9 -> 1987.1685 | AI10: ='Model inputs'!T32-'Base and upside comparison'!AI9 -> 18633.177 | AJ10: ='Model inputs'!U31-'Base and upside comparison'!AJ9 -> 2261.6288 | AK10: ='Model inputs'!U32-'Base and upside comparison'!AK9 -> 22798.476 | AL10: ='Model inputs'!V31-'Base and upside comparison'!AL9 -> 2569.0242 | AM10: ='Model inputs'!V32-'Base and upside comparison'!AM9 -> 27880.14 | AN10: ='Model inputs'!W31-'Base and upside comparison'!AN9 -> 2913.3071 | AO10: ='Model inputs'!W32-'Base and upside comparison'!AO9 -> 34079.771 | AP10: ='Model inputs'!X31-'Base and upside comparison'!AP9 -> 3298.904 | AQ10: ='Model inputs'!X32-'Base and upside comparison'!AQ9 -> 41643.321 | AR10: ='Model inputs'!Y31-'Base and upside comparison'!AR9 -> 3730.7725 | AS10: ='Model inputs'!Y32-'Base and upside comparison'!AS9 -> 50870.852 | AT10: ='Model inputs'!Z31-'Base and upside comparison'!AT9 -> 4214.4652 | AU10: ='Model inputs'!Z32-'Base and upside comparison'!AU9 -> 62128.439 | AV10: ='Model inputs'!B31-'Base and upside comparison'!AV9 -> 4756.201 | AW10: ='Model inputs'!B32-'Base and upside comparison'!AW9 -> 75862.696
A11: Monthly burn | B11: =MAX(0,-'Model inputs'!D42) -> 144 | C11: =MAX(0,-'Model inputs'!D43) -> 0 | D11: =MAX(0,-'Model inputs'!E42) -> 0 | E11: =MAX(0,-'Model inputs'!E43) -> 0 | F11: =MAX(0,-'Model inputs'!F42) -> 0 | G11: =MAX(0,-'Model inputs'!F43) -> 0 | H11: =MAX(0,-'Model inputs'!G42) -> 0 | I11: =MAX(0,-'Model inputs'!G43) -> 0 | J11: =MAX(0,-'Model inputs'!H42) -> 0 | K11: =MAX(0,-'Model inputs'!H43) -> 0 | L11: =MAX(0,-'Model inputs'!I42) -> 0 | M11: =MAX(0,-'Model inputs'!I43) -> 0 | N11: =MAX(0,-'Model inputs'!J42) -> 0 | O11: =MAX(0,-'Model inputs'!J43) -> 0 | P11: =MAX(0,-'Model inputs'!K42) -> 0 | Q11: =MAX(0,-'Model inputs'!K43) -> 0 | R11: =MAX(0,-'Model inputs'!L42) -> 0 | S11: =MAX(0,-'Model inputs'!L43) -> 0 | T11: =MAX(0,-'Model inputs'!M42) -> 0 | U11: =MAX(0,-'Model inputs'!M43) -> 0 | V11: =MAX(0,-'Model inputs'!N42) -> 0 | W11: =MAX(0,-'Model inputs'!N43) -> 0 | X11: =MAX(0,-'Model inputs'!O42) -> 0 | Y11: =MAX(0,-'Model inputs'!O43) -> 0 | Z11: =MAX(0,-'Model inputs'!P42) -> 0 | AA11: =MAX(0,-'Model inputs'!P43) -> 0 | AB11: =MAX(0,-'Model inputs'!Q42) -> 0 | AC11: =MAX(0,-'Model inputs'!Q43) -> 0 | AD11: =MAX(0,-'Model inputs'!R42) -> 0 | AE11: =MAX(0,-'Model inputs'!R43) -> 0 | AF11: =MAX(0,-'Model inputs'!S42) -> 0 | AG11: =MAX(0,-'Model inputs'!S43) -> 0 | AH11: =MAX(0,-'Model inputs'!T42) -> 0 | AI11: =MAX(0,-'Model inputs'!T43) -> 0 | AJ11: =MAX(0,-'Model inputs'!U42) -> 0 | AK11: =MAX(0,-'Model inputs'!U43) -> 0 | AL11: =MAX(0,-'Model inputs'!V42) -> 0 | AM11: =MAX(0,-'Model inputs'!V43) -> 0 | AN11: =MAX(0,-'Model inputs'!W42) -> 0 | AO11: =MAX(0,-'Model inputs'!W43) -> 0 | AP11: =MAX(0,-'Model inputs'!X42) -> 0 | AQ11: =MAX(0,-'Model inputs'!X43) -> 0 | AR11: =MAX(0,-'Model inputs'!Y42) -> 0 | AS11: =MAX(0,-'Model inputs'!Y43) -> 0 | AT11: =MAX(0,-'Model inputs'!Z42) -> 0 | AU11: =MAX(0,-'Model inputs'!Z43) -> 0 | AV11: =MAX(0,-'Model inputs'!B42) -> 0 | AW11: =MAX(0,-'Model inputs'!B43) -> 0
A12: Unfunded cash | B12: =IF(IF(IF(IF(ISERROR('Model inputs'!D23=1),'Model inputs'!D23=1,IF('Model inputs'!D23="","",'Model inputs'!D23=1))="",FALSE,IF(ISERROR('Model inputs'!D23=1),'Model inputs'!D23=1,IF('Model inputs'!D23="","",'Model inputs'!D23=1))),IF('Model inputs'!AB64="","",'Model inputs'!AB64),IF('Model inputs'!AA68="","",'Model inputs'!AA68))="",0,IF(IF(IF(ISERROR('Model inputs'!D23=1),'Model inputs'!D23=1,IF('Model inputs'!D23="","",'Model inputs'!D23=1))="",FALSE,IF(ISERROR('Model inputs'!D23=1),'Model inputs'!D23=1,IF('Model inputs'!D23="","",'Model inputs'!D23=1))),IF('Model inputs'!AB64="","",'Model inputs'!AB64),IF('Model inputs'!AA68="","",'Model inputs'!AA68)))+'Model inputs'!D42 -> -144 | C12: =IF(IF(IF(IF(ISERROR('Model inputs'!D24=1),'Model inputs'!D24=1,IF('Model inputs'!D24="","",'Model inputs'!D24=1))="",FALSE,IF(ISERROR('Model inputs'!D24=1),'Model inputs'!D24=1,IF('Model inputs'!D24="","",'Model inputs'!D24=1))),IF('Model inputs'!AB65="","",'Model inputs'!AB65),IF('Model inputs'!AA69="","",'Model inputs'!AA69))="",0,IF(IF(IF(ISERROR('Model inputs'!D24=1),'Model inputs'!D24=1,IF('Model inputs'!D24="","",'Model inputs'!D24=1))="",FALSE,IF(ISERROR('Model inputs'!D24=1),'Model inputs'!D24=1,IF('Model inputs'!D24="","",'Model inputs'!D24=1))),IF('Model inputs'!AB65="","",'Model inputs'!AB65),IF('Model inputs'!AA69="","",'Model inputs'!AA69)))+'Model inputs'!D43 -> 90 | D12: =IF(IF(IF(IF(ISERROR('Model inputs'!E23=1),'Model inputs'!E23=1,IF('Model inputs'!E23="","",'Model inputs'!E23=1))="",FALSE,IF(ISERROR('Model inputs'!E23=1),'Model inputs'!E23=1,IF('Model inputs'!E23="","",'Model inputs'!E23=1))),IF('Model inputs'!AB64="","",'Model inputs'!AB64),IF('Base and upside comparison'!B12="","",'Base and upside comparison'!B12))="",0,IF(IF(IF(ISERROR('Model inputs'!E23=1),'Model inputs'!E23=1,IF('Model inputs'!E23="","",'Model inputs'!E23=1))="",FALSE,IF(ISERROR('Model inputs'!E23=1),'Model inputs'!E23=1,IF('Model inputs'!E23="","",'Model inputs'!E23=1))),IF('Model inputs'!AB64="","",'Model inputs'!AB64),IF('Base and upside comparison'!B12="","",'Base and upside comparison'!B12)))+'Model inputs'!E42 -> -132 | E12: =IF(IF(IF(IF(ISERROR('Model inputs'!E24=1),'Model inputs'!E24=1,IF('Model inputs'!E24="","",'Model inputs'!E24=1))="",FALSE,IF(ISERROR('Model inputs'!E24=1),'Model inputs'!E24=1,IF('Model inputs'!E24="","",'Model inputs'!E24=1))),IF('Model inputs'!AB65="","",'Model inputs'!AB65),IF('Base and upside comparison'!C12="","",'Base and upside comparison'!C12))="",0,IF(IF(IF(ISERROR('Model inputs'!E24=1),'Model inputs'!E24=1,IF('Model inputs'!E24="","",'Model inputs'!E24=1))="",FALSE,IF(ISERROR('Model inputs'!E24=1),'Model inputs'!E24=1,IF('Model inputs'!E24="","",'Model inputs'!E24=1))),IF('Model inputs'!AB65="","",'Model inputs'!AB65),IF('Base and upside comparison'!C12="","",'Base and upside comparison'!C12)))+'Model inputs'!E43 -> 570 | F12: =IF(IF(IF(IF(ISERROR('Model inputs'!F23=1),'Model inputs'!F23=1,IF('Model inputs'!F23="","",'Model inputs'!F23=1))="",FALSE,IF(ISERROR('Model inputs'!F23=1),'Model inputs'!F23=1,IF('Model inputs'!F23="","",'Model inputs'!F23=1))),IF('Model inputs'!AB64="","",'Model inputs'!AB64),IF('Base and upside comparison'!D12="","",'Base and upside comparison'!D12))="",0,IF(IF(IF(ISERROR('Model inputs'!F23=1),'Model inputs'!F23=1,IF('Model inputs'!F23="","",'Model inputs'!F23=1))="",FALSE,IF(ISERROR('Model inputs'!F23=1),'Model inputs'!F23=1,IF('Model inputs'!F23="","",'Model inputs'!F23=1))),IF('Model inputs'!AB64="","",'Model inputs'!AB64),IF('Base and upside comparison'!D12="","",'Base and upside comparison'!D12)))+'Model inputs'!F42 -> 36 | G12: =IF(IF(IF(IF(ISERROR('Model inputs'!F24=1),'Model inputs'!F24=1,IF('Model inputs'!F24="","",'Model inputs'!F24=1))="",FALSE,IF(ISERROR('Model inputs'!F24=1),'Model inputs'!F24=1,IF('Model inputs'!F24="","",'Model inputs'!F24=1))),IF('Model inputs'!AB65="","",'Model inputs'!AB65),IF('Base and upside comparison'!E12="","",'Base and upside comparison'!E12))="",0,IF(IF(IF(ISERROR('Model inputs'!F24=1),'Model inputs'!F24=1,IF('Model inputs'!F24="","",'Model inputs'!F24=1))="",FALSE,IF(ISERROR('Model inputs'!F24=1),'Model inputs'!F24=1,IF('Model inputs'!F24="","",'Model inputs'!F24=1))),IF('Model inputs'!AB65="","",'Model inputs'!AB65),IF('Base and upside comparison'!E12="","",'Base and upside comparison'!E12)))+'Model inputs'!F43 -> 1440 | H12: =IF(IF(IF(IF(ISERROR('Model inputs'!G23=1),'Model inputs'!G23=1,IF('Model inputs'!G23="","",'Model inputs'!G23=1))="",FALSE,IF(ISERROR('Model inputs'!G23=1),'Model inputs'!G23=1,IF('Model inputs'!G23="","",'Model inputs'!G23=1))),IF('Model inputs'!AB64="","",'Model inputs'!AB64),IF('Base and upside comparison'!F12="","",'Base and upside comparison'!F12))="",0,IF(IF(IF(ISERROR('Model inputs'!G23=1),'Model inputs'!G23=1,IF('Model inputs'!G23="","",'Model inputs'!G23=1))="",FALSE,IF(ISERROR('Model inputs'!G23=1),'Model inputs'!G23=1,IF('Model inputs'!G23="","",'Model inputs'!G23=1))),IF('Model inputs'!AB64="","",'Model inputs'!AB64),IF('Base and upside comparison'!F12="","",'Base and upside comparison'!F12)))+'Model inputs'!G42 -> 260.16 | I12: =IF(IF(IF(IF(ISERROR('Model inputs'!G24=1),'Model inputs'!G24=1,IF('Model inputs'!G24="","",'Model inputs'!G24=1))="",FALSE,IF(ISERROR('Model inputs'!G24=1),'Model inputs'!G24=1,IF('Model inputs'!G24="","",'Model inputs'!G24=1))),IF('Model inputs'!AB65="","",'Model inputs'!AB65),IF('Base and upside comparison'!G12="","",'Base and upside comparison'!G12))="",0,IF(IF(IF(ISERROR('Model inputs'!G24=1),'Model inputs'!G24=1,IF('Model inputs'!G24="","",'Model inputs'!G24=1))="",FALSE,IF(ISERROR('Model inputs'!G24=1),'Model inputs'!G24=1,IF('Model inputs'!G24="","",'Model inputs'!G24=1))),IF('Model inputs'!AB65="","",'Model inputs'!AB65),IF('Base and upside comparison'!G12="","",'Base and upside comparison'!G12)))+'Model inputs'!G43 -> 2567.4 | J12: =IF(IF(IF(IF(ISERROR('Model inputs'!H23=1),'Model inputs'!H23=1,IF('Model inputs'!H23="","",'Model inputs'!H23=1))="",FALSE,IF(ISERROR('Model inputs'!H23=1),'Model inputs'!H23=1,IF('Model inputs'!H23="","",'Model inputs'!H23=1))),IF('Model inputs'!AB64="","",'Model inputs'!AB64),IF('Base and upside comparison'!H12="","",'Base and upside comparison'!H12))="",0,IF(IF(IF(ISERROR('Model inputs'!H23=1),'Model inputs'!H23=1,IF('Model inputs'!H23="","",'Model inputs'!H23=1))="",FALSE,IF(ISERROR('Model inputs'!H23=1),'Model inputs'!H23=1,IF('Model inputs'!H23="","",'Model inputs'!H23=1))),IF('Model inputs'!AB64="","",'Model inputs'!AB64),IF('Base and upside comparison'!H12="","",'Base and upside comparison'!H12)))+'Model inputs'!H42 -> 547.2192 | K12: =IF(IF(IF(IF(ISERROR('Model inputs'!H24=1),'Model inputs'!H24=1,IF('Model inputs'!H24="","",'Model inputs'!H24=1))="",FALSE,IF(ISERROR('Model inputs'!H24=1),'Model inputs'!H24=1,IF('Model inputs'!H24="","",'Model inputs'!H24=1))),IF('Model inputs'!AB65="","",'Model inputs'!AB65),IF('Base and upside comparison'!I12="","",'Base and upside comparison'!I12))="",0,IF(IF(IF(ISERROR('Model inputs'!H24=1),'Model inputs'!H24=1,IF('Model inputs'!H24="","",'Model inputs'!H24=1))="",FALSE,IF(ISERROR('Model inputs'!H24=1),'Model inputs'!H24=1,IF('Model inputs'!H24="","",'Model inputs'!H24=1))),IF('Model inputs'!AB65="","",'Model inputs'!AB65),IF('Base and upside comparison'!I12="","",'Base and upside comparison'!I12)))+'Model inputs'!H43 -> 4008.828 | L12: =IF(IF(IF(IF(ISERROR('Model inputs'!I23=1),'Model inputs'!I23=1,IF('Model inputs'!I23="","",'Model inputs'!I23=1))="",FALSE,IF(ISERROR('Model inputs'!I23=1),'Model inputs'!I23=1,IF('Model inputs'!I23="","",'Model inputs'!I23=1))),IF('Model inputs'!AB64="","",'Model inputs'!AB64),IF('Base and upside comparison'!J12="","",'Base and upside comparison'!J12))="",0,IF(IF(IF(ISERROR('Model inputs'!I23=1),'Model inputs'!I23=1,IF('Model inputs'!I23="","",'Model inputs'!I23=1))="",FALSE,IF(ISERROR('Model inputs'!I23=1),'Model inputs'!I23=1,IF('Model inputs'!I23="","",'Model inputs'!I23=1))),IF('Model inputs'!AB64="","",'Model inputs'!AB64),IF('Base and upside comparison'!J12="","",'Base and upside comparison'!J12)))+'Model inputs'!I42 -> 904.7255 | M12: =IF(IF(IF(IF(ISERROR('Model inputs'!I24=1),'Model inputs'!I24=1,IF('Model inputs'!I24="","",'Model inputs'!I24=1))="",FALSE,IF(ISERROR('Model inputs'!I24=1),'Model inputs'!I24=1,IF('Model inputs'!I24="","",'Model inputs'!I24=1))),IF('Model inputs'!AB65="","",'Model inputs'!AB65),IF('Base and upside comparison'!K12="","",'Base and upside comparison'!K12))="",0,IF(IF(IF(ISERROR('Model inputs'!I24=1),'Model inputs'!I24=1,IF('Model inputs'!I24="","",'Model inputs'!I24=1))="",FALSE,IF(ISERROR('Model inputs'!I24=1),'Model inputs'!I24=1,IF('Model inputs'!I24="","",'Model inputs'!I24=1))),IF('Model inputs'!AB65="","",'Model inputs'!AB65),IF('Base and upside comparison'!K12="","",'Base and upside comparison'!K12)))+'Model inputs'!I43 -> 5833.3702 | N12: =IF(IF(IF(IF(ISERROR('Model inputs'!J23=1),'Model inputs'!J23=1,IF('Model inputs'!J23="","",'Model inputs'!J23=1))="",FALSE,IF(ISERROR('Model inputs'!J23=1),'Model inputs'!J23=1,IF('Model inputs'!J23="","",'Model inputs'!J23=1))),IF('Model inputs'!AB64="","",'Model inputs'!AB64),IF('Base and upside comparison'!L12="","",'Base and upside comparison'!L12))="",0,IF(IF(IF(ISERROR('Model inputs'!J23=1),'Model inputs'!J23=1,IF('Model inputs'!J23="","",'Model inputs'!J23=1))="",FALSE,IF(ISERROR('Model inputs'!J23=1),'Model inputs'!J23=1,IF('Model inputs'!J23="","",'Model inputs'!J23=1))),IF('Model inputs'!AB64="","",'Model inputs'!AB64),IF('Base and upside comparison'!L12="","",'Base and upside comparison'!L12)))+'Model inputs'!J42 -> 1341.1326 | O12: =IF(IF(IF(IF(ISERROR('Model inputs'!J24=1),'Model inputs'!J24=1,IF('Model inputs'!J24="","",'Model inputs'!J24=1))="",FALSE,IF(ISERROR('Model inputs'!J24=1),'Model inputs'!J24=1,IF('Model inputs'!J24="","",'Model inputs'!J24=1))),IF('Model inputs'!AB65="","",'Model inputs'!AB65),IF('Base and upside comparison'!M12="","",'Base and upside comparison'!M12))="",0,IF(IF(IF(ISERROR('Model inputs'!J24=1),'Model inputs'!J24=1,IF('Model inputs'!J24="","",'Model inputs'!J24=1))="",FALSE,IF(ISERROR('Model inputs'!J24=1),'Model inputs'!J24=1,IF('Model inputs'!J24="","",'Model inputs'!J24=1))),IF('Model inputs'!AB65="","",'Model inputs'!AB65),IF('Base and upside comparison'!M12="","",'Base and upside comparison'!M12)))+'Model inputs'!J43 -> 8125.3116 | P12: =IF(IF(IF(IF(ISERROR('Model inputs'!K23=1),'Model inputs'!K23=1,IF('Model inputs'!K23="","",'Model inputs'!K23=1))="",FALSE,IF(ISERROR('Model inputs'!K23=1),'Model inputs'!K23=1,IF('Model inputs'!K23="","",'Model inputs'!K23=1))),IF('Model inputs'!AB64="","",'Model inputs'!AB64),IF('Base and upside comparison'!N12="","",'Base and upside comparison'!N12))="",0,IF(IF(IF(ISERROR('Model inputs'!K23=1),'Model inputs'!K23=1,IF('Model inputs'!K23="","",'Model inputs'!K23=1))="",FALSE,IF(ISERROR('Model inputs'!K23=1),'Model inputs'!K23=1,IF('Model inputs'!K23="","",'Model inputs'!K23=1))),IF('Model inputs'!AB64="","",'Model inputs'!AB64),IF('Base and upside comparison'!N12="","",'Base and upside comparison'!N12)))+'Model inputs'!K42 -> 1865.9085 | Q12: =IF(IF(IF(IF(ISERROR('Model inputs'!K24=1),'Model inputs'!K24=1,IF('Model inputs'!K24="","",'Model inputs'!K24=1))="",FALSE,IF(ISERROR('Model inputs'!K24=1),'Model inputs'!K24=1,IF('Model inputs'!K24="","",'Model inputs'!K24=1))),IF('Model inputs'!AB65="","",'Model inputs'!AB65),IF('Base and upside comparison'!O12="","",'Base and upside comparison'!O12))="",0,IF(IF(IF(ISERROR('Model inputs'!K24=1),'Model inputs'!K24=1,IF('Model inputs'!K24="","",'Model inputs'!K24=1))="",FALSE,IF(ISERROR('Model inputs'!K24=1),'Model inputs'!K24=1,IF('Model inputs'!K24="","",'Model inputs'!K24=1))),IF('Model inputs'!AB65="","",'Model inputs'!AB65),IF('Base and upside comparison'!O12="","",'Base and upside comparison'!O12)))+'Model inputs'!K43 -> 10987.48 | R12: =IF(IF(IF(IF(ISERROR('Model inputs'!L23=1),'Model inputs'!L23=1,IF('Model inputs'!L23="","",'Model inputs'!L23=1))="",FALSE,IF(ISERROR('Model inputs'!L23=1),'Model inputs'!L23=1,IF('Model inputs'!L23="","",'Model inputs'!L23=1))),IF('Model inputs'!AB64="","",'Model inputs'!AB64),IF('Base and upside comparison'!P12="","",'Base and upside comparison'!P12))="",0,IF(IF(IF(ISERROR('Model inputs'!L23=1),'Model inputs'!L23=1,IF('Model inputs'!L23="","",'Model inputs'!L23=1))="",FALSE,IF(ISERROR('Model inputs'!L23=1),'Model inputs'!L23=1,IF('Model inputs'!L23="","",'Model inputs'!L23=1))),IF('Model inputs'!AB64="","",'Model inputs'!AB64),IF('Base and upside comparison'!P12="","",'Base and upside comparison'!P12)))+'Model inputs'!L42 -> 2489.6575 | S12: =IF(IF(IF(IF(ISERROR('Model inputs'!L24=1),'Model inputs'!L24=1,IF('Model inputs'!L24="","",'Model inputs'!L24=1))="",FALSE,IF(ISERROR('Model inputs'!L24=1),'Model inputs'!L24=1,IF('Model inputs'!L24="","",'Model inputs'!L24=1))),IF('Model inputs'!AB65="","",'Model inputs'!AB65),IF('Base and upside comparison'!Q12="","",'Base and upside comparison'!Q12))="",0,IF(IF(IF(ISERROR('Model inputs'!L24=1),'Model inputs'!L24=1,IF('Model inputs'!L24="","",'Model inputs'!L24=1))="",FALSE,IF(ISERROR('Model inputs'!L24=1),'Model inputs'!L24=1,IF('Model inputs'!L24="","",'Model inputs'!L24=1))),IF('Model inputs'!AB65="","",'Model inputs'!AB65),IF('Base and upside comparison'!Q12="","",'Base and upside comparison'!Q12)))+'Model inputs'!L43 -> 14545.326 | T12: =IF(IF(IF(IF(ISERROR('Model inputs'!M23=1),'Model inputs'!M23=1,IF('Model inputs'!M23="","",'Model inputs'!M23=1))="",FALSE,IF(ISERROR('Model inputs'!M23=1),'Model inputs'!M23=1,IF('Model inputs'!M23="","",'Model inputs'!M23=1))),IF('Model inputs'!AB64="","",'Model inputs'!AB64),IF('Base and upside comparison'!R12="","",'Base and upside comparison'!R12))="",0,IF(IF(IF(ISERROR('Model inputs'!M23=1),'Model inputs'!M23=1,IF('Model inputs'!M23="","",'Model inputs'!M23=1))="",FALSE,IF(ISERROR('Model inputs'!M23=1),'Model inputs'!M23=1,IF('Model inputs'!M23="","",'Model inputs'!M23=1))),IF('Model inputs'!AB64="","",'Model inputs'!AB64),IF('Base and upside comparison'!R12="","",'Base and upside comparison'!R12)))+'Model inputs'!M42 -> 3224.2564 | U12: =IF(IF(IF(IF(ISERROR('Model inputs'!M24=1),'Model inputs'!M24=1,IF('Model inputs'!M24="","",'Model inputs'!M24=1))="",FALSE,IF(ISERROR('Model inputs'!M24=1),'Model inputs'!M24=1,IF('Model inputs'!M24="","",'Model inputs'!M24=1))),IF('Model inputs'!AB65="","",'Model inputs'!AB65),IF('Base and upside comparison'!S12="","",'Base and upside comparison'!S12))="",0,IF(IF(IF(ISERROR('Model inputs'!M24=1),'Model inputs'!M24=1,IF('Model inputs'!M24="","",'Model inputs'!M24=1))="",FALSE,IF(ISERROR('Model inputs'!M24=1),'Model inputs'!M24=1,IF('Model inputs'!M24="","",'Model inputs'!M24=1))),IF('Model inputs'!AB65="","",'Model inputs'!AB65),IF('Base and upside comparison'!S12="","",'Base and upside comparison'!S12)))+'Model inputs'!M43 -> 18951.897 | V12: =IF(IF(IF(IF(ISERROR('Model inputs'!N23=1),'Model inputs'!N23=1,IF('Model inputs'!N23="","",'Model inputs'!N23=1))="",FALSE,IF(ISERROR('Model inputs'!N23=1),'Model inputs'!N23=1,IF('Model inputs'!N23="","",'Model inputs'!N23=1))),IF('Model inputs'!AB64="","",'Model inputs'!AB64),IF('Base and upside comparison'!T12="","",'Base and upside comparison'!T12))="",0,IF(IF(IF(ISERROR('Model inputs'!N23=1),'Model inputs'!N23=1,IF('Model inputs'!N23="","",'Model inputs'!N23=1))="",FALSE,IF(ISERROR('Model inputs'!N23=1),'Model inputs'!N23=1,IF('Model inputs'!N23="","",'Model inputs'!N23=1))),IF('Model inputs'!AB64="","",'Model inputs'!AB64),IF('Base and upside comparison'!T12="","",'Base and upside comparison'!T12)))+'Model inputs'!N42 -> 4083.0072 | W12: =IF(IF(IF(IF(ISERROR('Model inputs'!N24=1),'Model inputs'!N24=1,IF('Model inputs'!N24="","",'Model inputs'!N24=1))="",FALSE,IF(ISERROR('Model inputs'!N24=1),'Model inputs'!N24=1,IF('Model inputs'!N24="","",'Model inputs'!N24=1))),IF('Model inputs'!AB65="","",'Model inputs'!AB65),IF('Base and upside comparison'!U12="","",'Base and upside comparison'!U12))="",0,IF(IF(IF(ISERROR('Model inputs'!N24=1),'Model inputs'!N24=1,IF('Model inputs'!N24="","",'Model inputs'!N24=1))="",FALSE,IF(ISERROR('Model inputs'!N24=1),'Model inputs'!N24=1,IF('Model inputs'!N24="","",'Model inputs'!N24=1))),IF('Model inputs'!AB65="","",'Model inputs'!AB65),IF('Base and upside comparison'!U12="","",'Base and upside comparison'!U12)))+'Model inputs'!N43 -> 24393.915 | X12: =IF(IF(IF(IF(ISERROR('Model inputs'!O23=1),'Model inputs'!O23=1,IF('Model inputs'!O23="","",'Model inputs'!O23=1))="",FALSE,IF(ISERROR('Model inputs'!O23=1),'Model inputs'!O23=1,IF('Model inputs'!O23="","",'Model inputs'!O23=1))),IF('Model inputs'!AB64="","",'Model inputs'!AB64),IF('Base and upside comparison'!V12="","",'Base and upside comparison'!V12))="",0,IF(IF(IF(ISERROR('Model inputs'!O23=1),'Model inputs'!O23=1,IF('Model inputs'!O23="","",'Model inputs'!O23=1))="",FALSE,IF(ISERROR('Model inputs'!O23=1),'Model inputs'!O23=1,IF('Model inputs'!O23="","",'Model inputs'!O23=1))),IF('Model inputs'!AB64="","",'Model inputs'!AB64),IF('Base and upside comparison'!V12="","",'Base and upside comparison'!V12)))+'Model inputs'!O42 -> 5080.808 | Y12: =IF(IF(IF(IF(ISERROR('Model inputs'!O24=1),'Model inputs'!O24=1,IF('Model inputs'!O24="","",'Model inputs'!O24=1))="",FALSE,IF(ISERROR('Model inputs'!O24=1),'Model inputs'!O24=1,IF('Model inputs'!O24="","",'Model inputs'!O24=1))),IF('Model inputs'!AB65="","",'Model inputs'!AB65),IF('Base and upside comparison'!W12="","",'Base and upside comparison'!W12))="",0,IF(IF(IF(ISERROR('Model inputs'!O24=1),'Model inputs'!O24=1,IF('Model inputs'!O24="","",'Model inputs'!O24=1))="",FALSE,IF(ISERROR('Model inputs'!O24=1),'Model inputs'!O24=1,IF('Model inputs'!O24="","",'Model inputs'!O24=1))),IF('Model inputs'!AB65="","",'Model inputs'!AB65),IF('Base and upside comparison'!W12="","",'Base and upside comparison'!W12)))+'Model inputs'!O43 -> 31099.176 | Z12: =IF(IF(IF(IF(ISERROR('Model inputs'!P23=1),'Model inputs'!P23=1,IF('Model inputs'!P23="","",'Model inputs'!P23=1))="",FALSE,IF(ISERROR('Model inputs'!P23=1),'Model inputs'!P23=1,IF('Model inputs'!P23="","",'Model inputs'!P23=1))),IF('Model inputs'!AB64="","",'Model inputs'!AB64),IF('Base and upside comparison'!X12="","",'Base and upside comparison'!X12))="",0,IF(IF(IF(ISERROR('Model inputs'!P23=1),'Model inputs'!P23=1,IF('Model inputs'!P23="","",'Model inputs'!P23=1))="",FALSE,IF(ISERROR('Model inputs'!P23=1),'Model inputs'!P23=1,IF('Model inputs'!P23="","",'Model inputs'!P23=1))),IF('Model inputs'!AB64="","",'Model inputs'!AB64),IF('Base and upside comparison'!X12="","",'Base and upside comparison'!X12)))+'Model inputs'!P42 -> 6234.345 | AA12: =IF(IF(IF(IF(ISERROR('Model inputs'!P24=1),'Model inputs'!P24=1,IF('Model inputs'!P24="","",'Model inputs'!P24=1))="",FALSE,IF(ISERROR('Model inputs'!P24=1),'Model inputs'!P24=1,IF('Model inputs'!P24="","",'Model inputs'!P24=1))),IF('Model inputs'!AB65="","",'Model inputs'!AB65),IF('Base and upside comparison'!Y12="","",'Base and upside comparison'!Y12))="",0,IF(IF(IF(ISERROR('Model inputs'!P24=1),'Model inputs'!P24=1,IF('Model inputs'!P24="","",'Model inputs'!P24=1))="",FALSE,IF(ISERROR('Model inputs'!P24=1),'Model inputs'!P24=1,IF('Model inputs'!P24="","",'Model inputs'!P24=1))),IF('Model inputs'!AB65="","",'Model inputs'!AB65),IF('Base and upside comparison'!Y12="","",'Base and upside comparison'!Y12)))+'Model inputs'!P43 -> 39345.595 | AB12: =IF(IF(IF(IF(ISERROR('Model inputs'!Q23=1),'Model inputs'!Q23=1,IF('Model inputs'!Q23="","",'Model inputs'!Q23=1))="",FALSE,IF(ISERROR('Model inputs'!Q23=1),'Model inputs'!Q23=1,IF('Model inputs'!Q23="","",'Model inputs'!Q23=1))),IF('Model inputs'!AB64="","",'Model inputs'!AB64),IF('Base and upside comparison'!Z12="","",'Base and upside comparison'!Z12))="",0,IF(IF(IF(ISERROR('Model inputs'!Q23=1),'Model inputs'!Q23=1,IF('Model inputs'!Q23="","",'Model inputs'!Q23=1))="",FALSE,IF(ISERROR('Model inputs'!Q23=1),'Model inputs'!Q23=1,IF('Model inputs'!Q23="","",'Model inputs'!Q23=1))),IF('Model inputs'!AB64="","",'Model inputs'!AB64),IF('Base and upside comparison'!Z12="","",'Base and upside comparison'!Z12)))+'Model inputs'!Q42 -> 7562.3064 | AC12: =IF(IF(IF(IF(ISERROR('Model inputs'!Q24=1),'Model inputs'!Q24=1,IF('Model inputs'!Q24="","",'Model inputs'!Q24=1))="",FALSE,IF(ISERROR('Model inputs'!Q24=1),'Model inputs'!Q24=1,IF('Model inputs'!Q24="","",'Model inputs'!Q24=1))),IF('Model inputs'!AB65="","",'Model inputs'!AB65),IF('Base and upside comparison'!AA12="","",'Base and upside comparison'!AA12))="",0,IF(IF(IF(ISERROR('Model inputs'!Q24=1),'Model inputs'!Q24=1,IF('Model inputs'!Q24="","",'Model inputs'!Q24=1))="",FALSE,IF(ISERROR('Model inputs'!Q24=1),'Model inputs'!Q24=1,IF('Model inputs'!Q24="","",'Model inputs'!Q24=1))),IF('Model inputs'!AB65="","",'Model inputs'!AB65),IF('Base and upside comparison'!AA12="","",'Base and upside comparison'!AA12)))+'Model inputs'!Q43 -> 49472.226 | AD12: =IF(IF(IF(IF(ISERROR('Model inputs'!R23=1),'Model inputs'!R23=1,IF('Model inputs'!R23="","",'Model inputs'!R23=1))="",FALSE,IF(ISERROR('Model inputs'!R23=1),'Model inputs'!R23=1,IF('Model inputs'!R23="","",'Model inputs'!R23=1))),IF('Model inputs'!AB64="","",'Model inputs'!AB64),IF('Base and upside comparison'!AB12="","",'Base and upside comparison'!AB12))="",0,IF(IF(IF(ISERROR('Model inputs'!R23=1),'Model inputs'!R23=1,IF('Model inputs'!R23="","",'Model inputs'!R23=1))="",FALSE,IF(ISERROR('Model inputs'!R23=1),'Model inputs'!R23=1,IF('Model inputs'!R23="","",'Model inputs'!R23=1))),IF('Model inputs'!AB64="","",'Model inputs'!AB64),IF('Base and upside comparison'!AB12="","",'Base and upside comparison'!AB12)))+'Model inputs'!R42 -> 9085.6231 | AE12: =IF(IF(IF(IF(ISERROR('Model inputs'!R24=1),'Model inputs'!R24=1,IF('Model inputs'!R24="","",'Model inputs'!R24=1))="",FALSE,IF(ISERROR('Model inputs'!R24=1),'Model inputs'!R24=1,IF('Model inputs'!R24="","",'Model inputs'!R24=1))),IF('Model inputs'!AB65="","",'Model inputs'!AB65),IF('Base and upside comparison'!AC12="","",'Base and upside comparison'!AC12))="",0,IF(IF(IF(ISERROR('Model inputs'!R24=1),'Model inputs'!R24=1,IF('Model inputs'!R24="","",'Model inputs'!R24=1))="",FALSE,IF(ISERROR('Model inputs'!R24=1),'Model inputs'!R24=1,IF('Model inputs'!R24="","",'Model inputs'!R24=1))),IF('Model inputs'!AB65="","",'Model inputs'!AB65),IF('Base and upside comparison'!AC12="","",'Base and upside comparison'!AC12)))+'Model inputs'!R43 -> 61892.715 | AF12: =IF(IF(IF(IF(ISERROR('Model inputs'!S23=1),'Model inputs'!S23=1,IF('Model inputs'!S23="","",'Model inputs'!S23=1))="",FALSE,IF(ISERROR('Model inputs'!S23=1),'Model inputs'!S23=1,IF('Model inputs'!S23="","",'Model inputs'!S23=1))),IF('Model inputs'!AB64="","",'Model inputs'!AB64),IF('Base and upside comparison'!AD12="","",'Base and upside comparison'!AD12))="",0,IF(IF(IF(ISERROR('Model inputs'!S23=1),'Model inputs'!S23=1,IF('Model inputs'!S23="","",'Model inputs'!S23=1))="",FALSE,IF(ISERROR('Model inputs'!S23=1),'Model inputs'!S23=1,IF('Model inputs'!S23="","",'Model inputs'!S23=1))),IF('Model inputs'!AB64="","",'Model inputs'!AB64),IF('Base and upside comparison'!AD12="","",'Base and upside comparison'!AD12)))+'Model inputs'!S42 -> 10827.738 | AG12: =IF(IF(IF(IF(ISERROR('Model inputs'!S24=1),'Model inputs'!S24=1,IF('Model inputs'!S24="","",'Model inputs'!S24=1))="",FALSE,IF(ISERROR('Model inputs'!S24=1),'Model inputs'!S24=1,IF('Model inputs'!S24="","",'Model inputs'!S24=1))),IF('Model inputs'!AB65="","",'Model inputs'!AB65),IF('Base and upside comparison'!AE12="","",'Base and upside comparison'!AE12))="",0,IF(IF(IF(ISERROR('Model inputs'!S24=1),'Model inputs'!S24=1,IF('Model inputs'!S24="","",'Model inputs'!S24=1))="",FALSE,IF(ISERROR('Model inputs'!S24=1),'Model inputs'!S24=1,IF('Model inputs'!S24="","",'Model inputs'!S24=1))),IF('Model inputs'!AB65="","",'Model inputs'!AB65),IF('Base and upside comparison'!AE12="","",'Base and upside comparison'!AE12)))+'Model inputs'!S43 -> 77111.713 | AH12: =IF(IF(IF(IF(ISERROR('Model inputs'!T23=1),'Model inputs'!T23=1,IF('Model inputs'!T23="","",'Model inputs'!T23=1))="",FALSE,IF(ISERROR('Model inputs'!T23=1),'Model inputs'!T23=1,IF('Model inputs'!T23="","",'Model inputs'!T23=1))),IF('Model inputs'!AB64="","",'Model inputs'!AB64),IF('Base and upside comparison'!AF12="","",'Base and upside comparison'!AF12))="",0,IF(IF(IF(ISERROR('Model inputs'!T23=1),'Model inputs'!T23=1,IF('Model inputs'!T23="","",'Model inputs'!T23=1))="",FALSE,IF(ISERROR('Model inputs'!T23=1),'Model inputs'!T23=1,IF('Model inputs'!T23="","",'Model inputs'!T23=1))),IF('Model inputs'!AB64="","",'Model inputs'!AB64),IF('Base and upside comparison'!AF12="","",'Base and upside comparison'!AF12)))+'Model inputs'!T42 -> 12814.906 | AI12: =IF(IF(IF(IF(ISERROR('Model inputs'!T24=1),'Model inputs'!T24=1,IF('Model inputs'!T24="","",'Model inputs'!T24=1))="",FALSE,IF(ISERROR('Model inputs'!T24=1),'Model inputs'!T24=1,IF('Model inputs'!T24="","",'Model inputs'!T24=1))),IF('Model inputs'!AB65="","",'Model inputs'!AB65),IF('Base and upside comparison'!AG12="","",'Base and upside comparison'!AG12))="",0,IF(IF(IF(ISERROR('Model inputs'!T24=1),'Model inputs'!T24=1,IF('Model inputs'!T24="","",'Model inputs'!T24=1))="",FALSE,IF(ISERROR('Model inputs'!T24=1),'Model inputs'!T24=1,IF('Model inputs'!T24="","",'Model inputs'!T24=1))),IF('Model inputs'!AB65="","",'Model inputs'!AB65),IF('Base and upside comparison'!AG12="","",'Base and upside comparison'!AG12)))+'Model inputs'!T43 -> 95744.89 | AJ12: =IF(IF(IF(IF(ISERROR('Model inputs'!U23=1),'Model inputs'!U23=1,IF('Model inputs'!U23="","",'Model inputs'!U23=1))="",FALSE,IF(ISERROR('Model inputs'!U23=1),'Model inputs'!U23=1,IF('Model inputs'!U23="","",'Model inputs'!U23=1))),IF('Model inputs'!AB64="","",'Model inputs'!AB64),IF('Base and upside comparison'!AH12="","",'Base and upside comparison'!AH12))="",0,IF(IF(IF(ISERROR('Model inputs'!U23=1),'Model inputs'!U23=1,IF('Model inputs'!U23="","",'Model inputs'!U23=1))="",FALSE,IF(ISERROR('Model inputs'!U23=1),'Model inputs'!U23=1,IF('Model inputs'!U23="","",'Model inputs'!U23=1))),IF('Model inputs'!AB64="","",'Model inputs'!AB64),IF('Base and upside comparison'!AH12="","",'Base and upside comparison'!AH12)))+'Model inputs'!U42 -> 15076.535 | AK12: =IF(IF(IF(IF(ISERROR('Model inputs'!U24=1),'Model inputs'!U24=1,IF('Model inputs'!U24="","",'Model inputs'!U24=1))="",FALSE,IF(ISERROR('Model inputs'!U24=1),'Model inputs'!U24=1,IF('Model inputs'!U24="","",'Model inputs'!U24=1))),IF('Model inputs'!AB65="","",'Model inputs'!AB65),IF('Base and upside comparison'!AI12="","",'Base and upside comparison'!AI12))="",0,IF(IF(IF(ISERROR('Model inputs'!U24=1),'Model inputs'!U24=1,IF('Model inputs'!U24="","",'Model inputs'!U24=1))="",FALSE,IF(ISERROR('Model inputs'!U24=1),'Model inputs'!U24=1,IF('Model inputs'!U24="","",'Model inputs'!U24=1))),IF('Model inputs'!AB65="","",'Model inputs'!AB65),IF('Base and upside comparison'!AI12="","",'Base and upside comparison'!AI12)))+'Model inputs'!U43 -> 118543.37 | AL12: =IF(IF(IF(IF(ISERROR('Model inputs'!V23=1),'Model inputs'!V23=1,IF('Model inputs'!V23="","",'Model inputs'!V23=1))="",FALSE,IF(ISERROR('Model inputs'!V23=1),'Model inputs'!V23=1,IF('Model inputs'!V23="","",'Model inputs'!V23=1))),IF('Model inputs'!AB64="","",'Model inputs'!AB64),IF('Base and upside comparison'!AJ12="","",'Base and upside comparison'!AJ12))="",0,IF(IF(IF(ISERROR('Model inputs'!V23=1),'Model inputs'!V23=1,IF('Model inputs'!V23="","",'Model inputs'!V23=1))="",FALSE,IF(ISERROR('Model inputs'!V23=1),'Model inputs'!V23=1,IF('Model inputs'!V23="","",'Model inputs'!V23=1))),IF('Model inputs'!AB64="","",'Model inputs'!AB64),IF('Base and upside comparison'!AJ12="","",'Base and upside comparison'!AJ12)))+'Model inputs'!V42 -> 17645.559 | AM12: =IF(IF(IF(IF(ISERROR('Model inputs'!V24=1),'Model inputs'!V24=1,IF('Model inputs'!V24="","",'Model inputs'!V24=1))="",FALSE,IF(ISERROR('Model inputs'!V24=1),'Model inputs'!V24=1,IF('Model inputs'!V24="","",'Model inputs'!V24=1))),IF('Model inputs'!AB65="","",'Model inputs'!AB65),IF('Base and upside comparison'!AK12="","",'Base and upside comparison'!AK12))="",0,IF(IF(IF(ISERROR('Model inputs'!V24=1),'Model inputs'!V24=1,IF('Model inputs'!V24="","",'Model inputs'!V24=1))="",FALSE,IF(ISERROR('Model inputs'!V24=1),'Model inputs'!V24=1,IF('Model inputs'!V24="","",'Model inputs'!V24=1))),IF('Model inputs'!AB65="","",'Model inputs'!AB65),IF('Base and upside comparison'!AK12="","",'Base and upside comparison'!AK12)))+'Model inputs'!V43 -> 146423.51 | AN12: =IF(IF(IF(IF(ISERROR('Model inputs'!W23=1),'Model inputs'!W23=1,IF('Model inputs'!W23="","",'Model inputs'!W23=1))="",FALSE,IF(ISERROR('Model inputs'!W23=1),'Model inputs'!W23=1,IF('Model inputs'!W23="","",'Model inputs'!W23=1))),IF('Model inputs'!AB64="","",'Model inputs'!AB64),IF('Base and upside comparison'!AL12="","",'Base and upside comparison'!AL12))="",0,IF(IF(IF(ISERROR('Model inputs'!W23=1),'Model inputs'!W23=1,IF('Model inputs'!W23="","",'Model inputs'!W23=1))="",FALSE,IF(ISERROR('Model inputs'!W23=1),'Model inputs'!W23=1,IF('Model inputs'!W23="","",'Model inputs'!W23=1))),IF('Model inputs'!AB64="","",'Model inputs'!AB64),IF('Base and upside comparison'!AL12="","",'Base and upside comparison'!AL12)))+'Model inputs'!W42 -> 20558.867 | AO12: =IF(IF(IF(IF(ISERROR('Model inputs'!W24=1),'Model inputs'!W24=1,IF('Model inputs'!W24="","",'Model inputs'!W24=1))="",FALSE,IF(ISERROR('Model inputs'!W24=1),'Model inputs'!W24=1,IF('Model inputs'!W24="","",'Model inputs'!W24=1))),IF('Model inputs'!AB65="","",'Model inputs'!AB65),IF('Base and upside comparison'!AM12="","",'Base and upside comparison'!AM12))="",0,IF(IF(IF(ISERROR('Model inputs'!W24=1),'Model inputs'!W24=1,IF('Model inputs'!W24="","",'Model inputs'!W24=1))="",FALSE,IF(ISERROR('Model inputs'!W24=1),'Model inputs'!W24=1,IF('Model inputs'!W24="","",'Model inputs'!W24=1))),IF('Model inputs'!AB65="","",'Model inputs'!AB65),IF('Base and upside comparison'!AM12="","",'Base and upside comparison'!AM12)))+'Model inputs'!W43 -> 180503.28 | AP12: =IF(IF(IF(IF(ISERROR('Model inputs'!X23=1),'Model inputs'!X23=1,IF('Model inputs'!X23="","",'Model inputs'!X23=1))="",FALSE,IF(ISERROR('Model inputs'!X23=1),'Model inputs'!X23=1,IF('Model inputs'!X23="","",'Model inputs'!X23=1))),IF('Model inputs'!AB64="","",'Model inputs'!AB64),IF('Base and upside comparison'!AN12="","",'Base and upside comparison'!AN12))="",0,IF(IF(IF(ISERROR('Model inputs'!X23=1),'Model inputs'!X23=1,IF('Model inputs'!X23="","",'Model inputs'!X23=1))="",FALSE,IF(ISERROR('Model inputs'!X23=1),'Model inputs'!X23=1,IF('Model inputs'!X23="","",'Model inputs'!X23=1))),IF('Model inputs'!AB64="","",'Model inputs'!AB64),IF('Base and upside comparison'!AN12="","",'Base and upside comparison'!AN12)))+'Model inputs'!X42 -> 23857.771 | AQ12: =IF(IF(IF(IF(ISERROR('Model inputs'!X24=1),'Model inputs'!X24=1,IF('Model inputs'!X24="","",'Model inputs'!X24=1))="",FALSE,IF(ISERROR('Model inputs'!X24=1),'Model inputs'!X24=1,IF('Model inputs'!X24="","",'Model inputs'!X24=1))),IF('Model inputs'!AB65="","",'Model inputs'!AB65),IF('Base and upside comparison'!AO12="","",'Base and upside comparison'!AO12))="",0,IF(IF(IF(ISERROR('Model inputs'!X24=1),'Model inputs'!X24=1,IF('Model inputs'!X24="","",'Model inputs'!X24=1))="",FALSE,IF(ISERROR('Model inputs'!X24=1),'Model inputs'!X24=1,IF('Model inputs'!X24="","",'Model inputs'!X24=1))),IF('Model inputs'!AB65="","",'Model inputs'!AB65),IF('Base and upside comparison'!AO12="","",'Base and upside comparison'!AO12)))+'Model inputs'!X43 -> 222146.6 | AR12: =IF(IF(IF(IF(ISERROR('Model inputs'!Y23=1),'Model inputs'!Y23=1,IF('Model inputs'!Y23="","",'Model inputs'!Y23=1))="",FALSE,IF(ISERROR('Model inputs'!Y23=1),'Model inputs'!Y23=1,IF('Model inputs'!Y23="","",'Model inputs'!Y23=1))),IF('Model inputs'!AB64="","",'Model inputs'!AB64),IF('Base and upside comparison'!AP12="","",'Base and upside comparison'!AP12))="",0,IF(IF(IF(ISERROR('Model inputs'!Y23=1),'Model inputs'!Y23=1,IF('Model inputs'!Y23="","",'Model inputs'!Y23=1))="",FALSE,IF(ISERROR('Model inputs'!Y23=1),'Model inputs'!Y23=1,IF('Model inputs'!Y23="","",'Model inputs'!Y23=1))),IF('Model inputs'!AB64="","",'Model inputs'!AB64),IF('Base and upside comparison'!AP12="","",'Base and upside comparison'!AP12)))+'Model inputs'!Y42 -> 27588.543 | AS12: =IF(IF(IF(IF(ISERROR('Model inputs'!Y24=1),'Model inputs'!Y24=1,IF('Model inputs'!Y24="","",'Model inputs'!Y24=1))="",FALSE,IF(ISERROR('Model inputs'!Y24=1),'Model inputs'!Y24=1,IF('Model inputs'!Y24="","",'Model inputs'!Y24=1))),IF('Model inputs'!AB65="","",'Model inputs'!AB65),IF('Base and upside comparison'!AQ12="","",'Base and upside comparison'!AQ12))="",0,IF(IF(IF(ISERROR('Model inputs'!Y24=1),'Model inputs'!Y24=1,IF('Model inputs'!Y24="","",'Model inputs'!Y24=1))="",FALSE,IF(ISERROR('Model inputs'!Y24=1),'Model inputs'!Y24=1,IF('Model inputs'!Y24="","",'Model inputs'!Y24=1))),IF('Model inputs'!AB65="","",'Model inputs'!AB65),IF('Base and upside comparison'!AQ12="","",'Base and upside comparison'!AQ12)))+'Model inputs'!Y43 -> 273017.45 | AT12: =IF(IF(IF(IF(ISERROR('Model inputs'!Z23=1),'Model inputs'!Z23=1,IF('Model inputs'!Z23="","",'Model inputs'!Z23=1))="",FALSE,IF(ISERROR('Model inputs'!Z23=1),'Model inputs'!Z23=1,IF('Model inputs'!Z23="","",'Model inputs'!Z23=1))),IF('Model inputs'!AB64="","",'Model inputs'!AB64),IF('Base and upside comparison'!AR12="","",'Base and upside comparison'!AR12))="",0,IF(IF(IF(ISERROR('Model inputs'!Z23=1),'Model inputs'!Z23=1,IF('Model inputs'!Z23="","",'Model inputs'!Z23=1))="",FALSE,IF(ISERROR('Model inputs'!Z23=1),'Model inputs'!Z23=1,IF('Model inputs'!Z23="","",'Model inputs'!Z23=1))),IF('Model inputs'!AB64="","",'Model inputs'!AB64),IF('Base and upside comparison'!AR12="","",'Base and upside comparison'!AR12)))+'Model inputs'!Z42 -> 31803.008 | AU12: =IF(IF(IF(IF(ISERROR('Model inputs'!Z24=1),'Model inputs'!Z24=1,IF('Model inputs'!Z24="","",'Model inputs'!Z24=1))="",FALSE,IF(ISERROR('Model inputs'!Z24=1),'Model inputs'!Z24=1,IF('Model inputs'!Z24="","",'Model inputs'!Z24=1))),IF('Model inputs'!AB65="","",'Model inputs'!AB65),IF('Base and upside comparison'!AS12="","",'Base and upside comparison'!AS12))="",0,IF(IF(IF(ISERROR('Model inputs'!Z24=1),'Model inputs'!Z24=1,IF('Model inputs'!Z24="","",'Model inputs'!Z24=1))="",FALSE,IF(ISERROR('Model inputs'!Z24=1),'Model inputs'!Z24=1,IF('Model inputs'!Z24="","",'Model inputs'!Z24=1))),IF('Model inputs'!AB65="","",'Model inputs'!AB65),IF('Base and upside comparison'!AS12="","",'Base and upside comparison'!AS12)))+'Model inputs'!Z43 -> 335145.89 | AV12: =IF(IF(IF(IF(ISERROR('Model inputs'!B23=1),'Model inputs'!B23=1,IF('Model inputs'!B23="","",'Model inputs'!B23=1))="",FALSE,IF(ISERROR('Model inputs'!B23=1),'Model inputs'!B23=1,IF('Model inputs'!B23="","",'Model inputs'!B23=1))),IF('Model inputs'!AB64="","",'Model inputs'!AB64),IF('Base and upside comparison'!AT12="","",'Base and upside comparison'!AT12))="",0,IF(IF(IF(ISERROR('Model inputs'!B23=1),'Model inputs'!B23=1,IF('Model inputs'!B23="","",'Model inputs'!B23=1))="",FALSE,IF(ISERROR('Model inputs'!B23=1),'Model inputs'!B23=1,IF('Model inputs'!B23="","",'Model inputs'!B23=1))),IF('Model inputs'!AB64="","",'Model inputs'!AB64),IF('Base and upside comparison'!AT12="","",'Base and upside comparison'!AT12)))+'Model inputs'!B42 -> 36559.209 | AW12: =IF(IF(IF(IF(ISERROR('Model inputs'!B24=1),'Model inputs'!B24=1,IF('Model inputs'!B24="","",'Model inputs'!B24=1))="",FALSE,IF(ISERROR('Model inputs'!B24=1),'Model inputs'!B24=1,IF('Model inputs'!B24="","",'Model inputs'!B24=1))),IF('Model inputs'!AB65="","",'Model inputs'!AB65),IF('Base and upside comparison'!AU12="","",'Base and upside comparison'!AU12))="",0,IF(IF(IF(ISERROR('Model inputs'!B24=1),'Model inputs'!B24=1,IF('Model inputs'!B24="","",'Model inputs'!B24=1))="",FALSE,IF(ISERROR('Model inputs'!B24=1),'Model inputs'!B24=1,IF('Model inputs'!B24="","",'Model inputs'!B24=1))),IF('Model inputs'!AB65="","",'Model inputs'!AB65),IF('Base and upside comparison'!AU12="","",'Base and upside comparison'!AU12)))+'Model inputs'!B43 -> 411008.58
A13: Founder funding required to date | B13: =MAX(IF(IF(IF(ISERROR('Model inputs'!D23=1),'Model inputs'!D23=1,IF('Model inputs'!D23="","",'Model inputs'!D23=1))="",FALSE,IF(ISERROR('Model inputs'!D23=1),'Model inputs'!D23=1,IF('Model inputs'!D23="","",'Model inputs'!D23=1))),0,IF('Model inputs'!AA25="","",'Model inputs'!AA25)),-'Base and upside comparison'!B12,0) -> 144 | C13: =MAX(IF(IF(IF(ISERROR('Model inputs'!D24=1),'Model inputs'!D24=1,IF('Model inputs'!D24="","",'Model inputs'!D24=1))="",FALSE,IF(ISERROR('Model inputs'!D24=1),'Model inputs'!D24=1,IF('Model inputs'!D24="","",'Model inputs'!D24=1))),0,IF('Model inputs'!AA26="","",'Model inputs'!AA26)),-'Base and upside comparison'!C12,0) -> 0 | D13: =MAX(IF(IF(IF(ISERROR('Model inputs'!E23=1),'Model inputs'!E23=1,IF('Model inputs'!E23="","",'Model inputs'!E23=1))="",FALSE,IF(ISERROR('Model inputs'!E23=1),'Model inputs'!E23=1,IF('Model inputs'!E23="","",'Model inputs'!E23=1))),0,IF('Base and upside comparison'!B13="","",'Base and upside comparison'!B13)),-'Base and upside comparison'!D12,0) -> 144 | E13: =MAX(IF(IF(IF(ISERROR('Model inputs'!E24=1),'Model inputs'!E24=1,IF('Model inputs'!E24="","",'Model inputs'!E24=1))="",FALSE,IF(ISERROR('Model inputs'!E24=1),'Model inputs'!E24=1,IF('Model inputs'!E24="","",'Model inputs'!E24=1))),0,IF('Base and upside comparison'!C13="","",'Base and upside comparison'!C13)),-'Base and upside comparison'!E12,0) -> 0 | F13: =MAX(IF(IF(IF(ISERROR('Model inputs'!F23=1),'Model inputs'!F23=1,IF('Model inputs'!F23="","",'Model inputs'!F23=1))="",FALSE,IF(ISERROR('Model inputs'!F23=1),'Model inputs'!F23=1,IF('Model inputs'!F23="","",'Model inputs'!F23=1))),0,IF('Base and upside comparison'!D13="","",'Base and upside comparison'!D13)),-'Base and upside comparison'!F12,0) -> 144 | G13: =MAX(IF(IF(IF(ISERROR('Model inputs'!F24=1),'Model inputs'!F24=1,IF('Model inputs'!F24="","",'Model inputs'!F24=1))="",FALSE,IF(ISERROR('Model inputs'!F24=1),'Model inputs'!F24=1,IF('Model inputs'!F24="","",'Model inputs'!F24=1))),0,IF('Base and upside comparison'!E13="","",'Base and upside comparison'!E13)),-'Base and upside comparison'!G12,0) -> 0 | H13: =MAX(IF(IF(IF(ISERROR('Model inputs'!G23=1),'Model inputs'!G23=1,IF('Model inputs'!G23="","",'Model inputs'!G23=1))="",FALSE,IF(ISERROR('Model inputs'!G23=1),'Model inputs'!G23=1,IF('Model inputs'!G23="","",'Model inputs'!G23=1))),0,IF('Base and upside comparison'!F13="","",'Base and upside comparison'!F13)),-'Base and upside comparison'!H12,0) -> 144 | I13: =MAX(IF(IF(IF(ISERROR('Model inputs'!G24=1),'Model inputs'!G24=1,IF('Model inputs'!G24="","",'Model inputs'!G24=1))="",FALSE,IF(ISERROR('Model inputs'!G24=1),'Model inputs'!G24=1,IF('Model inputs'!G24="","",'Model inputs'!G24=1))),0,IF('Base and upside comparison'!G13="","",'Base and upside comparison'!G13)),-'Base and upside comparison'!I12,0) -> 0 | J13: =MAX(IF(IF(IF(ISERROR('Model inputs'!H23=1),'Model inputs'!H23=1,IF('Model inputs'!H23="","",'Model inputs'!H23=1))="",FALSE,IF(ISERROR('Model inputs'!H23=1),'Model inputs'!H23=1,IF('Model inputs'!H23="","",'Model inputs'!H23=1))),0,IF('Base and upside comparison'!H13="","",'Base and upside comparison'!H13)),-'Base and upside comparison'!J12,0) -> 144 | K13: =MAX(IF(IF(IF(ISERROR('Model inputs'!H24=1),'Model inputs'!H24=1,IF('Model inputs'!H24="","",'Model inputs'!H24=1))="",FALSE,IF(ISERROR('Model inputs'!H24=1),'Model inputs'!H24=1,IF('Model inputs'!H24="","",'Model inputs'!H24=1))),0,IF('Base and upside comparison'!I13="","",'Base and upside comparison'!I13)),-'Base and upside comparison'!K12,0) -> 0 | L13: =MAX(IF(IF(IF(ISERROR('Model inputs'!I23=1),'Model inputs'!I23=1,IF('Model inputs'!I23="","",'Model inputs'!I23=1))="",FALSE,IF(ISERROR('Model inputs'!I23=1),'Model inputs'!I23=1,IF('Model inputs'!I23="","",'Model inputs'!I23=1))),0,IF('Base and upside comparison'!J13="","",'Base and upside comparison'!J13)),-'Base and upside comparison'!L12,0) -> 144 | M13: =MAX(IF(IF(IF(ISERROR('Model inputs'!I24=1),'Model inputs'!I24=1,IF('Model inputs'!I24="","",'Model inputs'!I24=1))="",FALSE,IF(ISERROR('Model inputs'!I24=1),'Model inputs'!I24=1,IF('Model inputs'!I24="","",'Model inputs'!I24=1))),0,IF('Base and upside comparison'!K13="","",'Base and upside comparison'!K13)),-'Base and upside comparison'!M12,0) -> 0 | N13: =MAX(IF(IF(IF(ISERROR('Model inputs'!J23=1),'Model inputs'!J23=1,IF('Model inputs'!J23="","",'Model inputs'!J23=1))="",FALSE,IF(ISERROR('Model inputs'!J23=1),'Model inputs'!J23=1,IF('Model inputs'!J23="","",'Model inputs'!J23=1))),0,IF('Base and upside comparison'!L13="","",'Base and upside comparison'!L13)),-'Base and upside comparison'!N12,0) -> 144 | O13: =MAX(IF(IF(IF(ISERROR('Model inputs'!J24=1),'Model inputs'!J24=1,IF('Model inputs'!J24="","",'Model inputs'!J24=1))="",FALSE,IF(ISERROR('Model inputs'!J24=1),'Model inputs'!J24=1,IF('Model inputs'!J24="","",'Model inputs'!J24=1))),0,IF('Base and upside comparison'!M13="","",'Base and upside comparison'!M13)),-'Base and upside comparison'!O12,0) -> 0 | P13: =MAX(IF(IF(IF(ISERROR('Model inputs'!K23=1),'Model inputs'!K23=1,IF('Model inputs'!K23="","",'Model inputs'!K23=1))="",FALSE,IF(ISERROR('Model inputs'!K23=1),'Model inputs'!K23=1,IF('Model inputs'!K23="","",'Model inputs'!K23=1))),0,IF('Base and upside comparison'!N13="","",'Base and upside comparison'!N13)),-'Base and upside comparison'!P12,0) -> 144 | Q13: =MAX(IF(IF(IF(ISERROR('Model inputs'!K24=1),'Model inputs'!K24=1,IF('Model inputs'!K24="","",'Model inputs'!K24=1))="",FALSE,IF(ISERROR('Model inputs'!K24=1),'Model inputs'!K24=1,IF('Model inputs'!K24="","",'Model inputs'!K24=1))),0,IF('Base and upside comparison'!O13="","",'Base and upside comparison'!O13)),-'Base and upside comparison'!Q12,0) -> 0 | R13: =MAX(IF(IF(IF(ISERROR('Model inputs'!L23=1),'Model inputs'!L23=1,IF('Model inputs'!L23="","",'Model inputs'!L23=1))="",FALSE,IF(ISERROR('Model inputs'!L23=1),'Model inputs'!L23=1,IF('Model inputs'!L23="","",'Model inputs'!L23=1))),0,IF('Base and upside comparison'!P13="","",'Base and upside comparison'!P13)),-'Base and upside comparison'!R12,0) -> 144 | S13: =MAX(IF(IF(IF(ISERROR('Model inputs'!L24=1),'Model inputs'!L24=1,IF('Model inputs'!L24="","",'Model inputs'!L24=1))="",FALSE,IF(ISERROR('Model inputs'!L24=1),'Model inputs'!L24=1,IF('Model inputs'!L24="","",'Model inputs'!L24=1))),0,IF('Base and upside comparison'!Q13="","",'Base and upside comparison'!Q13)),-'Base and upside comparison'!S12,0) -> 0 | T13: =MAX(IF(IF(IF(ISERROR('Model inputs'!M23=1),'Model inputs'!M23=1,IF('Model inputs'!M23="","",'Model inputs'!M23=1))="",FALSE,IF(ISERROR('Model inputs'!M23=1),'Model inputs'!M23=1,IF('Model inputs'!M23="","",'Model inputs'!M23=1))),0,IF('Base and upside comparison'!R13="","",'Base and upside comparison'!R13)),-'Base and upside comparison'!T12,0) -> 144 | U13: =MAX(IF(IF(IF(ISERROR('Model inputs'!M24=1),'Model inputs'!M24=1,IF('Model inputs'!M24="","",'Model inputs'!M24=1))="",FALSE,IF(ISERROR('Model inputs'!M24=1),'Model inputs'!M24=1,IF('Model inputs'!M24="","",'Model inputs'!M24=1))),0,IF('Base and upside comparison'!S13="","",'Base and upside comparison'!S13)),-'Base and upside comparison'!U12,0) -> 0 | V13: =MAX(IF(IF(IF(ISERROR('Model inputs'!N23=1),'Model inputs'!N23=1,IF('Model inputs'!N23="","",'Model inputs'!N23=1))="",FALSE,IF(ISERROR('Model inputs'!N23=1),'Model inputs'!N23=1,IF('Model inputs'!N23="","",'Model inputs'!N23=1))),0,IF('Base and upside comparison'!T13="","",'Base and upside comparison'!T13)),-'Base and upside comparison'!V12,0) -> 144 | W13: =MAX(IF(IF(IF(ISERROR('Model inputs'!N24=1),'Model inputs'!N24=1,IF('Model inputs'!N24="","",'Model inputs'!N24=1))="",FALSE,IF(ISERROR('Model inputs'!N24=1),'Model inputs'!N24=1,IF('Model inputs'!N24="","",'Model inputs'!N24=1))),0,IF('Base and upside comparison'!U13="","",'Base and upside comparison'!U13)),-'Base and upside comparison'!W12,0) -> 0 | X13: =MAX(IF(IF(IF(ISERROR('Model inputs'!O23=1),'Model inputs'!O23=1,IF('Model inputs'!O23="","",'Model inputs'!O23=1))="",FALSE,IF(ISERROR('Model inputs'!O23=1),'Model inputs'!O23=1,IF('Model inputs'!O23="","",'Model inputs'!O23=1))),0,IF('Base and upside comparison'!V13="","",'Base and upside comparison'!V13)),-'Base and upside comparison'!X12,0) -> 144 | Y13: =MAX(IF(IF(IF(ISERROR('Model inputs'!O24=1),'Model inputs'!O24=1,IF('Model inputs'!O24="","",'Model inputs'!O24=1))="",FALSE,IF(ISERROR('Model inputs'!O24=1),'Model inputs'!O24=1,IF('Model inputs'!O24="","",'Model inputs'!O24=1))),0,IF('Base and upside comparison'!W13="","",'Base and upside comparison'!W13)),-'Base and upside comparison'!Y12,0) -> 0 | Z13: =MAX(IF(IF(IF(ISERROR('Model inputs'!P23=1),'Model inputs'!P23=1,IF('Model inputs'!P23="","",'Model inputs'!P23=1))="",FALSE,IF(ISERROR('Model inputs'!P23=1),'Model inputs'!P23=1,IF('Model inputs'!P23="","",'Model inputs'!P23=1))),0,IF('Base and upside comparison'!X13="","",'Base and upside comparison'!X13)),-'Base and upside comparison'!Z12,0) -> 144 | AA13: =MAX(IF(IF(IF(ISERROR('Model inputs'!P24=1),'Model inputs'!P24=1,IF('Model inputs'!P24="","",'Model inputs'!P24=1))="",FALSE,IF(ISERROR('Model inputs'!P24=1),'Model inputs'!P24=1,IF('Model inputs'!P24="","",'Model inputs'!P24=1))),0,IF('Base and upside comparison'!Y13="","",'Base and upside comparison'!Y13)),-'Base and upside comparison'!AA12,0) -> 0 | AB13: =MAX(IF(IF(IF(ISERROR('Model inputs'!Q23=1),'Model inputs'!Q23=1,IF('Model inputs'!Q23="","",'Model inputs'!Q23=1))="",FALSE,IF(ISERROR('Model inputs'!Q23=1),'Model inputs'!Q23=1,IF('Model inputs'!Q23="","",'Model inputs'!Q23=1))),0,IF('Base and upside comparison'!Z13="","",'Base and upside comparison'!Z13)),-'Base and upside comparison'!AB12,0) -> 144 | AC13: =MAX(IF(IF(IF(ISERROR('Model inputs'!Q24=1),'Model inputs'!Q24=1,IF('Model inputs'!Q24="","",'Model inputs'!Q24=1))="",FALSE,IF(ISERROR('Model inputs'!Q24=1),'Model inputs'!Q24=1,IF('Model inputs'!Q24="","",'Model inputs'!Q24=1))),0,IF('Base and upside comparison'!AA13="","",'Base and upside comparison'!AA13)),-'Base and upside comparison'!AC12,0) -> 0 | AD13: =MAX(IF(IF(IF(ISERROR('Model inputs'!R23=1),'Model inputs'!R23=1,IF('Model inputs'!R23="","",'Model inputs'!R23=1))="",FALSE,IF(ISERROR('Model inputs'!R23=1),'Model inputs'!R23=1,IF('Model inputs'!R23="","",'Model inputs'!R23=1))),0,IF('Base and upside comparison'!AB13="","",'Base and upside comparison'!AB13)),-'Base and upside comparison'!AD12,0) -> 144 | AE13: =MAX(IF(IF(IF(ISERROR('Model inputs'!R24=1),'Model inputs'!R24=1,IF('Model inputs'!R24="","",'Model inputs'!R24=1))="",FALSE,IF(ISERROR('Model inputs'!R24=1),'Model inputs'!R24=1,IF('Model inputs'!R24="","",'Model inputs'!R24=1))),0,IF('Base and upside comparison'!AC13="","",'Base and upside comparison'!AC13)),-'Base and upside comparison'!AE12,0) -> 0 | AF13: =MAX(IF(IF(IF(ISERROR('Model inputs'!S23=1),'Model inputs'!S23=1,IF('Model inputs'!S23="","",'Model inputs'!S23=1))="",FALSE,IF(ISERROR('Model inputs'!S23=1),'Model inputs'!S23=1,IF('Model inputs'!S23="","",'Model inputs'!S23=1))),0,IF('Base and upside comparison'!AD13="","",'Base and upside comparison'!AD13)),-'Base and upside comparison'!AF12,0) -> 144 | AG13: =MAX(IF(IF(IF(ISERROR('Model inputs'!S24=1),'Model inputs'!S24=1,IF('Model inputs'!S24="","",'Model inputs'!S24=1))="",FALSE,IF(ISERROR('Model inputs'!S24=1),'Model inputs'!S24=1,IF('Model inputs'!S24="","",'Model inputs'!S24=1))),0,IF('Base and upside comparison'!AE13="","",'Base and upside comparison'!AE13)),-'Base and upside comparison'!AG12,0) -> 0 | AH13: =MAX(IF(IF(IF(ISERROR('Model inputs'!T23=1),'Model inputs'!T23=1,IF('Model inputs'!T23="","",'Model inputs'!T23=1))="",FALSE,IF(ISERROR('Model inputs'!T23=1),'Model inputs'!T23=1,IF('Model inputs'!T23="","",'Model inputs'!T23=1))),0,IF('Base and upside comparison'!AF13="","",'Base and upside comparison'!AF13)),-'Base and upside comparison'!AH12,0) -> 144 | AI13: =MAX(IF(IF(IF(ISERROR('Model inputs'!T24=1),'Model inputs'!T24=1,IF('Model inputs'!T24="","",'Model inputs'!T24=1))="",FALSE,IF(ISERROR('Model inputs'!T24=1),'Model inputs'!T24=1,IF('Model inputs'!T24="","",'Model inputs'!T24=1))),0,IF('Base and upside comparison'!AG13="","",'Base and upside comparison'!AG13)),-'Base and upside comparison'!AI12,0) -> 0 | AJ13: =MAX(IF(IF(IF(ISERROR('Model inputs'!U23=1),'Model inputs'!U23=1,IF('Model inputs'!U23="","",'Model inputs'!U23=1))="",FALSE,IF(ISERROR('Model inputs'!U23=1),'Model inputs'!U23=1,IF('Model inputs'!U23="","",'Model inputs'!U23=1))),0,IF('Base and upside comparison'!AH13="","",'Base and upside comparison'!AH13)),-'Base and upside comparison'!AJ12,0) -> 144 | AK13: =MAX(IF(IF(IF(ISERROR('Model inputs'!U24=1),'Model inputs'!U24=1,IF('Model inputs'!U24="","",'Model inputs'!U24=1))="",FALSE,IF(ISERROR('Model inputs'!U24=1),'Model inputs'!U24=1,IF('Model inputs'!U24="","",'Model inputs'!U24=1))),0,IF('Base and upside comparison'!AI13="","",'Base and upside comparison'!AI13)),-'Base and upside comparison'!AK12,0) -> 0 | AL13: =MAX(IF(IF(IF(ISERROR('Model inputs'!V23=1),'Model inputs'!V23=1,IF('Model inputs'!V23="","",'Model inputs'!V23=1))="",FALSE,IF(ISERROR('Model inputs'!V23=1),'Model inputs'!V23=1,IF('Model inputs'!V23="","",'Model inputs'!V23=1))),0,IF('Base and upside comparison'!AJ13="","",'Base and upside comparison'!AJ13)),-'Base and upside comparison'!AL12,0) -> 144 | AM13: =MAX(IF(IF(IF(ISERROR('Model inputs'!V24=1),'Model inputs'!V24=1,IF('Model inputs'!V24="","",'Model inputs'!V24=1))="",FALSE,IF(ISERROR('Model inputs'!V24=1),'Model inputs'!V24=1,IF('Model inputs'!V24="","",'Model inputs'!V24=1))),0,IF('Base and upside comparison'!AK13="","",'Base and upside comparison'!AK13)),-'Base and upside comparison'!AM12,0) -> 0 | AN13: =MAX(IF(IF(IF(ISERROR('Model inputs'!W23=1),'Model inputs'!W23=1,IF('Model inputs'!W23="","",'Model inputs'!W23=1))="",FALSE,IF(ISERROR('Model inputs'!W23=1),'Model inputs'!W23=1,IF('Model inputs'!W23="","",'Model inputs'!W23=1))),0,IF('Base and upside comparison'!AL13="","",'Base and upside comparison'!AL13)),-'Base and upside comparison'!AN12,0) -> 144 | AO13: =MAX(IF(IF(IF(ISERROR('Model inputs'!W24=1),'Model inputs'!W24=1,IF('Model inputs'!W24="","",'Model inputs'!W24=1))="",FALSE,IF(ISERROR('Model inputs'!W24=1),'Model inputs'!W24=1,IF('Model inputs'!W24="","",'Model inputs'!W24=1))),0,IF('Base and upside comparison'!AM13="","",'Base and upside comparison'!AM13)),-'Base and upside comparison'!AO12,0) -> 0 | AP13: =MAX(IF(IF(IF(ISERROR('Model inputs'!X23=1),'Model inputs'!X23=1,IF('Model inputs'!X23="","",'Model inputs'!X23=1))="",FALSE,IF(ISERROR('Model inputs'!X23=1),'Model inputs'!X23=1,IF('Model inputs'!X23="","",'Model inputs'!X23=1))),0,IF('Base and upside comparison'!AN13="","",'Base and upside comparison'!AN13)),-'Base and upside comparison'!AP12,0) -> 144 | AQ13: =MAX(IF(IF(IF(ISERROR('Model inputs'!X24=1),'Model inputs'!X24=1,IF('Model inputs'!X24="","",'Model inputs'!X24=1))="",FALSE,IF(ISERROR('Model inputs'!X24=1),'Model inputs'!X24=1,IF('Model inputs'!X24="","",'Model inputs'!X24=1))),0,IF('Base and upside comparison'!AO13="","",'Base and upside comparison'!AO13)),-'Base and upside comparison'!AQ12,0) -> 0 | AR13: =MAX(IF(IF(IF(ISERROR('Model inputs'!Y23=1),'Model inputs'!Y23=1,IF('Model inputs'!Y23="","",'Model inputs'!Y23=1))="",FALSE,IF(ISERROR('Model inputs'!Y23=1),'Model inputs'!Y23=1,IF('Model inputs'!Y23="","",'Model inputs'!Y23=1))),0,IF('Base and upside comparison'!AP13="","",'Base and upside comparison'!AP13)),-'Base and upside comparison'!AR12,0) -> 144 | AS13: =MAX(IF(IF(IF(ISERROR('Model inputs'!Y24=1),'Model inputs'!Y24=1,IF('Model inputs'!Y24="","",'Model inputs'!Y24=1))="",FALSE,IF(ISERROR('Model inputs'!Y24=1),'Model inputs'!Y24=1,IF('Model inputs'!Y24="","",'Model inputs'!Y24=1))),0,IF('Base and upside comparison'!AQ13="","",'Base and upside comparison'!AQ13)),-'Base and upside comparison'!AS12,0) -> 0 | AT13: =MAX(IF(IF(IF(ISERROR('Model inputs'!Z23=1),'Model inputs'!Z23=1,IF('Model inputs'!Z23="","",'Model inputs'!Z23=1))="",FALSE,IF(ISERROR('Model inputs'!Z23=1),'Model inputs'!Z23=1,IF('Model inputs'!Z23="","",'Model inputs'!Z23=1))),0,IF('Base and upside comparison'!AR13="","",'Base and upside comparison'!AR13)),-'Base and upside comparison'!AT12,0) -> 144 | AU13: =MAX(IF(IF(IF(ISERROR('Model inputs'!Z24=1),'Model inputs'!Z24=1,IF('Model inputs'!Z24="","",'Model inputs'!Z24=1))="",FALSE,IF(ISERROR('Model inputs'!Z24=1),'Model inputs'!Z24=1,IF('Model inputs'!Z24="","",'Model inputs'!Z24=1))),0,IF('Base and upside comparison'!AS13="","",'Base and upside comparison'!AS13)),-'Base and upside comparison'!AU12,0) -> 0 | AV13: =MAX(IF(IF(IF(ISERROR('Model inputs'!B23=1),'Model inputs'!B23=1,IF('Model inputs'!B23="","",'Model inputs'!B23=1))="",FALSE,IF(ISERROR('Model inputs'!B23=1),'Model inputs'!B23=1,IF('Model inputs'!B23="","",'Model inputs'!B23=1))),0,IF('Base and upside comparison'!AT13="","",'Base and upside comparison'!AT13)),-'Base and upside comparison'!AV12,0) -> 144 | AW13: =MAX(IF(IF(IF(ISERROR('Model inputs'!B24=1),'Model inputs'!B24=1,IF('Model inputs'!B24="","",'Model inputs'!B24=1))="",FALSE,IF(ISERROR('Model inputs'!B24=1),'Model inputs'!B24=1,IF('Model inputs'!B24="","",'Model inputs'!B24=1))),0,IF('Base and upside comparison'!AU13="","",'Base and upside comparison'!AU13)),-'Base and upside comparison'!AW12,0) -> 0

Sheet Sensitivity decision summary
A1: Sensitivity decision summary
A2: Upshift — Business Plan · Main Scenario
A4: Variable / dimension | B4: Value
A5: Migration stress break-even month | B5: =MIN('Model inputs'!D36,'Model inputs'!E36,'Model inputs'!F36,'Model inputs'!G36,'Model inputs'!H36,'Model inputs'!I36,'Model inputs'!J36,'Model inputs'!K36,'Model inputs'!L36,'Model inputs'!M36,'Model inputs'!N36,'Model inputs'!O36,'Model inputs'!P36,'Model inputs'!Q36,'Model inputs'!R36,'Model inputs'!S36,'Model inputs'!T36,'Model inputs'!U36,'Model inputs'!V36,'Model inputs'!W36,'Model inputs'!X36,'Model inputs'!Y36,'Model inputs'!Z36,'Model inputs'!B36) -> 46357
A6: Migration stress funding need | B6: =MAX(0,-MIN('Model inputs'!D11,'Model inputs'!E11,'Model inputs'!F11,'Model inputs'!G11,'Model inputs'!H11,'Model inputs'!I11,'Model inputs'!J11,'Model inputs'!K11,'Model inputs'!L11,'Model inputs'!M11,'Model inputs'!N11,'Model inputs'!O11,'Model inputs'!P11,'Model inputs'!Q11,'Model inputs'!R11,'Model inputs'!S11,'Model inputs'!T11,'Model inputs'!U11,'Model inputs'!V11,'Model inputs'!W11,'Model inputs'!X11,'Model inputs'!Y11,'Model inputs'!Z11,'Model inputs'!B11)) -> 162
A7: Price stress break-even month | B7: =MIN('Model inputs'!D60,'Model inputs'!E60,'Model inputs'!F60,'Model inputs'!G60,'Model inputs'!H60,'Model inputs'!I60,'Model inputs'!J60,'Model inputs'!K60,'Model inputs'!L60,'Model inputs'!M60,'Model inputs'!N60,'Model inputs'!O60,'Model inputs'!P60,'Model inputs'!Q60,'Model inputs'!R60,'Model inputs'!S60,'Model inputs'!T60,'Model inputs'!U60,'Model inputs'!V60,'Model inputs'!W60,'Model inputs'!X60,'Model inputs'!Y60,'Model inputs'!Z60,'Model inputs'!B60) -> 46388
A8: Price stress funding need | B8: =MAX(0,-MIN('Model inputs'!D12,'Model inputs'!E12,'Model inputs'!F12,'Model inputs'!G12,'Model inputs'!H12,'Model inputs'!I12,'Model inputs'!J12,'Model inputs'!K12,'Model inputs'!L12,'Model inputs'!M12,'Model inputs'!N12,'Model inputs'!O12,'Model inputs'!P12,'Model inputs'!Q12,'Model inputs'!R12,'Model inputs'!S12,'Model inputs'!T12,'Model inputs'!U12,'Model inputs'!V12,'Model inputs'!W12,'Model inputs'!X12,'Model inputs'!Y12,'Model inputs'!Z12,'Model inputs'!B12)) -> 364
A9: Combined stress break-even month | B9: =MIN('Model inputs'!D16,'Model inputs'!E16,'Model inputs'!F16,'Model inputs'!G16,'Model inputs'!H16,'Model inputs'!I16,'Model inputs'!J16,'Model inputs'!K16,'Model inputs'!L16,'Model inputs'!M16,'Model inputs'!N16,'Model inputs'!O16,'Model inputs'!P16,'Model inputs'!Q16,'Model inputs'!R16,'Model inputs'!S16,'Model inputs'!T16,'Model inputs'!U16,'Model inputs'!V16,'Model inputs'!W16,'Model inputs'!X16,'Model inputs'!Y16,'Model inputs'!Z16,'Model inputs'!B16) -> 46447
A10: Combined stress funding need | B10: =MAX(0,-MIN('Model inputs'!D10,'Model inputs'!E10,'Model inputs'!F10,'Model inputs'!G10,'Model inputs'!H10,'Model inputs'!I10,'Model inputs'!J10,'Model inputs'!K10,'Model inputs'!L10,'Model inputs'!M10,'Model inputs'!N10,'Model inputs'!O10,'Model inputs'!P10,'Model inputs'!Q10,'Model inputs'!R10,'Model inputs'!S10,'Model inputs'!T10,'Model inputs'!U10,'Model inputs'!V10,'Model inputs'!W10,'Model inputs'!X10,'Model inputs'!Y10,'Model inputs'!Z10,'Model inputs'!B10)) -> 458.8928

Sheet Model inputs
A1: Model inputs
A2: Integration values are aggregated snapshots; raw source records are not included.
A4: Variables
A5: Variable / segment | B5: 2028-09 | C5: Value | D5: 2026-10 | E5: 2026-11 | F5: 2026-12 | G5: 2027-01 | H5: 2027-02 | I5: 2027-03 | J5: 2027-04 | K5: 2027-05 | L5: 2027-06 | M5: 2027-07 | N5: 2027-08 | O5: 2027-09 | P5: 2027-10 | Q5: 2027-11 | R5: 2027-12 | S5: 2028-01 | T5: 2028-02 | U5: 2028-03 | V5: 2028-04 | W5: 2028-05 | X5: 2028-06 | Y5: 2028-07 | Z5: 2028-08 | AA5: 2026-09 | AB5: Value
A6: Annual recurring revenue | B6: ='Model inputs'!B66*12 -> 63526.628
A7: Breaking compute cost | C7: =0.1 -> 0.1
A8: Breaking migrations per repo | C8: =1 -> 1
A9: Breaking model cost | C9: =2 -> 2
A10: Cash at combined stress | B10: =IF(IF(IF(IF(ISERROR('Model inputs'!B23=1),'Model inputs'!B23=1,IF('Model inputs'!B23="","",'Model inputs'!B23=1))="",FALSE,IF(ISERROR('Model inputs'!B23=1),'Model inputs'!B23=1,IF('Model inputs'!B23="","",'Model inputs'!B23=1))),IF('Model inputs'!AB64="","",'Model inputs'!AB64),IF('Model inputs'!Z10="","",'Model inputs'!Z10))="",0,IF(IF(IF(ISERROR('Model inputs'!B23=1),'Model inputs'!B23=1,IF('Model inputs'!B23="","",'Model inputs'!B23=1))="",FALSE,IF(ISERROR('Model inputs'!B23=1),'Model inputs'!B23=1,IF('Model inputs'!B23="","",'Model inputs'!B23=1))),IF('Model inputs'!AB64="","",'Model inputs'!AB64),IF('Model inputs'!Z10="","",'Model inputs'!Z10)))+'Model inputs'!B115-'Model inputs'!C37 -> 15053.615 | D10: =IF(IF(IF(IF(ISERROR('Model inputs'!D23=1),'Model inputs'!D23=1,IF('Model inputs'!D23="","",'Model inputs'!D23=1))="",FALSE,IF(ISERROR('Model inputs'!D23=1),'Model inputs'!D23=1,IF('Model inputs'!D23="","",'Model inputs'!D23=1))),IF('Model inputs'!AB64="","",'Model inputs'!AB64),IF('Model inputs'!AA78="","",'Model inputs'!AA78))="",0,IF(IF(IF(ISERROR('Model inputs'!D23=1),'Model inputs'!D23=1,IF('Model inputs'!D23="","",'Model inputs'!D23=1))="",FALSE,IF(ISERROR('Model inputs'!D23=1),'Model inputs'!D23=1,IF('Model inputs'!D23="","",'Model inputs'!D23=1))),IF('Model inputs'!AB64="","",'Model inputs'!AB64),IF('Model inputs'!AA78="","",'Model inputs'!AA78)))+'Model inputs'!D115-'Model inputs'!C37 -> -220.66667 | E10: =IF(IF(IF(IF(ISERROR('Model inputs'!E23=1),'Model inputs'!E23=1,IF('Model inputs'!E23="","",'Model inputs'!E23=1))="",FALSE,IF(ISERROR('Model inputs'!E23=1),'Model inputs'!E23=1,IF('Model inputs'!E23="","",'Model inputs'!E23=1))),IF('Model inputs'!AB64="","",'Model inputs'!AB64),IF('Model inputs'!D10="","",'Model inputs'!D10))="",0,IF(IF(IF(ISERROR('Model inputs'!E23=1),'Model inputs'!E23=1,IF('Model inputs'!E23="","",'Model inputs'!E23=1))="",FALSE,IF(ISERROR('Model inputs'!E23=1),'Model inputs'!E23=1,IF('Model inputs'!E23="","",'Model inputs'!E23=1))),IF('Model inputs'!AB64="","",'Model inputs'!AB64),IF('Model inputs'!D10="","",'Model inputs'!D10)))+'Model inputs'!E115-'Model inputs'!C37 -> -362 | F10: =IF(IF(IF(IF(ISERROR('Model inputs'!F23=1),'Model inputs'!F23=1,IF('Model inputs'!F23="","",'Model inputs'!F23=1))="",FALSE,IF(ISERROR('Model inputs'!F23=1),'Model inputs'!F23=1,IF('Model inputs'!F23="","",'Model inputs'!F23=1))),IF('Model inputs'!AB64="","",'Model inputs'!AB64),IF('Model inputs'!E10="","",'Model inputs'!E10))="",0,IF(IF(IF(ISERROR('Model inputs'!F23=1),'Model inputs'!F23=1,IF('Model inputs'!F23="","",'Model inputs'!F23=1))="",FALSE,IF(ISERROR('Model inputs'!F23=1),'Model inputs'!F23=1,IF('Model inputs'!F23="","",'Model inputs'!F23=1))),IF('Model inputs'!AB64="","",'Model inputs'!AB64),IF('Model inputs'!E10="","",'Model inputs'!E10)))+'Model inputs'!F115-'Model inputs'!C37 -> -424 | G10: =IF(IF(IF(IF(ISERROR('Model inputs'!G23=1),'Model inputs'!G23=1,IF('Model inputs'!G23="","",'Model inputs'!G23=1))="",FALSE,IF(ISERROR('Model inputs'!G23=1),'Model inputs'!G23=1,IF('Model inputs'!G23="","",'Model inputs'!G23=1))),IF('Model inputs'!AB64="","",'Model inputs'!AB64),IF('Model inputs'!F10="","",'Model inputs'!F10))="",0,IF(IF(IF(ISERROR('Model inputs'!G23=1),'Model inputs'!G23=1,IF('Model inputs'!G23="","",'Model inputs'!G23=1))="",FALSE,IF(ISERROR('Model inputs'!G23=1),'Model inputs'!G23=1,IF('Model inputs'!G23="","",'Model inputs'!G23=1))),IF('Model inputs'!AB64="","",'Model inputs'!AB64),IF('Model inputs'!F10="","",'Model inputs'!F10)))+'Model inputs'!G115-'Model inputs'!C37 -> -457.44 | H10: =IF(IF(IF(IF(ISERROR('Model inputs'!H23=1),'Model inputs'!H23=1,IF('Model inputs'!H23="","",'Model inputs'!H23=1))="",FALSE,IF(ISERROR('Model inputs'!H23=1),'Model inputs'!H23=1,IF('Model inputs'!H23="","",'Model inputs'!H23=1))),IF('Model inputs'!AB64="","",'Model inputs'!AB64),IF('Model inputs'!G10="","",'Model inputs'!G10))="",0,IF(IF(IF(ISERROR('Model inputs'!H23=1),'Model inputs'!H23=1,IF('Model inputs'!H23="","",'Model inputs'!H23=1))="",FALSE,IF(ISERROR('Model inputs'!H23=1),'Model inputs'!H23=1,IF('Model inputs'!H23="","",'Model inputs'!H23=1))),IF('Model inputs'!AB64="","",'Model inputs'!AB64),IF('Model inputs'!G10="","",'Model inputs'!G10)))+'Model inputs'!H115-'Model inputs'!C37 -> -458.8928 | I10: =IF(IF(IF(IF(ISERROR('Model inputs'!I23=1),'Model inputs'!I23=1,IF('Model inputs'!I23="","",'Model inputs'!I23=1))="",FALSE,IF(ISERROR('Model inputs'!I23=1),'Model inputs'!I23=1,IF('Model inputs'!I23="","",'Model inputs'!I23=1))),IF('Model inputs'!AB64="","",'Model inputs'!AB64),IF('Model inputs'!H10="","",'Model inputs'!H10))="",0,IF(IF(IF(ISERROR('Model inputs'!I23=1),'Model inputs'!I23=1,IF('Model inputs'!I23="","",'Model inputs'!I23=1))="",FALSE,IF(ISERROR('Model inputs'!I23=1),'Model inputs'!I23=1,IF('Model inputs'!I23="","",'Model inputs'!I23=1))),IF('Model inputs'!AB64="","",'Model inputs'!AB64),IF('Model inputs'!H10="","",'Model inputs'!H10)))+'Model inputs'!I115-'Model inputs'!C37 -> -424.51994 | J10: =IF(IF(IF(IF(ISERROR('Model inputs'!J23=1),'Model inputs'!J23=1,IF('Model inputs'!J23="","",'Model inputs'!J23=1))="",FALSE,IF(ISERROR('Model inputs'!J23=1),'Model inputs'!J23=1,IF('Model inputs'!J23="","",'Model inputs'!J23=1))),IF('Model inputs'!AB64="","",'Model inputs'!AB64),IF('Model inputs'!I10="","",'Model inputs'!I10))="",0,IF(IF(IF(ISERROR('Model inputs'!J23=1),'Model inputs'!J23=1,IF('Model inputs'!J23="","",'Model inputs'!J23=1))="",FALSE,IF(ISERROR('Model inputs'!J23=1),'Model inputs'!J23=1,IF('Model inputs'!J23="","",'Model inputs'!J23=1))),IF('Model inputs'!AB64="","",'Model inputs'!AB64),IF('Model inputs'!I10="","",'Model inputs'!I10)))+'Model inputs'!J115-'Model inputs'!C37 -> -350.02233 | K10: =IF(IF(IF(IF(ISERROR('Model inputs'!K23=1),'Model inputs'!K23=1,IF('Model inputs'!K23="","",'Model inputs'!K23=1))="",FALSE,IF(ISERROR('Model inputs'!K23=1),'Model inputs'!K23=1,IF('Model inputs'!K23="","",'Model inputs'!K23=1))),IF('Model inputs'!AB64="","",'Model inputs'!AB64),IF('Model inputs'!J10="","",'Model inputs'!J10))="",0,IF(IF(IF(ISERROR('Model inputs'!K23=1),'Model inputs'!K23=1,IF('Model inputs'!K23="","",'Model inputs'!K23=1))="",FALSE,IF(ISERROR('Model inputs'!K23=1),'Model inputs'!K23=1,IF('Model inputs'!K23="","",'Model inputs'!K23=1))),IF('Model inputs'!AB64="","",'Model inputs'!AB64),IF('Model inputs'!J10="","",'Model inputs'!J10)))+'Model inputs'!K115-'Model inputs'!C37 -> -230.58501 | L10: =IF(IF(IF(IF(ISERROR('Model inputs'!L23=1),'Model inputs'!L23=1,IF('Model inputs'!L23="","",'Model inputs'!L23=1))="",FALSE,IF(ISERROR('Model inputs'!L23=1),'Model inputs'!L23=1,IF('Model inputs'!L23="","",'Model inputs'!L23=1))),IF('Model inputs'!AB64="","",'Model inputs'!AB64),IF('Model inputs'!K10="","",'Model inputs'!K10))="",0,IF(IF(IF(ISERROR('Model inputs'!L23=1),'Model inputs'!L23=1,IF('Model inputs'!L23="","",'Model inputs'!L23=1))="",FALSE,IF(ISERROR('Model inputs'!L23=1),'Model inputs'!L23=1,IF('Model inputs'!L23="","",'Model inputs'!L23=1))),IF('Model inputs'!AB64="","",'Model inputs'!AB64),IF('Model inputs'!K10="","",'Model inputs'!K10)))+'Model inputs'!L115-'Model inputs'!C37 -> -60.815209 | M10: =IF(IF(IF(IF(ISERROR('Model inputs'!M23=1),'Model inputs'!M23=1,IF('Model inputs'!M23="","",'Model inputs'!M23=1))="",FALSE,IF(ISERROR('Model inputs'!M23=1),'Model inputs'!M23=1,IF('Model inputs'!M23="","",'Model inputs'!M23=1))),IF('Model inputs'!AB64="","",'Model inputs'!AB64),IF('Model inputs'!L10="","",'Model inputs'!L10))="",0,IF(IF(IF(ISERROR('Model inputs'!M23=1),'Model inputs'!M23=1,IF('Model inputs'!M23="","",'Model inputs'!M23=1))="",FALSE,IF(ISERROR('Model inputs'!M23=1),'Model inputs'!M23=1,IF('Model inputs'!M23="","",'Model inputs'!M23=1))),IF('Model inputs'!AB64="","",'Model inputs'!AB64),IF('Model inputs'!L10="","",'Model inputs'!L10)))+'Model inputs'!M115-'Model inputs'!C37 -> 165.32697 | N10: =IF(IF(IF(IF(ISERROR('Model inputs'!N23=1),'Model inputs'!N23=1,IF('Model inputs'!N23="","",'Model inputs'!N23=1))="",FALSE,IF(ISERROR('Model inputs'!N23=1),'Model inputs'!N23=1,IF('Model inputs'!N23="","",'Model inputs'!N23=1))),IF('Model inputs'!AB64="","",'Model inputs'!AB64),IF('Model inputs'!M10="","",'Model inputs'!M10))="",0,IF(IF(IF(ISERROR('Model inputs'!N23=1),'Model inputs'!N23=1,IF('Model inputs'!N23="","",'Model inputs'!N23=1))="",FALSE,IF(ISERROR('Model inputs'!N23=1),'Model inputs'!N23=1,IF('Model inputs'!N23="","",'Model inputs'!N23=1))),IF('Model inputs'!AB64="","",'Model inputs'!AB64),IF('Model inputs'!M10="","",'Model inputs'!M10)))+'Model inputs'!N115-'Model inputs'!C37 -> 454.6062 | O10: =IF(IF(IF(IF(ISERROR('Model inputs'!O23=1),'Model inputs'!O23=1,IF('Model inputs'!O23="","",'Model inputs'!O23=1))="",FALSE,IF(ISERROR('Model inputs'!O23=1),'Model inputs'!O23=1,IF('Model inputs'!O23="","",'Model inputs'!O23=1))),IF('Model inputs'!AB64="","",'Model inputs'!AB64),IF('Model inputs'!N10="","",'Model inputs'!N10))="",0,IF(IF(IF(ISERROR('Model inputs'!O23=1),'Model inputs'!O23=1,IF('Model inputs'!O23="","",'Model inputs'!O23=1))="",FALSE,IF(ISERROR('Model inputs'!O23=1),'Model inputs'!O23=1,IF('Model inputs'!O23="","",'Model inputs'!O23=1))),IF('Model inputs'!AB64="","",'Model inputs'!AB64),IF('Model inputs'!N10="","",'Model inputs'!N10)))+'Model inputs'!O115-'Model inputs'!C37 -> 814.59895 | P10: =IF(IF(IF(IF(ISERROR('Model inputs'!P23=1),'Model inputs'!P23=1,IF('Model inputs'!P23="","",'Model inputs'!P23=1))="",FALSE,IF(ISERROR('Model inputs'!P23=1),'Model inputs'!P23=1,IF('Model inputs'!P23="","",'Model inputs'!P23=1))),IF('Model inputs'!AB64="","",'Model inputs'!AB64),IF('Model inputs'!O10="","",'Model inputs'!O10))="",0,IF(IF(IF(ISERROR('Model inputs'!P23=1),'Model inputs'!P23=1,IF('Model inputs'!P23="","",'Model inputs'!P23=1))="",FALSE,IF(ISERROR('Model inputs'!P23=1),'Model inputs'!P23=1,IF('Model inputs'!P23="","",'Model inputs'!P23=1))),IF('Model inputs'!AB64="","",'Model inputs'!AB64),IF('Model inputs'!O10="","",'Model inputs'!O10)))+'Model inputs'!P115-'Model inputs'!C37 -> 1253.7908 | Q10: =IF(IF(IF(IF(ISERROR('Model inputs'!Q23=1),'Model inputs'!Q23=1,IF('Model inputs'!Q23="","",'Model inputs'!Q23=1))="",FALSE,IF(ISERROR('Model inputs'!Q23=1),'Model inputs'!Q23=1,IF('Model inputs'!Q23="","",'Model inputs'!Q23=1))),IF('Model inputs'!AB64="","",'Model inputs'!AB64),IF('Model inputs'!P10="","",'Model inputs'!P10))="",0,IF(IF(IF(ISERROR('Model inputs'!Q23=1),'Model inputs'!Q23=1,IF('Model inputs'!Q23="","",'Model inputs'!Q23=1))="",FALSE,IF(ISERROR('Model inputs'!Q23=1),'Model inputs'!Q23=1,IF('Model inputs'!Q23="","",'Model inputs'!Q23=1))),IF('Model inputs'!AB64="","",'Model inputs'!AB64),IF('Model inputs'!P10="","",'Model inputs'!P10)))+'Model inputs'!Q115-'Model inputs'!C37 -> 1781.6857 | R10: =IF(IF(IF(IF(ISERROR('Model inputs'!R23=1),'Model inputs'!R23=1,IF('Model inputs'!R23="","",'Model inputs'!R23=1))="",FALSE,IF(ISERROR('Model inputs'!R23=1),'Model inputs'!R23=1,IF('Model inputs'!R23="","",'Model inputs'!R23=1))),IF('Model inputs'!AB64="","",'Model inputs'!AB64),IF('Model inputs'!Q10="","",'Model inputs'!Q10))="",0,IF(IF(IF(ISERROR('Model inputs'!R23=1),'Model inputs'!R23=1,IF('Model inputs'!R23="","",'Model inputs'!R23=1))="",FALSE,IF(ISERROR('Model inputs'!R23=1),'Model inputs'!R23=1,IF('Model inputs'!R23="","",'Model inputs'!R23=1))),IF('Model inputs'!AB64="","",'Model inputs'!AB64),IF('Model inputs'!Q10="","",'Model inputs'!Q10)))+'Model inputs'!R115-'Model inputs'!C37 -> 2408.928 | S10: =IF(IF(IF(IF(ISERROR('Model inputs'!S23=1),'Model inputs'!S23=1,IF('Model inputs'!S23="","",'Model inputs'!S23=1))="",FALSE,IF(ISERROR('Model inputs'!S23=1),'Model inputs'!S23=1,IF('Model inputs'!S23="","",'Model inputs'!S23=1))),IF('Model inputs'!AB64="","",'Model inputs'!AB64),IF('Model inputs'!R10="","",'Model inputs'!R10))="",0,IF(IF(IF(ISERROR('Model inputs'!S23=1),'Model inputs'!S23=1,IF('Model inputs'!S23="","",'Model inputs'!S23=1))="",FALSE,IF(ISERROR('Model inputs'!S23=1),'Model inputs'!S23=1,IF('Model inputs'!S23="","",'Model inputs'!S23=1))),IF('Model inputs'!AB64="","",'Model inputs'!AB64),IF('Model inputs'!R10="","",'Model inputs'!R10)))+'Model inputs'!S115-'Model inputs'!C37 -> 3147.4394 | T10: =IF(IF(IF(IF(ISERROR('Model inputs'!T23=1),'Model inputs'!T23=1,IF('Model inputs'!T23="","",'Model inputs'!T23=1))="",FALSE,IF(ISERROR('Model inputs'!T23=1),'Model inputs'!T23=1,IF('Model inputs'!T23="","",'Model inputs'!T23=1))),IF('Model inputs'!AB64="","",'Model inputs'!AB64),IF('Model inputs'!S10="","",'Model inputs'!S10))="",0,IF(IF(IF(ISERROR('Model inputs'!T23=1),'Model inputs'!T23=1,IF('Model inputs'!T23="","",'Model inputs'!T23=1))="",FALSE,IF(ISERROR('Model inputs'!T23=1),'Model inputs'!T23=1,IF('Model inputs'!T23="","",'Model inputs'!T23=1))),IF('Model inputs'!AB64="","",'Model inputs'!AB64),IF('Model inputs'!S10="","",'Model inputs'!S10)))+'Model inputs'!T115-'Model inputs'!C37 -> 4010.5721 | U10: =IF(IF(IF(IF(ISERROR('Model inputs'!U23=1),'Model inputs'!U23=1,IF('Model inputs'!U23="","",'Model inputs'!U23=1))="",FALSE,IF(ISERROR('Model inputs'!U23=1),'Model inputs'!U23=1,IF('Model inputs'!U23="","",'Model inputs'!U23=1))),IF('Model inputs'!AB64="","",'Model inputs'!AB64),IF('Model inputs'!T10="","",'Model inputs'!T10))="",0,IF(IF(IF(ISERROR('Model inputs'!U23=1),'Model inputs'!U23=1,IF('Model inputs'!U23="","",'Model inputs'!U23=1))="",FALSE,IF(ISERROR('Model inputs'!U23=1),'Model inputs'!U23=1,IF('Model inputs'!U23="","",'Model inputs'!U23=1))),IF('Model inputs'!AB64="","",'Model inputs'!AB64),IF('Model inputs'!T10="","",'Model inputs'!T10)))+'Model inputs'!U115-'Model inputs'!C37 -> 5013.2807 | V10: =IF(IF(IF(IF(ISERROR('Model inputs'!V23=1),'Model inputs'!V23=1,IF('Model inputs'!V23="","",'Model inputs'!V23=1))="",FALSE,IF(ISERROR('Model inputs'!V23=1),'Model inputs'!V23=1,IF('Model inputs'!V23="","",'Model inputs'!V23=1))),IF('Model inputs'!AB64="","",'Model inputs'!AB64),IF('Model inputs'!U10="","",'Model inputs'!U10))="",0,IF(IF(IF(ISERROR('Model inputs'!V23=1),'Model inputs'!V23=1,IF('Model inputs'!V23="","",'Model inputs'!V23=1))="",FALSE,IF(ISERROR('Model inputs'!V23=1),'Model inputs'!V23=1,IF('Model inputs'!V23="","",'Model inputs'!V23=1))),IF('Model inputs'!AB64="","",'Model inputs'!AB64),IF('Model inputs'!U10="","",'Model inputs'!U10)))+'Model inputs'!V115-'Model inputs'!C37 -> 6172.3144 | W10: =IF(IF(IF(IF(ISERROR('Model inputs'!W23=1),'Model inputs'!W23=1,IF('Model inputs'!W23="","",'Model inputs'!W23=1))="",FALSE,IF(ISERROR('Model inputs'!W23=1),'Model inputs'!W23=1,IF('Model inputs'!W23="","",'Model inputs'!W23=1))),IF('Model inputs'!AB64="","",'Model inputs'!AB64),IF('Model inputs'!V10="","",'Model inputs'!V10))="",0,IF(IF(IF(ISERROR('Model inputs'!W23=1),'Model inputs'!W23=1,IF('Model inputs'!W23="","",'Model inputs'!W23=1))="",FALSE,IF(ISERROR('Model inputs'!W23=1),'Model inputs'!W23=1,IF('Model inputs'!W23="","",'Model inputs'!W23=1))),IF('Model inputs'!AB64="","",'Model inputs'!AB64),IF('Model inputs'!V10="","",'Model inputs'!V10)))+'Model inputs'!W115-'Model inputs'!C37 -> 7506.4322 | X10: =IF(IF(IF(IF(ISERROR('Model inputs'!X23=1),'Model inputs'!X23=1,IF('Model inputs'!X23="","",'Model inputs'!X23=1))="",FALSE,IF(ISERROR('Model inputs'!X23=1),'Model inputs'!X23=1,IF('Model inputs'!X23="","",'Model inputs'!X23=1))),IF('Model inputs'!AB64="","",'Model inputs'!AB64),IF('Model inputs'!W10="","",'Model inputs'!W10))="",0,IF(IF(IF(ISERROR('Model inputs'!X23=1),'Model inputs'!X23=1,IF('Model inputs'!X23="","",'Model inputs'!X23=1))="",FALSE,IF(ISERROR('Model inputs'!X23=1),'Model inputs'!X23=1,IF('Model inputs'!X23="","",'Model inputs'!X23=1))),IF('Model inputs'!AB64="","",'Model inputs'!AB64),IF('Model inputs'!W10="","",'Model inputs'!W10)))+'Model inputs'!X115-'Model inputs'!C37 -> 9036.644 | Y10: =IF(IF(IF(IF(ISERROR('Model inputs'!Y23=1),'Model inputs'!Y23=1,IF('Model inputs'!Y23="","",'Model inputs'!Y23=1))="",FALSE,IF(ISERROR('Model inputs'!Y23=1),'Model inputs'!Y23=1,IF('Model inputs'!Y23="","",'Model inputs'!Y23=1))),IF('Model inputs'!AB64="","",'Model inputs'!AB64),IF('Model inputs'!X10="","",'Model inputs'!X10))="",0,IF(IF(IF(ISERROR('Model inputs'!Y23=1),'Model inputs'!Y23=1,IF('Model inputs'!Y23="","",'Model inputs'!Y23=1))="",FALSE,IF(ISERROR('Model inputs'!Y23=1),'Model inputs'!Y23=1,IF('Model inputs'!Y23="","",'Model inputs'!Y23=1))),IF('Model inputs'!AB64="","",'Model inputs'!AB64),IF('Model inputs'!X10="","",'Model inputs'!X10)))+'Model inputs'!Y115-'Model inputs'!C37 -> 10786.481 | Z10: =IF(IF(IF(IF(ISERROR('Model inputs'!Z23=1),'Model inputs'!Z23=1,IF('Model inputs'!Z23="","",'Model inputs'!Z23=1))="",FALSE,IF(ISERROR('Model inputs'!Z23=1),'Model inputs'!Z23=1,IF('Model inputs'!Z23="","",'Model inputs'!Z23=1))),IF('Model inputs'!AB64="","",'Model inputs'!AB64),IF('Model inputs'!Y10="","",'Model inputs'!Y10))="",0,IF(IF(IF(ISERROR('Model inputs'!Z23=1),'Model inputs'!Z23=1,IF('Model inputs'!Z23="","",'Model inputs'!Z23=1))="",FALSE,IF(ISERROR('Model inputs'!Z23=1),'Model inputs'!Z23=1,IF('Model inputs'!Z23="","",'Model inputs'!Z23=1))),IF('Model inputs'!AB64="","",'Model inputs'!AB64),IF('Model inputs'!Y10="","",'Model inputs'!Y10)))+'Model inputs'!Z115-'Model inputs'!C37 -> 12782.299
A11: Cash at stress migration cost | B11: =IF(IF(IF(IF(ISERROR('Model inputs'!B23=1),'Model inputs'!B23=1,IF('Model inputs'!B23="","",'Model inputs'!B23=1))="",FALSE,IF(ISERROR('Model inputs'!B23=1),'Model inputs'!B23=1,IF('Model inputs'!B23="","",'Model inputs'!B23=1))),IF('Model inputs'!AB64="","",'Model inputs'!AB64),IF('Model inputs'!Z11="","",'Model inputs'!Z11))="",0,IF(IF(IF(ISERROR('Model inputs'!B23=1),'Model inputs'!B23=1,IF('Model inputs'!B23="","",'Model inputs'!B23=1))="",FALSE,IF(ISERROR('Model inputs'!B23=1),'Model inputs'!B23=1,IF('Model inputs'!B23="","",'Model inputs'!B23=1))),IF('Model inputs'!AB64="","",'Model inputs'!AB64),IF('Model inputs'!Z11="","",'Model inputs'!Z11)))+'Model inputs'!B116-'Model inputs'!C37 -> 33754.132 | D11: =IF(IF(IF(IF(ISERROR('Model inputs'!D23=1),'Model inputs'!D23=1,IF('Model inputs'!D23="","",'Model inputs'!D23=1))="",FALSE,IF(ISERROR('Model inputs'!D23=1),'Model inputs'!D23=1,IF('Model inputs'!D23="","",'Model inputs'!D23=1))),IF('Model inputs'!AB64="","",'Model inputs'!AB64),IF('Model inputs'!AA79="","",'Model inputs'!AA79))="",0,IF(IF(IF(ISERROR('Model inputs'!D23=1),'Model inputs'!D23=1,IF('Model inputs'!D23="","",'Model inputs'!D23=1))="",FALSE,IF(ISERROR('Model inputs'!D23=1),'Model inputs'!D23=1,IF('Model inputs'!D23="","",'Model inputs'!D23=1))),IF('Model inputs'!AB64="","",'Model inputs'!AB64),IF('Model inputs'!AA79="","",'Model inputs'!AA79)))+'Model inputs'!D116-'Model inputs'!C37 -> -154 | E11: =IF(IF(IF(IF(ISERROR('Model inputs'!E23=1),'Model inputs'!E23=1,IF('Model inputs'!E23="","",'Model inputs'!E23=1))="",FALSE,IF(ISERROR('Model inputs'!E23=1),'Model inputs'!E23=1,IF('Model inputs'!E23="","",'Model inputs'!E23=1))),IF('Model inputs'!AB64="","",'Model inputs'!AB64),IF('Model inputs'!D11="","",'Model inputs'!D11))="",0,IF(IF(IF(ISERROR('Model inputs'!E23=1),'Model inputs'!E23=1,IF('Model inputs'!E23="","",'Model inputs'!E23=1))="",FALSE,IF(ISERROR('Model inputs'!E23=1),'Model inputs'!E23=1,IF('Model inputs'!E23="","",'Model inputs'!E23=1))),IF('Model inputs'!AB64="","",'Model inputs'!AB64),IF('Model inputs'!D11="","",'Model inputs'!D11)))+'Model inputs'!E116-'Model inputs'!C37 -> -162 | F11: =IF(IF(IF(IF(ISERROR('Model inputs'!F23=1),'Model inputs'!F23=1,IF('Model inputs'!F23="","",'Model inputs'!F23=1))="",FALSE,IF(ISERROR('Model inputs'!F23=1),'Model inputs'!F23=1,IF('Model inputs'!F23="","",'Model inputs'!F23=1))),IF('Model inputs'!AB64="","",'Model inputs'!AB64),IF('Model inputs'!E11="","",'Model inputs'!E11))="",0,IF(IF(IF(ISERROR('Model inputs'!F23=1),'Model inputs'!F23=1,IF('Model inputs'!F23="","",'Model inputs'!F23=1))="",FALSE,IF(ISERROR('Model inputs'!F23=1),'Model inputs'!F23=1,IF('Model inputs'!F23="","",'Model inputs'!F23=1))),IF('Model inputs'!AB64="","",'Model inputs'!AB64),IF('Model inputs'!E11="","",'Model inputs'!E11)))+'Model inputs'!F116-'Model inputs'!C37 -> -24 | G11: =IF(IF(IF(IF(ISERROR('Model inputs'!G23=1),'Model inputs'!G23=1,IF('Model inputs'!G23="","",'Model inputs'!G23=1))="",FALSE,IF(ISERROR('Model inputs'!G23=1),'Model inputs'!G23=1,IF('Model inputs'!G23="","",'Model inputs'!G23=1))),IF('Model inputs'!AB64="","",'Model inputs'!AB64),IF('Model inputs'!F11="","",'Model inputs'!F11))="",0,IF(IF(IF(ISERROR('Model inputs'!G23=1),'Model inputs'!G23=1,IF('Model inputs'!G23="","",'Model inputs'!G23=1))="",FALSE,IF(ISERROR('Model inputs'!G23=1),'Model inputs'!G23=1,IF('Model inputs'!G23="","",'Model inputs'!G23=1))),IF('Model inputs'!AB64="","",'Model inputs'!AB64),IF('Model inputs'!F11="","",'Model inputs'!F11)))+'Model inputs'!G116-'Model inputs'!C37 -> 166.56 | H11: =IF(IF(IF(IF(ISERROR('Model inputs'!H23=1),'Model inputs'!H23=1,IF('Model inputs'!H23="","",'Model inputs'!H23=1))="",FALSE,IF(ISERROR('Model inputs'!H23=1),'Model inputs'!H23=1,IF('Model inputs'!H23="","",'Model inputs'!H23=1))),IF('Model inputs'!AB64="","",'Model inputs'!AB64),IF('Model inputs'!G11="","",'Model inputs'!G11))="",0,IF(IF(IF(ISERROR('Model inputs'!H23=1),'Model inputs'!H23=1,IF('Model inputs'!H23="","",'Model inputs'!H23=1))="",FALSE,IF(ISERROR('Model inputs'!H23=1),'Model inputs'!H23=1,IF('Model inputs'!H23="","",'Model inputs'!H23=1))),IF('Model inputs'!AB64="","",'Model inputs'!AB64),IF('Model inputs'!G11="","",'Model inputs'!G11)))+'Model inputs'!H116-'Model inputs'!C37 -> 415.9872 | I11: =IF(IF(IF(IF(ISERROR('Model inputs'!I23=1),'Model inputs'!I23=1,IF('Model inputs'!I23="","",'Model inputs'!I23=1))="",FALSE,IF(ISERROR('Model inputs'!I23=1),'Model inputs'!I23=1,IF('Model inputs'!I23="","",'Model inputs'!I23=1))),IF('Model inputs'!AB64="","",'Model inputs'!AB64),IF('Model inputs'!H11="","",'Model inputs'!H11))="",0,IF(IF(IF(ISERROR('Model inputs'!I23=1),'Model inputs'!I23=1,IF('Model inputs'!I23="","",'Model inputs'!I23=1))="",FALSE,IF(ISERROR('Model inputs'!I23=1),'Model inputs'!I23=1,IF('Model inputs'!I23="","",'Model inputs'!I23=1))),IF('Model inputs'!AB64="","",'Model inputs'!AB64),IF('Model inputs'!H11="","",'Model inputs'!H11)))+'Model inputs'!I116-'Model inputs'!C37 -> 731.34566 | J11: =IF(IF(IF(IF(ISERROR('Model inputs'!J23=1),'Model inputs'!J23=1,IF('Model inputs'!J23="","",'Model inputs'!J23=1))="",FALSE,IF(ISERROR('Model inputs'!J23=1),'Model inputs'!J23=1,IF('Model inputs'!J23="","",'Model inputs'!J23=1))),IF('Model inputs'!AB64="","",'Model inputs'!AB64),IF('Model inputs'!I11="","",'Model inputs'!I11))="",0,IF(IF(IF(ISERROR('Model inputs'!J23=1),'Model inputs'!J23=1,IF('Model inputs'!J23="","",'Model inputs'!J23=1))="",FALSE,IF(ISERROR('Model inputs'!J23=1),'Model inputs'!J23=1,IF('Model inputs'!J23="","",'Model inputs'!J23=1))),IF('Model inputs'!AB64="","",'Model inputs'!AB64),IF('Model inputs'!I11="","",'Model inputs'!I11)))+'Model inputs'!J116-'Model inputs'!C37 -> 1120.5471 | K11: =IF(IF(IF(IF(ISERROR('Model inputs'!K23=1),'Model inputs'!K23=1,IF('Model inputs'!K23="","",'Model inputs'!K23=1))="",FALSE,IF(ISERROR('Model inputs'!K23=1),'Model inputs'!K23=1,IF('Model inputs'!K23="","",'Model inputs'!K23=1))),IF('Model inputs'!AB64="","",'Model inputs'!AB64),IF('Model inputs'!J11="","",'Model inputs'!J11))="",0,IF(IF(IF(ISERROR('Model inputs'!K23=1),'Model inputs'!K23=1,IF('Model inputs'!K23="","",'Model inputs'!K23=1))="",FALSE,IF(ISERROR('Model inputs'!K23=1),'Model inputs'!K23=1,IF('Model inputs'!K23="","",'Model inputs'!K23=1))),IF('Model inputs'!AB64="","",'Model inputs'!AB64),IF('Model inputs'!J11="","",'Model inputs'!J11)))+'Model inputs'!K116-'Model inputs'!C37 -> 1592.4528 | L11: =IF(IF(IF(IF(ISERROR('Model inputs'!L23=1),'Model inputs'!L23=1,IF('Model inputs'!L23="","",'Model inputs'!L23=1))="",FALSE,IF(ISERROR('Model inputs'!L23=1),'Model inputs'!L23=1,IF('Model inputs'!L23="","",'Model inputs'!L23=1))),IF('Model inputs'!AB64="","",'Model inputs'!AB64),IF('Model inputs'!K11="","",'Model inputs'!K11))="",0,IF(IF(IF(ISERROR('Model inputs'!L23=1),'Model inputs'!L23=1,IF('Model inputs'!L23="","",'Model inputs'!L23=1))="",FALSE,IF(ISERROR('Model inputs'!L23=1),'Model inputs'!L23=1,IF('Model inputs'!L23="","",'Model inputs'!L23=1))),IF('Model inputs'!AB64="","",'Model inputs'!AB64),IF('Model inputs'!K11="","",'Model inputs'!K11)))+'Model inputs'!L116-'Model inputs'!C37 -> 2156.9871 | M11: =IF(IF(IF(IF(ISERROR('Model inputs'!M23=1),'Model inputs'!M23=1,IF('Model inputs'!M23="","",'Model inputs'!M23=1))="",FALSE,IF(ISERROR('Model inputs'!M23=1),'Model inputs'!M23=1,IF('Model inputs'!M23="","",'Model inputs'!M23=1))),IF('Model inputs'!AB64="","",'Model inputs'!AB64),IF('Model inputs'!L11="","",'Model inputs'!L11))="",0,IF(IF(IF(ISERROR('Model inputs'!M23=1),'Model inputs'!M23=1,IF('Model inputs'!M23="","",'Model inputs'!M23=1))="",FALSE,IF(ISERROR('Model inputs'!M23=1),'Model inputs'!M23=1,IF('Model inputs'!M23="","",'Model inputs'!M23=1))),IF('Model inputs'!AB64="","",'Model inputs'!AB64),IF('Model inputs'!L11="","",'Model inputs'!L11)))+'Model inputs'!M116-'Model inputs'!C37 -> 2825.2656 | N11: =IF(IF(IF(IF(ISERROR('Model inputs'!N23=1),'Model inputs'!N23=1,IF('Model inputs'!N23="","",'Model inputs'!N23=1))="",FALSE,IF(ISERROR('Model inputs'!N23=1),'Model inputs'!N23=1,IF('Model inputs'!N23="","",'Model inputs'!N23=1))),IF('Model inputs'!AB64="","",'Model inputs'!AB64),IF('Model inputs'!M11="","",'Model inputs'!M11))="",0,IF(IF(IF(ISERROR('Model inputs'!N23=1),'Model inputs'!N23=1,IF('Model inputs'!N23="","",'Model inputs'!N23=1))="",FALSE,IF(ISERROR('Model inputs'!N23=1),'Model inputs'!N23=1,IF('Model inputs'!N23="","",'Model inputs'!N23=1))),IF('Model inputs'!AB64="","",'Model inputs'!AB64),IF('Model inputs'!M11="","",'Model inputs'!M11)))+'Model inputs'!N116-'Model inputs'!C37 -> 3609.7375 | O11: =IF(IF(IF(IF(ISERROR('Model inputs'!O23=1),'Model inputs'!O23=1,IF('Model inputs'!O23="","",'Model inputs'!O23=1))="",FALSE,IF(ISERROR('Model inputs'!O23=1),'Model inputs'!O23=1,IF('Model inputs'!O23="","",'Model inputs'!O23=1))),IF('Model inputs'!AB64="","",'Model inputs'!AB64),IF('Model inputs'!N11="","",'Model inputs'!N11))="",0,IF(IF(IF(ISERROR('Model inputs'!O23=1),'Model inputs'!O23=1,IF('Model inputs'!O23="","",'Model inputs'!O23=1))="",FALSE,IF(ISERROR('Model inputs'!O23=1),'Model inputs'!O23=1,IF('Model inputs'!O23="","",'Model inputs'!O23=1))),IF('Model inputs'!AB64="","",'Model inputs'!AB64),IF('Model inputs'!N11="","",'Model inputs'!N11)))+'Model inputs'!O116-'Model inputs'!C37 -> 4524.346 | P11: =IF(IF(IF(IF(ISERROR('Model inputs'!P23=1),'Model inputs'!P23=1,IF('Model inputs'!P23="","",'Model inputs'!P23=1))="",FALSE,IF(ISERROR('Model inputs'!P23=1),'Model inputs'!P23=1,IF('Model inputs'!P23="","",'Model inputs'!P23=1))),IF('Model inputs'!AB64="","",'Model inputs'!AB64),IF('Model inputs'!O11="","",'Model inputs'!O11))="",0,IF(IF(IF(ISERROR('Model inputs'!P23=1),'Model inputs'!P23=1,IF('Model inputs'!P23="","",'Model inputs'!P23=1))="",FALSE,IF(ISERROR('Model inputs'!P23=1),'Model inputs'!P23=1,IF('Model inputs'!P23="","",'Model inputs'!P23=1))),IF('Model inputs'!AB64="","",'Model inputs'!AB64),IF('Model inputs'!O11="","",'Model inputs'!O11)))+'Model inputs'!P116-'Model inputs'!C37 -> 5584.7075 | Q11: =IF(IF(IF(IF(ISERROR('Model inputs'!Q23=1),'Model inputs'!Q23=1,IF('Model inputs'!Q23="","",'Model inputs'!Q23=1))="",FALSE,IF(ISERROR('Model inputs'!Q23=1),'Model inputs'!Q23=1,IF('Model inputs'!Q23="","",'Model inputs'!Q23=1))),IF('Model inputs'!AB64="","",'Model inputs'!AB64),IF('Model inputs'!P11="","",'Model inputs'!P11))="",0,IF(IF(IF(ISERROR('Model inputs'!Q23=1),'Model inputs'!Q23=1,IF('Model inputs'!Q23="","",'Model inputs'!Q23=1))="",FALSE,IF(ISERROR('Model inputs'!Q23=1),'Model inputs'!Q23=1,IF('Model inputs'!Q23="","",'Model inputs'!Q23=1))),IF('Model inputs'!AB64="","",'Model inputs'!AB64),IF('Model inputs'!P11="","",'Model inputs'!P11)))+'Model inputs'!Q116-'Model inputs'!C37 -> 6808.3124 | R11: =IF(IF(IF(IF(ISERROR('Model inputs'!R23=1),'Model inputs'!R23=1,IF('Model inputs'!R23="","",'Model inputs'!R23=1))="",FALSE,IF(ISERROR('Model inputs'!R23=1),'Model inputs'!R23=1,IF('Model inputs'!R23="","",'Model inputs'!R23=1))),IF('Model inputs'!AB64="","",'Model inputs'!AB64),IF('Model inputs'!Q11="","",'Model inputs'!Q11))="",0,IF(IF(IF(ISERROR('Model inputs'!R23=1),'Model inputs'!R23=1,IF('Model inputs'!R23="","",'Model inputs'!R23=1))="",FALSE,IF(ISERROR('Model inputs'!R23=1),'Model inputs'!R23=1,IF('Model inputs'!R23="","",'Model inputs'!R23=1))),IF('Model inputs'!AB64="","",'Model inputs'!AB64),IF('Model inputs'!Q11="","",'Model inputs'!Q11)))+'Model inputs'!R116-'Model inputs'!C37 -> 8214.7499 | S11: =IF(IF(IF(IF(ISERROR('Model inputs'!S23=1),'Model inputs'!S23=1,IF('Model inputs'!S23="","",'Model inputs'!S23=1))="",FALSE,IF(ISERROR('Model inputs'!S23=1),'Model inputs'!S23=1,IF('Model inputs'!S23="","",'Model inputs'!S23=1))),IF('Model inputs'!AB64="","",'Model inputs'!AB64),IF('Model inputs'!R11="","",'Model inputs'!R11))="",0,IF(IF(IF(ISERROR('Model inputs'!S23=1),'Model inputs'!S23=1,IF('Model inputs'!S23="","",'Model inputs'!S23=1))="",FALSE,IF(ISERROR('Model inputs'!S23=1),'Model inputs'!S23=1,IF('Model inputs'!S23="","",'Model inputs'!S23=1))),IF('Model inputs'!AB64="","",'Model inputs'!AB64),IF('Model inputs'!R11="","",'Model inputs'!R11)))+'Model inputs'!S116-'Model inputs'!C37 -> 9825.9598 | T11: =IF(IF(IF(IF(ISERROR('Model inputs'!T23=1),'Model inputs'!T23=1,IF('Model inputs'!T23="","",'Model inputs'!T23=1))="",FALSE,IF(ISERROR('Model inputs'!T23=1),'Model inputs'!T23=1,IF('Model inputs'!T23="","",'Model inputs'!T23=1))),IF('Model inputs'!AB64="","",'Model inputs'!AB64),IF('Model inputs'!S11="","",'Model inputs'!S11))="",0,IF(IF(IF(ISERROR('Model inputs'!T23=1),'Model inputs'!T23=1,IF('Model inputs'!T23="","",'Model inputs'!T23=1))="",FALSE,IF(ISERROR('Model inputs'!T23=1),'Model inputs'!T23=1,IF('Model inputs'!T23="","",'Model inputs'!T23=1))),IF('Model inputs'!AB64="","",'Model inputs'!AB64),IF('Model inputs'!S11="","",'Model inputs'!S11)))+'Model inputs'!T116-'Model inputs'!C37 -> 11666.515 | U11: =IF(IF(IF(IF(ISERROR('Model inputs'!U23=1),'Model inputs'!U23=1,IF('Model inputs'!U23="","",'Model inputs'!U23=1))="",FALSE,IF(ISERROR('Model inputs'!U23=1),'Model inputs'!U23=1,IF('Model inputs'!U23="","",'Model inputs'!U23=1))),IF('Model inputs'!AB64="","",'Model inputs'!AB64),IF('Model inputs'!T11="","",'Model inputs'!T11))="",0,IF(IF(IF(ISERROR('Model inputs'!U23=1),'Model inputs'!U23=1,IF('Model inputs'!U23="","",'Model inputs'!U23=1))="",FALSE,IF(ISERROR('Model inputs'!U23=1),'Model inputs'!U23=1,IF('Model inputs'!U23="","",'Model inputs'!U23=1))),IF('Model inputs'!AB64="","",'Model inputs'!AB64),IF('Model inputs'!T11="","",'Model inputs'!T11)))+'Model inputs'!U116-'Model inputs'!C37 -> 13763.937 | V11: =IF(IF(IF(IF(ISERROR('Model inputs'!V23=1),'Model inputs'!V23=1,IF('Model inputs'!V23="","",'Model inputs'!V23=1))="",FALSE,IF(ISERROR('Model inputs'!V23=1),'Model inputs'!V23=1,IF('Model inputs'!V23="","",'Model inputs'!V23=1))),IF('Model inputs'!AB64="","",'Model inputs'!AB64),IF('Model inputs'!U11="","",'Model inputs'!U11))="",0,IF(IF(IF(ISERROR('Model inputs'!V23=1),'Model inputs'!V23=1,IF('Model inputs'!V23="","",'Model inputs'!V23=1))="",FALSE,IF(ISERROR('Model inputs'!V23=1),'Model inputs'!V23=1,IF('Model inputs'!V23="","",'Model inputs'!V23=1))),IF('Model inputs'!AB64="","",'Model inputs'!AB64),IF('Model inputs'!U11="","",'Model inputs'!U11)))+'Model inputs'!V116-'Model inputs'!C37 -> 16149.049 | W11: =IF(IF(IF(IF(ISERROR('Model inputs'!W23=1),'Model inputs'!W23=1,IF('Model inputs'!W23="","",'Model inputs'!W23=1))="",FALSE,IF(ISERROR('Model inputs'!W23=1),'Model inputs'!W23=1,IF('Model inputs'!W23="","",'Model inputs'!W23=1))),IF('Model inputs'!AB64="","",'Model inputs'!AB64),IF('Model inputs'!V11="","",'Model inputs'!V11))="",0,IF(IF(IF(ISERROR('Model inputs'!W23=1),'Model inputs'!W23=1,IF('Model inputs'!W23="","",'Model inputs'!W23=1))="",FALSE,IF(ISERROR('Model inputs'!W23=1),'Model inputs'!W23=1,IF('Model inputs'!W23="","",'Model inputs'!W23=1))),IF('Model inputs'!AB64="","",'Model inputs'!AB64),IF('Model inputs'!V11="","",'Model inputs'!V11)))+'Model inputs'!W116-'Model inputs'!C37 -> 18856.375 | X11: =IF(IF(IF(IF(ISERROR('Model inputs'!X23=1),'Model inputs'!X23=1,IF('Model inputs'!X23="","",'Model inputs'!X23=1))="",FALSE,IF(ISERROR('Model inputs'!X23=1),'Model inputs'!X23=1,IF('Model inputs'!X23="","",'Model inputs'!X23=1))),IF('Model inputs'!AB64="","",'Model inputs'!AB64),IF('Model inputs'!W11="","",'Model inputs'!W11))="",0,IF(IF(IF(ISERROR('Model inputs'!X23=1),'Model inputs'!X23=1,IF('Model inputs'!X23="","",'Model inputs'!X23=1))="",FALSE,IF(ISERROR('Model inputs'!X23=1),'Model inputs'!X23=1,IF('Model inputs'!X23="","",'Model inputs'!X23=1))),IF('Model inputs'!AB64="","",'Model inputs'!AB64),IF('Model inputs'!W11="","",'Model inputs'!W11)))+'Model inputs'!X116-'Model inputs'!C37 -> 21924.58 | Y11: =IF(IF(IF(IF(ISERROR('Model inputs'!Y23=1),'Model inputs'!Y23=1,IF('Model inputs'!Y23="","",'Model inputs'!Y23=1))="",FALSE,IF(ISERROR('Model inputs'!Y23=1),'Model inputs'!Y23=1,IF('Model inputs'!Y23="","",'Model inputs'!Y23=1))),IF('Model inputs'!AB64="","",'Model inputs'!AB64),IF('Model inputs'!X11="","",'Model inputs'!X11))="",0,IF(IF(IF(ISERROR('Model inputs'!Y23=1),'Model inputs'!Y23=1,IF('Model inputs'!Y23="","",'Model inputs'!Y23=1))="",FALSE,IF(ISERROR('Model inputs'!Y23=1),'Model inputs'!Y23=1,IF('Model inputs'!Y23="","",'Model inputs'!Y23=1))),IF('Model inputs'!AB64="","",'Model inputs'!AB64),IF('Model inputs'!X11="","",'Model inputs'!X11)))+'Model inputs'!Y116-'Model inputs'!C37 -> 25396.97 | Z11: =IF(IF(IF(IF(ISERROR('Model inputs'!Z23=1),'Model inputs'!Z23=1,IF('Model inputs'!Z23="","",'Model inputs'!Z23=1))="",FALSE,IF(ISERROR('Model inputs'!Z23=1),'Model inputs'!Z23=1,IF('Model inputs'!Z23="","",'Model inputs'!Z23=1))),IF('Model inputs'!AB64="","",'Model inputs'!AB64),IF('Model inputs'!Y11="","",'Model inputs'!Y11))="",0,IF(IF(IF(ISERROR('Model inputs'!Z23=1),'Model inputs'!Z23=1,IF('Model inputs'!Z23="","",'Model inputs'!Z23=1))="",FALSE,IF(ISERROR('Model inputs'!Z23=1),'Model inputs'!Z23=1,IF('Model inputs'!Z23="","",'Model inputs'!Z23=1))),IF('Model inputs'!AB64="","",'Model inputs'!AB64),IF('Model inputs'!Y11="","",'Model inputs'!Y11)))+'Model inputs'!Z116-'Model inputs'!C37 -> 29322.046
A12: Cash at stress price | B12: =IF(IF(IF(IF(ISERROR('Model inputs'!B23=1),'Model inputs'!B23=1,IF('Model inputs'!B23="","",'Model inputs'!B23=1))="",FALSE,IF(ISERROR('Model inputs'!B23=1),'Model inputs'!B23=1,IF('Model inputs'!B23="","",'Model inputs'!B23=1))),IF('Model inputs'!AB64="","",'Model inputs'!AB64),IF('Model inputs'!Z12="","",'Model inputs'!Z12))="",0,IF(IF(IF(ISERROR('Model inputs'!B23=1),'Model inputs'!B23=1,IF('Model inputs'!B23="","",'Model inputs'!B23=1))="",FALSE,IF(ISERROR('Model inputs'!B23=1),'Model inputs'!B23=1,IF('Model inputs'!B23="","",'Model inputs'!B23=1))),IF('Model inputs'!AB64="","",'Model inputs'!AB64),IF('Model inputs'!Z12="","",'Model inputs'!Z12)))+'Model inputs'!B117-'Model inputs'!C37 -> 17858.692 | D12: =IF(IF(IF(IF(ISERROR('Model inputs'!D23=1),'Model inputs'!D23=1,IF('Model inputs'!D23="","",'Model inputs'!D23=1))="",FALSE,IF(ISERROR('Model inputs'!D23=1),'Model inputs'!D23=1,IF('Model inputs'!D23="","",'Model inputs'!D23=1))),IF('Model inputs'!AB64="","",'Model inputs'!AB64),IF('Model inputs'!AA80="","",'Model inputs'!AA80))="",0,IF(IF(IF(ISERROR('Model inputs'!D23=1),'Model inputs'!D23=1,IF('Model inputs'!D23="","",'Model inputs'!D23=1))="",FALSE,IF(ISERROR('Model inputs'!D23=1),'Model inputs'!D23=1,IF('Model inputs'!D23="","",'Model inputs'!D23=1))),IF('Model inputs'!AB64="","",'Model inputs'!AB64),IF('Model inputs'!AA80="","",'Model inputs'!AA80)))+'Model inputs'!D117-'Model inputs'!C37 -> -210.66667 | E12: =IF(IF(IF(IF(ISERROR('Model inputs'!E23=1),'Model inputs'!E23=1,IF('Model inputs'!E23="","",'Model inputs'!E23=1))="",FALSE,IF(ISERROR('Model inputs'!E23=1),'Model inputs'!E23=1,IF('Model inputs'!E23="","",'Model inputs'!E23=1))),IF('Model inputs'!AB64="","",'Model inputs'!AB64),IF('Model inputs'!D12="","",'Model inputs'!D12))="",0,IF(IF(IF(ISERROR('Model inputs'!E23=1),'Model inputs'!E23=1,IF('Model inputs'!E23="","",'Model inputs'!E23=1))="",FALSE,IF(ISERROR('Model inputs'!E23=1),'Model inputs'!E23=1,IF('Model inputs'!E23="","",'Model inputs'!E23=1))),IF('Model inputs'!AB64="","",'Model inputs'!AB64),IF('Model inputs'!D12="","",'Model inputs'!D12)))+'Model inputs'!E117-'Model inputs'!C37 -> -332 | F12: =IF(IF(IF(IF(ISERROR('Model inputs'!F23=1),'Model inputs'!F23=1,IF('Model inputs'!F23="","",'Model inputs'!F23=1))="",FALSE,IF(ISERROR('Model inputs'!F23=1),'Model inputs'!F23=1,IF('Model inputs'!F23="","",'Model inputs'!F23=1))),IF('Model inputs'!AB64="","",'Model inputs'!AB64),IF('Model inputs'!E12="","",'Model inputs'!E12))="",0,IF(IF(IF(ISERROR('Model inputs'!F23=1),'Model inputs'!F23=1,IF('Model inputs'!F23="","",'Model inputs'!F23=1))="",FALSE,IF(ISERROR('Model inputs'!F23=1),'Model inputs'!F23=1,IF('Model inputs'!F23="","",'Model inputs'!F23=1))),IF('Model inputs'!AB64="","",'Model inputs'!AB64),IF('Model inputs'!E12="","",'Model inputs'!E12)))+'Model inputs'!F117-'Model inputs'!C37 -> -364 | G12: =IF(IF(IF(IF(ISERROR('Model inputs'!G23=1),'Model inputs'!G23=1,IF('Model inputs'!G23="","",'Model inputs'!G23=1))="",FALSE,IF(ISERROR('Model inputs'!G23=1),'Model inputs'!G23=1,IF('Model inputs'!G23="","",'Model inputs'!G23=1))),IF('Model inputs'!AB64="","",'Model inputs'!AB64),IF('Model inputs'!F12="","",'Model inputs'!F12))="",0,IF(IF(IF(ISERROR('Model inputs'!G23=1),'Model inputs'!G23=1,IF('Model inputs'!G23="","",'Model inputs'!G23=1))="",FALSE,IF(ISERROR('Model inputs'!G23=1),'Model inputs'!G23=1,IF('Model inputs'!G23="","",'Model inputs'!G23=1))),IF('Model inputs'!AB64="","",'Model inputs'!AB64),IF('Model inputs'!F12="","",'Model inputs'!F12)))+'Model inputs'!G117-'Model inputs'!C37 -> -363.84 | H12: =IF(IF(IF(IF(ISERROR('Model inputs'!H23=1),'Model inputs'!H23=1,IF('Model inputs'!H23="","",'Model inputs'!H23=1))="",FALSE,IF(ISERROR('Model inputs'!H23=1),'Model inputs'!H23=1,IF('Model inputs'!H23="","",'Model inputs'!H23=1))),IF('Model inputs'!AB64="","",'Model inputs'!AB64),IF('Model inputs'!G12="","",'Model inputs'!G12))="",0,IF(IF(IF(ISERROR('Model inputs'!H23=1),'Model inputs'!H23=1,IF('Model inputs'!H23="","",'Model inputs'!H23=1))="",FALSE,IF(ISERROR('Model inputs'!H23=1),'Model inputs'!H23=1,IF('Model inputs'!H23="","",'Model inputs'!H23=1))),IF('Model inputs'!AB64="","",'Model inputs'!AB64),IF('Model inputs'!G12="","",'Model inputs'!G12)))+'Model inputs'!H117-'Model inputs'!C37 -> -327.6608 | I12: =IF(IF(IF(IF(ISERROR('Model inputs'!I23=1),'Model inputs'!I23=1,IF('Model inputs'!I23="","",'Model inputs'!I23=1))="",FALSE,IF(ISERROR('Model inputs'!I23=1),'Model inputs'!I23=1,IF('Model inputs'!I23="","",'Model inputs'!I23=1))),IF('Model inputs'!AB64="","",'Model inputs'!AB64),IF('Model inputs'!H12="","",'Model inputs'!H12))="",0,IF(IF(IF(ISERROR('Model inputs'!I23=1),'Model inputs'!I23=1,IF('Model inputs'!I23="","",'Model inputs'!I23=1))="",FALSE,IF(ISERROR('Model inputs'!I23=1),'Model inputs'!I23=1,IF('Model inputs'!I23="","",'Model inputs'!I23=1))),IF('Model inputs'!AB64="","",'Model inputs'!AB64),IF('Model inputs'!H12="","",'Model inputs'!H12)))+'Model inputs'!I117-'Model inputs'!C37 -> -251.1401 | J12: =IF(IF(IF(IF(ISERROR('Model inputs'!J23=1),'Model inputs'!J23=1,IF('Model inputs'!J23="","",'Model inputs'!J23=1))="",FALSE,IF(ISERROR('Model inputs'!J23=1),'Model inputs'!J23=1,IF('Model inputs'!J23="","",'Model inputs'!J23=1))),IF('Model inputs'!AB64="","",'Model inputs'!AB64),IF('Model inputs'!I12="","",'Model inputs'!I12))="",0,IF(IF(IF(ISERROR('Model inputs'!J23=1),'Model inputs'!J23=1,IF('Model inputs'!J23="","",'Model inputs'!J23=1))="",FALSE,IF(ISERROR('Model inputs'!J23=1),'Model inputs'!J23=1,IF('Model inputs'!J23="","",'Model inputs'!J23=1))),IF('Model inputs'!AB64="","",'Model inputs'!AB64),IF('Model inputs'!I12="","",'Model inputs'!I12)))+'Model inputs'!J117-'Model inputs'!C37 -> -129.43691 | K12: =IF(IF(IF(IF(ISERROR('Model inputs'!K23=1),'Model inputs'!K23=1,IF('Model inputs'!K23="","",'Model inputs'!K23=1))="",FALSE,IF(ISERROR('Model inputs'!K23=1),'Model inputs'!K23=1,IF('Model inputs'!K23="","",'Model inputs'!K23=1))),IF('Model inputs'!AB64="","",'Model inputs'!AB64),IF('Model inputs'!J12="","",'Model inputs'!J12))="",0,IF(IF(IF(ISERROR('Model inputs'!K23=1),'Model inputs'!K23=1,IF('Model inputs'!K23="","",'Model inputs'!K23=1))="",FALSE,IF(ISERROR('Model inputs'!K23=1),'Model inputs'!K23=1,IF('Model inputs'!K23="","",'Model inputs'!K23=1))),IF('Model inputs'!AB64="","",'Model inputs'!AB64),IF('Model inputs'!J12="","",'Model inputs'!J12)))+'Model inputs'!K117-'Model inputs'!C37 -> 42.870664 | L12: =IF(IF(IF(IF(ISERROR('Model inputs'!L23=1),'Model inputs'!L23=1,IF('Model inputs'!L23="","",'Model inputs'!L23=1))="",FALSE,IF(ISERROR('Model inputs'!L23=1),'Model inputs'!L23=1,IF('Model inputs'!L23="","",'Model inputs'!L23=1))),IF('Model inputs'!AB64="","",'Model inputs'!AB64),IF('Model inputs'!K12="","",'Model inputs'!K12))="",0,IF(IF(IF(ISERROR('Model inputs'!L23=1),'Model inputs'!L23=1,IF('Model inputs'!L23="","",'Model inputs'!L23=1))="",FALSE,IF(ISERROR('Model inputs'!L23=1),'Model inputs'!L23=1,IF('Model inputs'!L23="","",'Model inputs'!L23=1))),IF('Model inputs'!AB64="","",'Model inputs'!AB64),IF('Model inputs'!K12="","",'Model inputs'!K12)))+'Model inputs'!L117-'Model inputs'!C37 -> 271.85514 | M12: =IF(IF(IF(IF(ISERROR('Model inputs'!M23=1),'Model inputs'!M23=1,IF('Model inputs'!M23="","",'Model inputs'!M23=1))="",FALSE,IF(ISERROR('Model inputs'!M23=1),'Model inputs'!M23=1,IF('Model inputs'!M23="","",'Model inputs'!M23=1))),IF('Model inputs'!AB64="","",'Model inputs'!AB64),IF('Model inputs'!L12="","",'Model inputs'!L12))="",0,IF(IF(IF(ISERROR('Model inputs'!M23=1),'Model inputs'!M23=1,IF('Model inputs'!M23="","",'Model inputs'!M23=1))="",FALSE,IF(ISERROR('Model inputs'!M23=1),'Model inputs'!M23=1,IF('Model inputs'!M23="","",'Model inputs'!M23=1))),IF('Model inputs'!AB64="","",'Model inputs'!AB64),IF('Model inputs'!L12="","",'Model inputs'!L12)))+'Model inputs'!M117-'Model inputs'!C37 -> 564.31776 | N12: =IF(IF(IF(IF(ISERROR('Model inputs'!N23=1),'Model inputs'!N23=1,IF('Model inputs'!N23="","",'Model inputs'!N23=1))="",FALSE,IF(ISERROR('Model inputs'!N23=1),'Model inputs'!N23=1,IF('Model inputs'!N23="","",'Model inputs'!N23=1))),IF('Model inputs'!AB64="","",'Model inputs'!AB64),IF('Model inputs'!M12="","",'Model inputs'!M12))="",0,IF(IF(IF(ISERROR('Model inputs'!N23=1),'Model inputs'!N23=1,IF('Model inputs'!N23="","",'Model inputs'!N23=1))="",FALSE,IF(ISERROR('Model inputs'!N23=1),'Model inputs'!N23=1,IF('Model inputs'!N23="","",'Model inputs'!N23=1))),IF('Model inputs'!AB64="","",'Model inputs'!AB64),IF('Model inputs'!M12="","",'Model inputs'!M12)))+'Model inputs'!N117-'Model inputs'!C37 -> 927.87589 | O12: =IF(IF(IF(IF(ISERROR('Model inputs'!O23=1),'Model inputs'!O23=1,IF('Model inputs'!O23="","",'Model inputs'!O23=1))="",FALSE,IF(ISERROR('Model inputs'!O23=1),'Model inputs'!O23=1,IF('Model inputs'!O23="","",'Model inputs'!O23=1))),IF('Model inputs'!AB64="","",'Model inputs'!AB64),IF('Model inputs'!N12="","",'Model inputs'!N12))="",0,IF(IF(IF(ISERROR('Model inputs'!O23=1),'Model inputs'!O23=1,IF('Model inputs'!O23="","",'Model inputs'!O23=1))="",FALSE,IF(ISERROR('Model inputs'!O23=1),'Model inputs'!O23=1,IF('Model inputs'!O23="","",'Model inputs'!O23=1))),IF('Model inputs'!AB64="","",'Model inputs'!AB64),IF('Model inputs'!N12="","",'Model inputs'!N12)))+'Model inputs'!O117-'Model inputs'!C37 -> 1371.061 | P12: =IF(IF(IF(IF(ISERROR('Model inputs'!P23=1),'Model inputs'!P23=1,IF('Model inputs'!P23="","",'Model inputs'!P23=1))="",FALSE,IF(ISERROR('Model inputs'!P23=1),'Model inputs'!P23=1,IF('Model inputs'!P23="","",'Model inputs'!P23=1))),IF('Model inputs'!AB64="","",'Model inputs'!AB64),IF('Model inputs'!O12="","",'Model inputs'!O12))="",0,IF(IF(IF(ISERROR('Model inputs'!P23=1),'Model inputs'!P23=1,IF('Model inputs'!P23="","",'Model inputs'!P23=1))="",FALSE,IF(ISERROR('Model inputs'!P23=1),'Model inputs'!P23=1,IF('Model inputs'!P23="","",'Model inputs'!P23=1))),IF('Model inputs'!AB64="","",'Model inputs'!AB64),IF('Model inputs'!O12="","",'Model inputs'!O12)))+'Model inputs'!P117-'Model inputs'!C37 -> 1903.4283 | Q12: =IF(IF(IF(IF(ISERROR('Model inputs'!Q23=1),'Model inputs'!Q23=1,IF('Model inputs'!Q23="","",'Model inputs'!Q23=1))="",FALSE,IF(ISERROR('Model inputs'!Q23=1),'Model inputs'!Q23=1,IF('Model inputs'!Q23="","",'Model inputs'!Q23=1))),IF('Model inputs'!AB64="","",'Model inputs'!AB64),IF('Model inputs'!P12="","",'Model inputs'!P12))="",0,IF(IF(IF(ISERROR('Model inputs'!Q23=1),'Model inputs'!Q23=1,IF('Model inputs'!Q23="","",'Model inputs'!Q23=1))="",FALSE,IF(ISERROR('Model inputs'!Q23=1),'Model inputs'!Q23=1,IF('Model inputs'!Q23="","",'Model inputs'!Q23=1))),IF('Model inputs'!AB64="","",'Model inputs'!AB64),IF('Model inputs'!P12="","",'Model inputs'!P12)))+'Model inputs'!Q117-'Model inputs'!C37 -> 2535.6797 | R12: =IF(IF(IF(IF(ISERROR('Model inputs'!R23=1),'Model inputs'!R23=1,IF('Model inputs'!R23="","",'Model inputs'!R23=1))="",FALSE,IF(ISERROR('Model inputs'!R23=1),'Model inputs'!R23=1,IF('Model inputs'!R23="","",'Model inputs'!R23=1))),IF('Model inputs'!AB64="","",'Model inputs'!AB64),IF('Model inputs'!Q12="","",'Model inputs'!Q12))="",0,IF(IF(IF(ISERROR('Model inputs'!R23=1),'Model inputs'!R23=1,IF('Model inputs'!R23="","",'Model inputs'!R23=1))="",FALSE,IF(ISERROR('Model inputs'!R23=1),'Model inputs'!R23=1,IF('Model inputs'!R23="","",'Model inputs'!R23=1))),IF('Model inputs'!AB64="","",'Model inputs'!AB64),IF('Model inputs'!Q12="","",'Model inputs'!Q12)))+'Model inputs'!R117-'Model inputs'!C37 -> 3279.8013 | S12: =IF(IF(IF(IF(ISERROR('Model inputs'!S23=1),'Model inputs'!S23=1,IF('Model inputs'!S23="","",'Model inputs'!S23=1))="",FALSE,IF(ISERROR('Model inputs'!S23=1),'Model inputs'!S23=1,IF('Model inputs'!S23="","",'Model inputs'!S23=1))),IF('Model inputs'!AB64="","",'Model inputs'!AB64),IF('Model inputs'!R12="","",'Model inputs'!R12))="",0,IF(IF(IF(ISERROR('Model inputs'!S23=1),'Model inputs'!S23=1,IF('Model inputs'!S23="","",'Model inputs'!S23=1))="",FALSE,IF(ISERROR('Model inputs'!S23=1),'Model inputs'!S23=1,IF('Model inputs'!S23="","",'Model inputs'!S23=1))),IF('Model inputs'!AB64="","",'Model inputs'!AB64),IF('Model inputs'!R12="","",'Model inputs'!R12)))+'Model inputs'!S117-'Model inputs'!C37 -> 4149.2174 | T12: =IF(IF(IF(IF(ISERROR('Model inputs'!T23=1),'Model inputs'!T23=1,IF('Model inputs'!T23="","",'Model inputs'!T23=1))="",FALSE,IF(ISERROR('Model inputs'!T23=1),'Model inputs'!T23=1,IF('Model inputs'!T23="","",'Model inputs'!T23=1))),IF('Model inputs'!AB64="","",'Model inputs'!AB64),IF('Model inputs'!S12="","",'Model inputs'!S12))="",0,IF(IF(IF(ISERROR('Model inputs'!T23=1),'Model inputs'!T23=1,IF('Model inputs'!T23="","",'Model inputs'!T23=1))="",FALSE,IF(ISERROR('Model inputs'!T23=1),'Model inputs'!T23=1,IF('Model inputs'!T23="","",'Model inputs'!T23=1))),IF('Model inputs'!AB64="","",'Model inputs'!AB64),IF('Model inputs'!S12="","",'Model inputs'!S12)))+'Model inputs'!T117-'Model inputs'!C37 -> 5158.9635 | U12: =IF(IF(IF(IF(ISERROR('Model inputs'!U23=1),'Model inputs'!U23=1,IF('Model inputs'!U23="","",'Model inputs'!U23=1))="",FALSE,IF(ISERROR('Model inputs'!U23=1),'Model inputs'!U23=1,IF('Model inputs'!U23="","",'Model inputs'!U23=1))),IF('Model inputs'!AB64="","",'Model inputs'!AB64),IF('Model inputs'!T12="","",'Model inputs'!T12))="",0,IF(IF(IF(ISERROR('Model inputs'!U23=1),'Model inputs'!U23=1,IF('Model inputs'!U23="","",'Model inputs'!U23=1))="",FALSE,IF(ISERROR('Model inputs'!U23=1),'Model inputs'!U23=1,IF('Model inputs'!U23="","",'Model inputs'!U23=1))),IF('Model inputs'!AB64="","",'Model inputs'!AB64),IF('Model inputs'!T12="","",'Model inputs'!T12)))+'Model inputs'!U117-'Model inputs'!C37 -> 6325.8792 | V12: =IF(IF(IF(IF(ISERROR('Model inputs'!V23=1),'Model inputs'!V23=1,IF('Model inputs'!V23="","",'Model inputs'!V23=1))="",FALSE,IF(ISERROR('Model inputs'!V23=1),'Model inputs'!V23=1,IF('Model inputs'!V23="","",'Model inputs'!V23=1))),IF('Model inputs'!AB64="","",'Model inputs'!AB64),IF('Model inputs'!U12="","",'Model inputs'!U12))="",0,IF(IF(IF(ISERROR('Model inputs'!V23=1),'Model inputs'!V23=1,IF('Model inputs'!V23="","",'Model inputs'!V23=1))="",FALSE,IF(ISERROR('Model inputs'!V23=1),'Model inputs'!V23=1,IF('Model inputs'!V23="","",'Model inputs'!V23=1))),IF('Model inputs'!AB64="","",'Model inputs'!AB64),IF('Model inputs'!U12="","",'Model inputs'!U12)))+'Model inputs'!V117-'Model inputs'!C37 -> 7668.8247 | W12: =IF(IF(IF(IF(ISERROR('Model inputs'!W23=1),'Model inputs'!W23=1,IF('Model inputs'!W23="","",'Model inputs'!W23=1))="",FALSE,IF(ISERROR('Model inputs'!W23=1),'Model inputs'!W23=1,IF('Model inputs'!W23="","",'Model inputs'!W23=1))),IF('Model inputs'!AB64="","",'Model inputs'!AB64),IF('Model inputs'!V12="","",'Model inputs'!V12))="",0,IF(IF(IF(ISERROR('Model inputs'!W23=1),'Model inputs'!W23=1,IF('Model inputs'!W23="","",'Model inputs'!W23=1))="",FALSE,IF(ISERROR('Model inputs'!W23=1),'Model inputs'!W23=1,IF('Model inputs'!W23="","",'Model inputs'!W23=1))),IF('Model inputs'!AB64="","",'Model inputs'!AB64),IF('Model inputs'!V12="","",'Model inputs'!V12)))+'Model inputs'!W117-'Model inputs'!C37 -> 9208.9236 | X12: =IF(IF(IF(IF(ISERROR('Model inputs'!X23=1),'Model inputs'!X23=1,IF('Model inputs'!X23="","",'Model inputs'!X23=1))="",FALSE,IF(ISERROR('Model inputs'!X23=1),'Model inputs'!X23=1,IF('Model inputs'!X23="","",'Model inputs'!X23=1))),IF('Model inputs'!AB64="","",'Model inputs'!AB64),IF('Model inputs'!W12="","",'Model inputs'!W12))="",0,IF(IF(IF(ISERROR('Model inputs'!X23=1),'Model inputs'!X23=1,IF('Model inputs'!X23="","",'Model inputs'!X23=1))="",FALSE,IF(ISERROR('Model inputs'!X23=1),'Model inputs'!X23=1,IF('Model inputs'!X23="","",'Model inputs'!X23=1))),IF('Model inputs'!AB64="","",'Model inputs'!AB64),IF('Model inputs'!W12="","",'Model inputs'!W12)))+'Model inputs'!X117-'Model inputs'!C37 -> 10969.834 | Y12: =IF(IF(IF(IF(ISERROR('Model inputs'!Y23=1),'Model inputs'!Y23=1,IF('Model inputs'!Y23="","",'Model inputs'!Y23=1))="",FALSE,IF(ISERROR('Model inputs'!Y23=1),'Model inputs'!Y23=1,IF('Model inputs'!Y23="","",'Model inputs'!Y23=1))),IF('Model inputs'!AB64="","",'Model inputs'!AB64),IF('Model inputs'!X12="","",'Model inputs'!X12))="",0,IF(IF(IF(ISERROR('Model inputs'!Y23=1),'Model inputs'!Y23=1,IF('Model inputs'!Y23="","",'Model inputs'!Y23=1))="",FALSE,IF(ISERROR('Model inputs'!Y23=1),'Model inputs'!Y23=1,IF('Model inputs'!Y23="","",'Model inputs'!Y23=1))),IF('Model inputs'!AB64="","",'Model inputs'!AB64),IF('Model inputs'!X12="","",'Model inputs'!X12)))+'Model inputs'!Y117-'Model inputs'!C37 -> 12978.055 | Z12: =IF(IF(IF(IF(ISERROR('Model inputs'!Z23=1),'Model inputs'!Z23=1,IF('Model inputs'!Z23="","",'Model inputs'!Z23=1))="",FALSE,IF(ISERROR('Model inputs'!Z23=1),'Model inputs'!Z23=1,IF('Model inputs'!Z23="","",'Model inputs'!Z23=1))),IF('Model inputs'!AB64="","",'Model inputs'!AB64),IF('Model inputs'!Y12="","",'Model inputs'!Y12))="",0,IF(IF(IF(ISERROR('Model inputs'!Z23=1),'Model inputs'!Z23=1,IF('Model inputs'!Z23="","",'Model inputs'!Z23=1))="",FALSE,IF(ISERROR('Model inputs'!Z23=1),'Model inputs'!Z23=1,IF('Model inputs'!Z23="","",'Model inputs'!Z23=1))),IF('Model inputs'!AB64="","",'Model inputs'!AB64),IF('Model inputs'!Y12="","",'Model inputs'!Y12)))+'Model inputs'!Z117-'Model inputs'!C37 -> 15263.261
A13: Cash break-even marker | B13: =IF(IF(IF(ISERROR('Model inputs'!B42>=0),'Model inputs'!B42>=0,IF('Model inputs'!B42="","",'Model inputs'!B42>=0))="",FALSE,IF(ISERROR('Model inputs'!B42>=0),'Model inputs'!B42>=0,IF('Model inputs'!B42="","",'Model inputs'!B42>=0))),DATE(2028,9,1),"") -> 46997 | D13: =IF(IF(IF(ISERROR('Model inputs'!D42>=0),'Model inputs'!D42>=0,IF('Model inputs'!D42="","",'Model inputs'!D42>=0))="",FALSE,IF(ISERROR('Model inputs'!D42>=0),'Model inputs'!D42>=0,IF('Model inputs'!D42="","",'Model inputs'!D42>=0))),DATE(2026,10,1),"") | E13: =IF(IF(IF(ISERROR('Model inputs'!E42>=0),'Model inputs'!E42>=0,IF('Model inputs'!E42="","",'Model inputs'!E42>=0))="",FALSE,IF(ISERROR('Model inputs'!E42>=0),'Model inputs'!E42>=0,IF('Model inputs'!E42="","",'Model inputs'!E42>=0))),DATE(2026,11,1),"") -> 46327 | F13: =IF(IF(IF(ISERROR('Model inputs'!F42>=0),'Model inputs'!F42>=0,IF('Model inputs'!F42="","",'Model inputs'!F42>=0))="",FALSE,IF(ISERROR('Model inputs'!F42>=0),'Model inputs'!F42>=0,IF('Model inputs'!F42="","",'Model inputs'!F42>=0))),DATE(2026,12,1),"") -> 46357 | G13: =IF(IF(IF(ISERROR('Model inputs'!G42>=0),'Model inputs'!G42>=0,IF('Model inputs'!G42="","",'Model inputs'!G42>=0))="",FALSE,IF(ISERROR('Model inputs'!G42>=0),'Model inputs'!G42>=0,IF('Model inputs'!G42="","",'Model inputs'!G42>=0))),DATE(2027,1,1),"") -> 46388 | H13: =IF(IF(IF(ISERROR('Model inputs'!H42>=0),'Model inputs'!H42>=0,IF('Model inputs'!H42="","",'Model inputs'!H42>=0))="",FALSE,IF(ISERROR('Model inputs'!H42>=0),'Model inputs'!H42>=0,IF('Model inputs'!H42="","",'Model inputs'!H42>=0))),DATE(2027,2,1),"") -> 46419 | I13: =IF(IF(IF(ISERROR('Model inputs'!I42>=0),'Model inputs'!I42>=0,IF('Model inputs'!I42="","",'Model inputs'!I42>=0))="",FALSE,IF(ISERROR('Model inputs'!I42>=0),'Model inputs'!I42>=0,IF('Model inputs'!I42="","",'Model inputs'!I42>=0))),DATE(2027,3,1),"") -> 46447 | J13: =IF(IF(IF(ISERROR('Model inputs'!J42>=0),'Model inputs'!J42>=0,IF('Model inputs'!J42="","",'Model inputs'!J42>=0))="",FALSE,IF(ISERROR('Model inputs'!J42>=0),'Model inputs'!J42>=0,IF('Model inputs'!J42="","",'Model inputs'!J42>=0))),DATE(2027,4,1),"") -> 46478 | K13: =IF(IF(IF(ISERROR('Model inputs'!K42>=0),'Model inputs'!K42>=0,IF('Model inputs'!K42="","",'Model inputs'!K42>=0))="",FALSE,IF(ISERROR('Model inputs'!K42>=0),'Model inputs'!K42>=0,IF('Model inputs'!K42="","",'Model inputs'!K42>=0))),DATE(2027,5,1),"") -> 46508 | L13: =IF(IF(IF(ISERROR('Model inputs'!L42>=0),'Model inputs'!L42>=0,IF('Model inputs'!L42="","",'Model inputs'!L42>=0))="",FALSE,IF(ISERROR('Model inputs'!L42>=0),'Model inputs'!L42>=0,IF('Model inputs'!L42="","",'Model inputs'!L42>=0))),DATE(2027,6,1),"") -> 46539 | M13: =IF(IF(IF(ISERROR('Model inputs'!M42>=0),'Model inputs'!M42>=0,IF('Model inputs'!M42="","",'Model inputs'!M42>=0))="",FALSE,IF(ISERROR('Model inputs'!M42>=0),'Model inputs'!M42>=0,IF('Model inputs'!M42="","",'Model inputs'!M42>=0))),DATE(2027,7,1),"") -> 46569 | N13: =IF(IF(IF(ISERROR('Model inputs'!N42>=0),'Model inputs'!N42>=0,IF('Model inputs'!N42="","",'Model inputs'!N42>=0))="",FALSE,IF(ISERROR('Model inputs'!N42>=0),'Model inputs'!N42>=0,IF('Model inputs'!N42="","",'Model inputs'!N42>=0))),DATE(2027,8,1),"") -> 46600 | O13: =IF(IF(IF(ISERROR('Model inputs'!O42>=0),'Model inputs'!O42>=0,IF('Model inputs'!O42="","",'Model inputs'!O42>=0))="",FALSE,IF(ISERROR('Model inputs'!O42>=0),'Model inputs'!O42>=0,IF('Model inputs'!O42="","",'Model inputs'!O42>=0))),DATE(2027,9,1),"") -> 46631 | P13: =IF(IF(IF(ISERROR('Model inputs'!P42>=0),'Model inputs'!P42>=0,IF('Model inputs'!P42="","",'Model inputs'!P42>=0))="",FALSE,IF(ISERROR('Model inputs'!P42>=0),'Model inputs'!P42>=0,IF('Model inputs'!P42="","",'Model inputs'!P42>=0))),DATE(2027,10,1),"") -> 46661 | Q13: =IF(IF(IF(ISERROR('Model inputs'!Q42>=0),'Model inputs'!Q42>=0,IF('Model inputs'!Q42="","",'Model inputs'!Q42>=0))="",FALSE,IF(ISERROR('Model inputs'!Q42>=0),'Model inputs'!Q42>=0,IF('Model inputs'!Q42="","",'Model inputs'!Q42>=0))),DATE(2027,11,1),"") -> 46692 | R13: =IF(IF(IF(ISERROR('Model inputs'!R42>=0),'Model inputs'!R42>=0,IF('Model inputs'!R42="","",'Model inputs'!R42>=0))="",FALSE,IF(ISERROR('Model inputs'!R42>=0),'Model inputs'!R42>=0,IF('Model inputs'!R42="","",'Model inputs'!R42>=0))),DATE(2027,12,1),"") -> 46722 | S13: =IF(IF(IF(ISERROR('Model inputs'!S42>=0),'Model inputs'!S42>=0,IF('Model inputs'!S42="","",'Model inputs'!S42>=0))="",FALSE,IF(ISERROR('Model inputs'!S42>=0),'Model inputs'!S42>=0,IF('Model inputs'!S42="","",'Model inputs'!S42>=0))),DATE(2028,1,1),"") -> 46753 | T13: =IF(IF(IF(ISERROR('Model inputs'!T42>=0),'Model inputs'!T42>=0,IF('Model inputs'!T42="","",'Model inputs'!T42>=0))="",FALSE,IF(ISERROR('Model inputs'!T42>=0),'Model inputs'!T42>=0,IF('Model inputs'!T42="","",'Model inputs'!T42>=0))),DATE(2028,2,1),"") -> 46784 | U13: =IF(IF(IF(ISERROR('Model inputs'!U42>=0),'Model inputs'!U42>=0,IF('Model inputs'!U42="","",'Model inputs'!U42>=0))="",FALSE,IF(ISERROR('Model inputs'!U42>=0),'Model inputs'!U42>=0,IF('Model inputs'!U42="","",'Model inputs'!U42>=0))),DATE(2028,3,1),"") -> 46813 | V13: =IF(IF(IF(ISERROR('Model inputs'!V42>=0),'Model inputs'!V42>=0,IF('Model inputs'!V42="","",'Model inputs'!V42>=0))="",FALSE,IF(ISERROR('Model inputs'!V42>=0),'Model inputs'!V42>=0,IF('Model inputs'!V42="","",'Model inputs'!V42>=0))),DATE(2028,4,1),"") -> 46844 | W13: =IF(IF(IF(ISERROR('Model inputs'!W42>=0),'Model inputs'!W42>=0,IF('Model inputs'!W42="","",'Model inputs'!W42>=0))="",FALSE,IF(ISERROR('Model inputs'!W42>=0),'Model inputs'!W42>=0,IF('Model inputs'!W42="","",'Model inputs'!W42>=0))),DATE(2028,5,1),"") -> 46874 | X13: =IF(IF(IF(ISERROR('Model inputs'!X42>=0),'Model inputs'!X42>=0,IF('Model inputs'!X42="","",'Model inputs'!X42>=0))="",FALSE,IF(ISERROR('Model inputs'!X42>=0),'Model inputs'!X42>=0,IF('Model inputs'!X42="","",'Model inputs'!X42>=0))),DATE(2028,6,1),"") -> 46905 | Y13: =IF(IF(IF(ISERROR('Model inputs'!Y42>=0),'Model inputs'!Y42>=0,IF('Model inputs'!Y42="","",'Model inputs'!Y42>=0))="",FALSE,IF(ISERROR('Model inputs'!Y42>=0),'Model inputs'!Y42>=0,IF('Model inputs'!Y42="","",'Model inputs'!Y42>=0))),DATE(2028,7,1),"") -> 46935 | Z13: =IF(IF(IF(ISERROR('Model inputs'!Z42>=0),'Model inputs'!Z42>=0,IF('Model inputs'!Z42="","",'Model inputs'!Z42>=0))="",FALSE,IF(ISERROR('Model inputs'!Z42>=0),'Model inputs'!Z42>=0,IF('Model inputs'!Z42="","",'Model inputs'!Z42>=0))),DATE(2028,8,1),"") -> 46966
A14: Churned repositories · Base and upside comparison · Main Scenario | B14: ='Model inputs'!B46*'Model inputs'!AB104 -> 2.8938879 | D14: ='Model inputs'!D46*'Model inputs'!AB104 -> 0 | E14: ='Model inputs'!E46*'Model inputs'!AB104 -> 0.1 | F14: ='Model inputs'!F46*'Model inputs'!AB104 -> 0.2 | G14: ='Model inputs'!G46*'Model inputs'!AB104 -> 0.3 | H14: ='Model inputs'!H46*'Model inputs'!AB104 -> 0.336 | I14: ='Model inputs'!I46*'Model inputs'!AB104 -> 0.37632 | J14: ='Model inputs'!J46*'Model inputs'!AB104 -> 0.4214784 | K14: ='Model inputs'!K46*'Model inputs'!AB104 -> 0.47205581 | L14: ='Model inputs'!L46*'Model inputs'!AB104 -> 0.5287025 | M14: ='Model inputs'!M46*'Model inputs'!AB104 -> 0.59214681 | N14: ='Model inputs'!N46*'Model inputs'!AB104 -> 0.66320442 | O14: ='Model inputs'!O46*'Model inputs'!AB104 -> 0.74278895 | P14: ='Model inputs'!P46*'Model inputs'!AB104 -> 0.83192363 | Q14: ='Model inputs'!Q46*'Model inputs'!AB104 -> 0.93175446 | R14: ='Model inputs'!R46*'Model inputs'!AB104 -> 1.043565 | S14: ='Model inputs'!S46*'Model inputs'!AB104 -> 1.1687928 | T14: ='Model inputs'!T46*'Model inputs'!AB104 -> 1.3090479 | U14: ='Model inputs'!U46*'Model inputs'!AB104 -> 1.4661337 | V14: ='Model inputs'!V46*'Model inputs'!AB104 -> 1.6420697 | W14: ='Model inputs'!W46*'Model inputs'!AB104 -> 1.8391181 | X14: ='Model inputs'!X46*'Model inputs'!AB104 -> 2.0598123 | Y14: ='Model inputs'!Y46*'Model inputs'!AB104 -> 2.3069897 | Z14: ='Model inputs'!Z46*'Model inputs'!AB104 -> 2.5838285
A15: Churned repositories · Upshift — Upside | B15: ='Model inputs'!B47*'Model inputs'!AB105 -> 40.01823 | D15: ='Model inputs'!D47*'Model inputs'!AB105 -> 0 | E15: ='Model inputs'!E47*'Model inputs'!AB105 -> 0.25 | F15: ='Model inputs'!F47*'Model inputs'!AB105 -> 0.5 | G15: ='Model inputs'!G47*'Model inputs'!AB105 -> 0.75 | H15: ='Model inputs'!H47*'Model inputs'!AB105 -> 0.915 | I15: ='Model inputs'!I47*'Model inputs'!AB105 -> 1.1163 | J15: ='Model inputs'!J47*'Model inputs'!AB105 -> 1.361886 | K15: ='Model inputs'!K47*'Model inputs'!AB105 -> 1.6615009 | L15: ='Model inputs'!L47*'Model inputs'!AB105 -> 2.0270311 | M15: ='Model inputs'!M47*'Model inputs'!AB105 -> 2.472978 | N15: ='Model inputs'!N47*'Model inputs'!AB105 -> 3.0170331 | O15: ='Model inputs'!O47*'Model inputs'!AB105 -> 3.6807804 | P15: ='Model inputs'!P47*'Model inputs'!AB105 -> 4.4905521 | Q15: ='Model inputs'!Q47*'Model inputs'!AB105 -> 5.4784736 | R15: ='Model inputs'!R47*'Model inputs'!AB105 -> 6.6837377 | S15: ='Model inputs'!S47*'Model inputs'!AB105 -> 8.15416 | T15: ='Model inputs'!T47*'Model inputs'!AB105 -> 9.9480753 | U15: ='Model inputs'!U47*'Model inputs'!AB105 -> 12.136652 | V15: ='Model inputs'!V47*'Model inputs'!AB105 -> 14.806715 | W15: ='Model inputs'!W47*'Model inputs'!AB105 -> 18.064193 | X15: ='Model inputs'!X47*'Model inputs'!AB105 -> 22.038315 | Y15: ='Model inputs'!Y47*'Model inputs'!AB105 -> 26.886744 | Z15: ='Model inputs'!Z47*'Model inputs'!AB105 -> 32.801828 | AA15: 0
A16: Combined stress break-even marker | B16: =IF(IF(IF(ISERROR('Model inputs'!B115>=0),'Model inputs'!B115>=0,IF('Model inputs'!B115="","",'Model inputs'!B115>=0))="",FALSE,IF(ISERROR('Model inputs'!B115>=0),'Model inputs'!B115>=0,IF('Model inputs'!B115="","",'Model inputs'!B115>=0))),DATE(2028,9,1),"") -> 46997 | D16: =IF(IF(IF(ISERROR('Model inputs'!D115>=0),'Model inputs'!D115>=0,IF('Model inputs'!D115="","",'Model inputs'!D115>=0))="",FALSE,IF(ISERROR('Model inputs'!D115>=0),'Model inputs'!D115>=0,IF('Model inputs'!D115="","",'Model inputs'!D115>=0))),DATE(2026,10,1),"") | E16: =IF(IF(IF(ISERROR('Model inputs'!E115>=0),'Model inputs'!E115>=0,IF('Model inputs'!E115="","",'Model inputs'!E115>=0))="",FALSE,IF(ISERROR('Model inputs'!E115>=0),'Model inputs'!E115>=0,IF('Model inputs'!E115="","",'Model inputs'!E115>=0))),DATE(2026,11,1),"") | F16: =IF(IF(IF(ISERROR('Model inputs'!F115>=0),'Model inputs'!F115>=0,IF('Model inputs'!F115="","",'Model inputs'!F115>=0))="",FALSE,IF(ISERROR('Model inputs'!F115>=0),'Model inputs'!F115>=0,IF('Model inputs'!F115="","",'Model inputs'!F115>=0))),DATE(2026,12,1),"") | G16: =IF(IF(IF(ISERROR('Model inputs'!G115>=0),'Model inputs'!G115>=0,IF('Model inputs'!G115="","",'Model inputs'!G115>=0))="",FALSE,IF(ISERROR('Model inputs'!G115>=0),'Model inputs'!G115>=0,IF('Model inputs'!G115="","",'Model inputs'!G115>=0))),DATE(2027,1,1),"") | H16: =IF(IF(IF(ISERROR('Model inputs'!H115>=0),'Model inputs'!H115>=0,IF('Model inputs'!H115="","",'Model inputs'!H115>=0))="",FALSE,IF(ISERROR('Model inputs'!H115>=0),'Model inputs'!H115>=0,IF('Model inputs'!H115="","",'Model inputs'!H115>=0))),DATE(2027,2,1),"") | I16: =IF(IF(IF(ISERROR('Model inputs'!I115>=0),'Model inputs'!I115>=0,IF('Model inputs'!I115="","",'Model inputs'!I115>=0))="",FALSE,IF(ISERROR('Model inputs'!I115>=0),'Model inputs'!I115>=0,IF('Model inputs'!I115="","",'Model inputs'!I115>=0))),DATE(2027,3,1),"") -> 46447 | J16: =IF(IF(IF(ISERROR('Model inputs'!J115>=0),'Model inputs'!J115>=0,IF('Model inputs'!J115="","",'Model inputs'!J115>=0))="",FALSE,IF(ISERROR('Model inputs'!J115>=0),'Model inputs'!J115>=0,IF('Model inputs'!J115="","",'Model inputs'!J115>=0))),DATE(2027,4,1),"") -> 46478 | K16: =IF(IF(IF(ISERROR('Model inputs'!K115>=0),'Model inputs'!K115>=0,IF('Model inputs'!K115="","",'Model inputs'!K115>=0))="",FALSE,IF(ISERROR('Model inputs'!K115>=0),'Model inputs'!K115>=0,IF('Model inputs'!K115="","",'Model inputs'!K115>=0))),DATE(2027,5,1),"") -> 46508 | L16: =IF(IF(IF(ISERROR('Model inputs'!L115>=0),'Model inputs'!L115>=0,IF('Model inputs'!L115="","",'Model inputs'!L115>=0))="",FALSE,IF(ISERROR('Model inputs'!L115>=0),'Model inputs'!L115>=0,IF('Model inputs'!L115="","",'Model inputs'!L115>=0))),DATE(2027,6,1),"") -> 46539 | M16: =IF(IF(IF(ISERROR('Model inputs'!M115>=0),'Model inputs'!M115>=0,IF('Model inputs'!M115="","",'Model inputs'!M115>=0))="",FALSE,IF(ISERROR('Model inputs'!M115>=0),'Model inputs'!M115>=0,IF('Model inputs'!M115="","",'Model inputs'!M115>=0))),DATE(2027,7,1),"") -> 46569 | N16: =IF(IF(IF(ISERROR('Model inputs'!N115>=0),'Model inputs'!N115>=0,IF('Model inputs'!N115="","",'Model inputs'!N115>=0))="",FALSE,IF(ISERROR('Model inputs'!N115>=0),'Model inputs'!N115>=0,IF('Model inputs'!N115="","",'Model inputs'!N115>=0))),DATE(2027,8,1),"") -> 46600 | O16: =IF(IF(IF(ISERROR('Model inputs'!O115>=0),'Model inputs'!O115>=0,IF('Model inputs'!O115="","",'Model inputs'!O115>=0))="",FALSE,IF(ISERROR('Model inputs'!O115>=0),'Model inputs'!O115>=0,IF('Model inputs'!O115="","",'Model inputs'!O115>=0))),DATE(2027,9,1),"") -> 46631 | P16: =IF(IF(IF(ISERROR('Model inputs'!P115>=0),'Model inputs'!P115>=0,IF('Model inputs'!P115="","",'Model inputs'!P115>=0))="",FALSE,IF(ISERROR('Model inputs'!P115>=0),'Model inputs'!P115>=0,IF('Model inputs'!P115="","",'Model inputs'!P115>=0))),DATE(2027,10,1),"") -> 46661 | Q16: =IF(IF(IF(ISERROR('Model inputs'!Q115>=0),'Model inputs'!Q115>=0,IF('Model inputs'!Q115="","",'Model inputs'!Q115>=0))="",FALSE,IF(ISERROR('Model inputs'!Q115>=0),'Model inputs'!Q115>=0,IF('Model inputs'!Q115="","",'Model inputs'!Q115>=0))),DATE(2027,11,1),"") -> 46692 | R16: =IF(IF(IF(ISERROR('Model inputs'!R115>=0),'Model inputs'!R115>=0,IF('Model inputs'!R115="","",'Model inputs'!R115>=0))="",FALSE,IF(ISERROR('Model inputs'!R115>=0),'Model inputs'!R115>=0,IF('Model inputs'!R115="","",'Model inputs'!R115>=0))),DATE(2027,12,1),"") -> 46722 | S16: =IF(IF(IF(ISERROR('Model inputs'!S115>=0),'Model inputs'!S115>=0,IF('Model inputs'!S115="","",'Model inputs'!S115>=0))="",FALSE,IF(ISERROR('Model inputs'!S115>=0),'Model inputs'!S115>=0,IF('Model inputs'!S115="","",'Model inputs'!S115>=0))),DATE(2028,1,1),"") -> 46753 | T16: =IF(IF(IF(ISERROR('Model inputs'!T115>=0),'Model inputs'!T115>=0,IF('Model inputs'!T115="","",'Model inputs'!T115>=0))="",FALSE,IF(ISERROR('Model inputs'!T115>=0),'Model inputs'!T115>=0,IF('Model inputs'!T115="","",'Model inputs'!T115>=0))),DATE(2028,2,1),"") -> 46784 | U16: =IF(IF(IF(ISERROR('Model inputs'!U115>=0),'Model inputs'!U115>=0,IF('Model inputs'!U115="","",'Model inputs'!U115>=0))="",FALSE,IF(ISERROR('Model inputs'!U115>=0),'Model inputs'!U115>=0,IF('Model inputs'!U115="","",'Model inputs'!U115>=0))),DATE(2028,3,1),"") -> 46813 | V16: =IF(IF(IF(ISERROR('Model inputs'!V115>=0),'Model inputs'!V115>=0,IF('Model inputs'!V115="","",'Model inputs'!V115>=0))="",FALSE,IF(ISERROR('Model inputs'!V115>=0),'Model inputs'!V115>=0,IF('Model inputs'!V115="","",'Model inputs'!V115>=0))),DATE(2028,4,1),"") -> 46844 | W16: =IF(IF(IF(ISERROR('Model inputs'!W115>=0),'Model inputs'!W115>=0,IF('Model inputs'!W115="","",'Model inputs'!W115>=0))="",FALSE,IF(ISERROR('Model inputs'!W115>=0),'Model inputs'!W115>=0,IF('Model inputs'!W115="","",'Model inputs'!W115>=0))),DATE(2028,5,1),"") -> 46874 | X16: =IF(IF(IF(ISERROR('Model inputs'!X115>=0),'Model inputs'!X115>=0,IF('Model inputs'!X115="","",'Model inputs'!X115>=0))="",FALSE,IF(ISERROR('Model inputs'!X115>=0),'Model inputs'!X115>=0,IF('Model inputs'!X115="","",'Model inputs'!X115>=0))),DATE(2028,6,1),"") -> 46905 | Y16: =IF(IF(IF(ISERROR('Model inputs'!Y115>=0),'Model inputs'!Y115>=0,IF('Model inputs'!Y115="","",'Model inputs'!Y115>=0))="",FALSE,IF(ISERROR('Model inputs'!Y115>=0),'Model inputs'!Y115>=0,IF('Model inputs'!Y115="","",'Model inputs'!Y115>=0))),DATE(2028,7,1),"") -> 46935 | Z16: =IF(IF(IF(ISERROR('Model inputs'!Z115>=0),'Model inputs'!Z115>=0,IF('Model inputs'!Z115="","",'Model inputs'!Z115>=0))="",FALSE,IF(ISERROR('Model inputs'!Z115>=0),'Model inputs'!Z115>=0,IF('Model inputs'!Z115="","",'Model inputs'!Z115>=0))),DATE(2028,8,1),"") -> 46966
A17: Compute costs · Main Scenario | B17: ='Model inputs'!B121*'Model inputs'!C62+'Model inputs'!B72*'Model inputs'!C7 -> 19.446927 | D17: ='Model inputs'!D121*'Model inputs'!C62+'Model inputs'!D72*'Model inputs'!C7 -> 0.6 | E17: ='Model inputs'!E121*'Model inputs'!C62+'Model inputs'!E72*'Model inputs'!C7 -> 1.2 | F17: ='Model inputs'!F121*'Model inputs'!C62+'Model inputs'!F72*'Model inputs'!C7 -> 1.8 | G17: ='Model inputs'!G121*'Model inputs'!C62+'Model inputs'!G72*'Model inputs'!C7 -> 2.016 | H17: ='Model inputs'!H121*'Model inputs'!C62+'Model inputs'!H72*'Model inputs'!C7 -> 2.25792 | I17: ='Model inputs'!I121*'Model inputs'!C62+'Model inputs'!I72*'Model inputs'!C7 -> 2.5288704 | J17: ='Model inputs'!J121*'Model inputs'!C62+'Model inputs'!J72*'Model inputs'!C7 -> 2.8323348 | K17: ='Model inputs'!K121*'Model inputs'!C62+'Model inputs'!K72*'Model inputs'!C7 -> 3.172215 | L17: ='Model inputs'!L121*'Model inputs'!C62+'Model inputs'!L72*'Model inputs'!C7 -> 3.5528808 | M17: ='Model inputs'!M121*'Model inputs'!C62+'Model inputs'!M72*'Model inputs'!C7 -> 3.9792265 | N17: ='Model inputs'!N121*'Model inputs'!C62+'Model inputs'!N72*'Model inputs'!C7 -> 4.4567337 | O17: ='Model inputs'!O121*'Model inputs'!C62+'Model inputs'!O72*'Model inputs'!C7 -> 4.9915418 | P17: ='Model inputs'!P121*'Model inputs'!C62+'Model inputs'!P72*'Model inputs'!C7 -> 5.5905268 | Q17: ='Model inputs'!Q121*'Model inputs'!C62+'Model inputs'!Q72*'Model inputs'!C7 -> 6.26139 | R17: ='Model inputs'!R121*'Model inputs'!C62+'Model inputs'!R72*'Model inputs'!C7 -> 7.0127568 | S17: ='Model inputs'!S121*'Model inputs'!C62+'Model inputs'!S72*'Model inputs'!C7 -> 7.8542876 | T17: ='Model inputs'!T121*'Model inputs'!C62+'Model inputs'!T72*'Model inputs'!C7 -> 8.7968021 | U17: ='Model inputs'!U121*'Model inputs'!C62+'Model inputs'!U72*'Model inputs'!C7 -> 9.8524184 | V17: ='Model inputs'!V121*'Model inputs'!C62+'Model inputs'!V72*'Model inputs'!C7 -> 11.034709 | W17: ='Model inputs'!W121*'Model inputs'!C62+'Model inputs'!W72*'Model inputs'!C7 -> 12.358874 | X17: ='Model inputs'!X121*'Model inputs'!C62+'Model inputs'!X72*'Model inputs'!C7 -> 13.841938 | Y17: ='Model inputs'!Y121*'Model inputs'!C62+'Model inputs'!Y72*'Model inputs'!C7 -> 15.502971 | Z17: ='Model inputs'!Z121*'Model inputs'!C62+'Model inputs'!Z72*'Model inputs'!C7 -> 17.363328
A18: Compute costs · Upshift — Upside | B18: ='Model inputs'!B122*'Model inputs'!AB120+'Model inputs'!B73*'Model inputs'!AB71 -> 292.93344 | D18: ='Model inputs'!D122*'Model inputs'!AB120+'Model inputs'!D73*'Model inputs'!AB71 -> 1.5 | E18: ='Model inputs'!E122*'Model inputs'!AB120+'Model inputs'!E73*'Model inputs'!AB71 -> 3 | F18: ='Model inputs'!F122*'Model inputs'!AB120+'Model inputs'!F73*'Model inputs'!AB71 -> 4.5 | G18: ='Model inputs'!G122*'Model inputs'!AB120+'Model inputs'!G73*'Model inputs'!AB71 -> 5.49 | H18: ='Model inputs'!H122*'Model inputs'!AB120+'Model inputs'!H73*'Model inputs'!AB71 -> 6.6978 | I18: ='Model inputs'!I122*'Model inputs'!AB120+'Model inputs'!I73*'Model inputs'!AB71 -> 8.171316 | J18: ='Model inputs'!J122*'Model inputs'!AB120+'Model inputs'!J73*'Model inputs'!AB71 -> 9.9690055 | K18: ='Model inputs'!K122*'Model inputs'!AB120+'Model inputs'!K73*'Model inputs'!AB71 -> 12.162187 | L18: ='Model inputs'!L122*'Model inputs'!AB120+'Model inputs'!L73*'Model inputs'!AB71 -> 14.837868 | M18: ='Model inputs'!M122*'Model inputs'!AB120+'Model inputs'!M73*'Model inputs'!AB71 -> 18.102199 | N18: ='Model inputs'!N122*'Model inputs'!AB120+'Model inputs'!N73*'Model inputs'!AB71 -> 22.084682 | O18: ='Model inputs'!O122*'Model inputs'!AB120+'Model inputs'!O73*'Model inputs'!AB71 -> 26.943313 | P18: ='Model inputs'!P122*'Model inputs'!AB120+'Model inputs'!P73*'Model inputs'!AB71 -> 32.870841 | Q18: ='Model inputs'!Q122*'Model inputs'!AB120+'Model inputs'!Q73*'Model inputs'!AB71 -> 40.102426 | R18: ='Model inputs'!R122*'Model inputs'!AB120+'Model inputs'!R73*'Model inputs'!AB71 -> 48.92496 | S18: ='Model inputs'!S122*'Model inputs'!AB120+'Model inputs'!S73*'Model inputs'!AB71 -> 59.688452 | T18: ='Model inputs'!T122*'Model inputs'!AB120+'Model inputs'!T73*'Model inputs'!AB71 -> 72.819911 | U18: ='Model inputs'!U122*'Model inputs'!AB120+'Model inputs'!U73*'Model inputs'!AB71 -> 88.840291 | V18: ='Model inputs'!V122*'Model inputs'!AB120+'Model inputs'!V73*'Model inputs'!AB71 -> 108.38516 | W18: ='Model inputs'!W122*'Model inputs'!AB120+'Model inputs'!W73*'Model inputs'!AB71 -> 132.22989 | X18: ='Model inputs'!X122*'Model inputs'!AB120+'Model inputs'!X73*'Model inputs'!AB71 -> 161.32047 | Y18: ='Model inputs'!Y122*'Model inputs'!AB120+'Model inputs'!Y73*'Model inputs'!AB71 -> 196.81097 | Z18: ='Model inputs'!Z122*'Model inputs'!AB120+'Model inputs'!Z73*'Model inputs'!AB71 -> 240.10938 | AA18: 0
A19: Delivery cost buffer · Main Scenario | B19: =('Model inputs'!B51+'Model inputs'!AB96)*'Model inputs'!C56 -> 2.1607697 | D19: =('Model inputs'!D51+'Model inputs'!AB96)*'Model inputs'!C56 -> 0.066666667 | E19: =('Model inputs'!E51+'Model inputs'!AB96)*'Model inputs'!C56 -> 0.13333333 | F19: =('Model inputs'!F51+'Model inputs'!AB96)*'Model inputs'!C56 -> 0.2 | G19: =('Model inputs'!G51+'Model inputs'!AB96)*'Model inputs'!C56 -> 0.224 | H19: =('Model inputs'!H51+'Model inputs'!AB96)*'Model inputs'!C56 -> 0.25088 | I19: =('Model inputs'!I51+'Model inputs'!AB96)*'Model inputs'!C56 -> 0.2809856 | J19: =('Model inputs'!J51+'Model inputs'!AB96)*'Model inputs'!C56 -> 0.31470387 | K19: =('Model inputs'!K51+'Model inputs'!AB96)*'Model inputs'!C56 -> 0.35246834 | L19: =('Model inputs'!L51+'Model inputs'!AB96)*'Model inputs'!C56 -> 0.39476454 | M19: =('Model inputs'!M51+'Model inputs'!AB96)*'Model inputs'!C56 -> 0.44213628 | N19: =('Model inputs'!N51+'Model inputs'!AB96)*'Model inputs'!C56 -> 0.49519264 | O19: =('Model inputs'!O51+'Model inputs'!AB96)*'Model inputs'!C56 -> 0.55461575 | P19: =('Model inputs'!P51+'Model inputs'!AB96)*'Model inputs'!C56 -> 0.62116964 | Q19: =('Model inputs'!Q51+'Model inputs'!AB96)*'Model inputs'!C56 -> 0.69571 | R19: =('Model inputs'!R51+'Model inputs'!AB96)*'Model inputs'!C56 -> 0.7791952 | S19: =('Model inputs'!S51+'Model inputs'!AB96)*'Model inputs'!C56 -> 0.87269862 | T19: =('Model inputs'!T51+'Model inputs'!AB96)*'Model inputs'!C56 -> 0.97742246 | U19: =('Model inputs'!U51+'Model inputs'!AB96)*'Model inputs'!C56 -> 1.0947132 | V19: =('Model inputs'!V51+'Model inputs'!AB96)*'Model inputs'!C56 -> 1.2260787 | W19: =('Model inputs'!W51+'Model inputs'!AB96)*'Model inputs'!C56 -> 1.3732082 | X19: =('Model inputs'!X51+'Model inputs'!AB96)*'Model inputs'!C56 -> 1.5379932 | Y19: =('Model inputs'!Y51+'Model inputs'!AB96)*'Model inputs'!C56 -> 1.7225523 | Z19: =('Model inputs'!Z51+'Model inputs'!AB96)*'Model inputs'!C56 -> 1.9292586 | AA19: 0
A20: Delivery cost buffer · Upshift — Upside | B20: =('Model inputs'!B110+'Model inputs'!AB97)*'Model inputs'!AB114 -> 32.54816 | D20: =('Model inputs'!D110+'Model inputs'!AB97)*'Model inputs'!AB114 -> 0.16666667 | E20: =('Model inputs'!E110+'Model inputs'!AB97)*'Model inputs'!AB114 -> 0.33333333 | F20: =('Model inputs'!F110+'Model inputs'!AB97)*'Model inputs'!AB114 -> 0.5 | G20: =('Model inputs'!G110+'Model inputs'!AB97)*'Model inputs'!AB114 -> 0.61 | H20: =('Model inputs'!H110+'Model inputs'!AB97)*'Model inputs'!AB114 -> 0.7442 | I20: =('Model inputs'!I110+'Model inputs'!AB97)*'Model inputs'!AB114 -> 0.907924 | J20: =('Model inputs'!J110+'Model inputs'!AB97)*'Model inputs'!AB114 -> 1.1076673 | K20: =('Model inputs'!K110+'Model inputs'!AB97)*'Model inputs'!AB114 -> 1.3513541 | L20: =('Model inputs'!L110+'Model inputs'!AB97)*'Model inputs'!AB114 -> 1.648652 | M20: =('Model inputs'!M110+'Model inputs'!AB97)*'Model inputs'!AB114 -> 2.0113554 | N20: =('Model inputs'!N110+'Model inputs'!AB97)*'Model inputs'!AB114 -> 2.4538536 | O20: =('Model inputs'!O110+'Model inputs'!AB97)*'Model inputs'!AB114 -> 2.9937014 | P20: =('Model inputs'!P110+'Model inputs'!AB97)*'Model inputs'!AB114 -> 3.6523157 | Q20: =('Model inputs'!Q110+'Model inputs'!AB97)*'Model inputs'!AB114 -> 4.4558252 | R20: =('Model inputs'!R110+'Model inputs'!AB97)*'Model inputs'!AB114 -> 5.4361067 | S20: =('Model inputs'!S110+'Model inputs'!AB97)*'Model inputs'!AB114 -> 6.6320502 | T20: =('Model inputs'!T110+'Model inputs'!AB97)*'Model inputs'!AB114 -> 8.0911012 | U20: =('Model inputs'!U110+'Model inputs'!AB97)*'Model inputs'!AB114 -> 9.8711435 | V20: =('Model inputs'!V110+'Model inputs'!AB97)*'Model inputs'!AB114 -> 12.042795 | W20: =('Model inputs'!W110+'Model inputs'!AB97)*'Model inputs'!AB114 -> 14.69221 | X20: =('Model inputs'!X110+'Model inputs'!AB97)*'Model inputs'!AB114 -> 17.924496 | Y20: =('Model inputs'!Y110+'Model inputs'!AB97)*'Model inputs'!AB114 -> 21.867885 | Z20: =('Model inputs'!Z110+'Model inputs'!AB97)*'Model inputs'!AB114 -> 26.67882 | AA20: 0
A21: Fixed operating costs · Main Scenario | B21: =SUM('Model inputs'!B89,'Model inputs'!B90,'Model inputs'!B91) -> 300 | D21: =SUM('Model inputs'!D89,'Model inputs'!D90,'Model inputs'!D91) -> 300 | E21: =SUM('Model inputs'!E89,'Model inputs'!E90,'Model inputs'!E91) -> 300 | F21: =SUM('Model inputs'!F89,'Model inputs'!F90,'Model inputs'!F91) -> 300 | G21: =SUM('Model inputs'!G89,'Model inputs'!G90,'Model inputs'!G91) -> 300 | H21: =SUM('Model inputs'!H89,'Model inputs'!H90,'Model inputs'!H91) -> 300 | I21: =SUM('Model inputs'!I89,'Model inputs'!I90,'Model inputs'!I91) -> 300 | J21: =SUM('Model inputs'!J89,'Model inputs'!J90,'Model inputs'!J91) -> 300 | K21: =SUM('Model inputs'!K89,'Model inputs'!K90,'Model inputs'!K91) -> 300 | ... AA21: =SUM('Model inputs'!AA89,'Model inputs'!AA90,'Model inputs'!AA91) -> 0
A22: Fixed operating costs · Upshift — Upside | B22: =SUM('Model inputs'!B93,'Model inputs'!B94,'Model inputs'!B95) -> 300 | D22: =SUM('Model inputs'!D93,'Model inputs'!D94,'Model inputs'!D95) -> 300 | E22: =SUM('Model inputs'!E93,'Model inputs'!E94,'Model inputs'!E95) -> 300 | F22: =SUM('Model inputs'!F93,'Model inputs'!F94,'Model inputs'!F95) -> 300 | G22: =SUM('Model inputs'!G93,'Model inputs'!G94,'Model inputs'!G95) -> 300 | H22: =SUM('Model inputs'!H93,'Model inputs'!H94,'Model inputs'!H95) -> 300 | I22: =SUM('Model inputs'!I93,'Model inputs'!I94,'Model inputs'!I95) -> 300 | J22: =SUM('Model inputs'!J93,'Model inputs'!J94,'Model inputs'!J95) -> 300 | K22: =SUM('Model inputs'!K93,'Model inputs'!K94,'Model inputs'!K95) -> 300 | ... AA22: =SUM('Model inputs'!AA93,'Model inputs'!AA94,'Model inputs'!AA95) -> 0
A23: Forecast month · Base and upside comparison · Main Scenario | B23: =DATEDIF(DATE(2026,10,1),DATE(2028,9,1),"M")+1 -> 24 | D23: =DATEDIF(DATE(2026,10,1),DATE(2026,10,1),"M")+1 -> 1 | E23: =DATEDIF(DATE(2026,10,1),DATE(2026,11,1),"M")+1 -> 2 | F23: =DATEDIF(DATE(2026,10,1),DATE(2026,12,1),"M")+1 -> 3 | G23: =DATEDIF(DATE(2026,10,1),DATE(2027,1,1),"M")+1 -> 4 | H23: =DATEDIF(DATE(2026,10,1),DATE(2027,2,1),"M")+1 -> 5 | I23: =DATEDIF(DATE(2026,10,1),DATE(2027,3,1),"M")+1 -> 6 | J23: =DATEDIF(DATE(2026,10,1),DATE(2027,4,1),"M")+1 -> 7 | K23: =DATEDIF(DATE(2026,10,1),DATE(2027,5,1),"M")+1 -> 8 | L23: =DATEDIF(DATE(2026,10,1),DATE(2027,6,1),"M")+1 -> 9 | M23: =DATEDIF(DATE(2026,10,1),DATE(2027,7,1),"M")+1 -> 10 | N23: =DATEDIF(DATE(2026,10,1),DATE(2027,8,1),"M")+1 -> 11 | O23: =DATEDIF(DATE(2026,10,1),DATE(2027,9,1),"M")+1 -> 12 | P23: =DATEDIF(DATE(2026,10,1),DATE(2027,10,1),"M")+1 -> 13 | Q23: =DATEDIF(DATE(2026,10,1),DATE(2027,11,1),"M")+1 -> 14 | R23: =DATEDIF(DATE(2026,10,1),DATE(2027,12,1),"M")+1 -> 15 | S23: =DATEDIF(DATE(2026,10,1),DATE(2028,1,1),"M")+1 -> 16 | T23: =DATEDIF(DATE(2026,10,1),DATE(2028,2,1),"M")+1 -> 17 | U23: =DATEDIF(DATE(2026,10,1),DATE(2028,3,1),"M")+1 -> 18 | V23: =DATEDIF(DATE(2026,10,1),DATE(2028,4,1),"M")+1 -> 19 | W23: =DATEDIF(DATE(2026,10,1),DATE(2028,5,1),"M")+1 -> 20 | X23: =DATEDIF(DATE(2026,10,1),DATE(2028,6,1),"M")+1 -> 21 | Y23: =DATEDIF(DATE(2026,10,1),DATE(2028,7,1),"M")+1 -> 22 | Z23: =DATEDIF(DATE(2026,10,1),DATE(2028,8,1),"M")+1 -> 23 | AA23: 0
A24: Forecast month · Upshift — Upside | B24: =DATEDIF(DATE(2026,10,1),DATE(2028,9,1),"M")+1 -> 24 | D24: =DATEDIF(DATE(2026,10,1),DATE(2026,10,1),"M")+1 -> 1 | E24: =DATEDIF(DATE(2026,10,1),DATE(2026,11,1),"M")+1 -> 2 | F24: =DATEDIF(DATE(2026,10,1),DATE(2026,12,1),"M")+1 -> 3 | G24: =DATEDIF(DATE(2026,10,1),DATE(2027,1,1),"M")+1 -> 4 | H24: =DATEDIF(DATE(2026,10,1),DATE(2027,2,1),"M")+1 -> 5 | I24: =DATEDIF(DATE(2026,10,1),DATE(2027,3,1),"M")+1 -> 6 | J24: =DATEDIF(DATE(2026,10,1),DATE(2027,4,1),"M")+1 -> 7 | K24: =DATEDIF(DATE(2026,10,1),DATE(2027,5,1),"M")+1 -> 8 | L24: =DATEDIF(DATE(2026,10,1),DATE(2027,6,1),"M")+1 -> 9 | M24: =DATEDIF(DATE(2026,10,1),DATE(2027,7,1),"M")+1 -> 10 | N24: =DATEDIF(DATE(2026,10,1),DATE(2027,8,1),"M")+1 -> 11 | O24: =DATEDIF(DATE(2026,10,1),DATE(2027,9,1),"M")+1 -> 12 | P24: =DATEDIF(DATE(2026,10,1),DATE(2027,10,1),"M")+1 -> 13 | Q24: =DATEDIF(DATE(2026,10,1),DATE(2027,11,1),"M")+1 -> 14 | R24: =DATEDIF(DATE(2026,10,1),DATE(2027,12,1),"M")+1 -> 15 | S24: =DATEDIF(DATE(2026,10,1),DATE(2028,1,1),"M")+1 -> 16 | T24: =DATEDIF(DATE(2026,10,1),DATE(2028,2,1),"M")+1 -> 17 | U24: =DATEDIF(DATE(2026,10,1),DATE(2028,3,1),"M")+1 -> 18 | V24: =DATEDIF(DATE(2026,10,1),DATE(2028,4,1),"M")+1 -> 19 | W24: =DATEDIF(DATE(2026,10,1),DATE(2028,5,1),"M")+1 -> 20 | X24: =DATEDIF(DATE(2026,10,1),DATE(2028,6,1),"M")+1 -> 21 | Y24: =DATEDIF(DATE(2026,10,1),DATE(2028,7,1),"M")+1 -> 22 | Z24: =DATEDIF(DATE(2026,10,1),DATE(2028,8,1),"M")+1 -> 23 | AA24: 0
A25: Founder funding required to date · Decision summary · Main Scenario | B25: =MAX(IF(IF(IF(ISERROR('Model inputs'!B23=1),'Model inputs'!B23=1,IF('Model inputs'!B23="","",'Model inputs'!B23=1))="",FALSE,IF(ISERROR('Model inputs'!B23=1),'Model inputs'!B23=1,IF('Model inputs'!B23="","",'Model inputs'!B23=1))),0,IF('Model inputs'!Z25="","",'Model inputs'!Z25)),-'Model inputs'!B68,0) -> 144 | D25: =MAX(IF(IF(IF(ISERROR('Model inputs'!D23=1),'Model inputs'!D23=1,IF('Model inputs'!D23="","",'Model inputs'!D23=1))="",FALSE,IF(ISERROR('Model inputs'!D23=1),'Model inputs'!D23=1,IF('Model inputs'!D23="","",'Model inputs'!D23=1))),0,IF('Model inputs'!AA25="","",'Model inputs'!AA25)),-'Model inputs'!D68,0) -> 144 | E25: =MAX(IF(IF(IF(ISERROR('Model inputs'!E23=1),'Model inputs'!E23=1,IF('Model inputs'!E23="","",'Model inputs'!E23=1))="",FALSE,IF(ISERROR('Model inputs'!E23=1),'Model inputs'!E23=1,IF('Model inputs'!E23="","",'Model inputs'!E23=1))),0,IF('Model inputs'!D25="","",'Model inputs'!D25)),-'Model inputs'!E68,0) -> 144 | F25: =MAX(IF(IF(IF(ISERROR('Model inputs'!F23=1),'Model inputs'!F23=1,IF('Model inputs'!F23="","",'Model inputs'!F23=1))="",FALSE,IF(ISERROR('Model inputs'!F23=1),'Model inputs'!F23=1,IF('Model inputs'!F23="","",'Model inputs'!F23=1))),0,IF('Model inputs'!E25="","",'Model inputs'!E25)),-'Model inputs'!F68,0) -> 144 | G25: =MAX(IF(IF(IF(ISERROR('Model inputs'!G23=1),'Model inputs'!G23=1,IF('Model inputs'!G23="","",'Model inputs'!G23=1))="",FALSE,IF(ISERROR('Model inputs'!G23=1),'Model inputs'!G23=1,IF('Model inputs'!G23="","",'Model inputs'!G23=1))),0,IF('Model inputs'!F25="","",'Model inputs'!F25)),-'Model inputs'!G68,0) -> 144 | H25: =MAX(IF(IF(IF(ISERROR('Model inputs'!H23=1),'Model inputs'!H23=1,IF('Model inputs'!H23="","",'Model inputs'!H23=1))="",FALSE,IF(ISERROR('Model inputs'!H23=1),'Model inputs'!H23=1,IF('Model inputs'!H23="","",'Model inputs'!H23=1))),0,IF('Model inputs'!G25="","",'Model inputs'!G25)),-'Model inputs'!H68,0) -> 144 | I25: =MAX(IF(IF(IF(ISERROR('Model inputs'!I23=1),'Model inputs'!I23=1,IF('Model inputs'!I23="","",'Model inputs'!I23=1))="",FALSE,IF(ISERROR('Model inputs'!I23=1),'Model inputs'!I23=1,IF('Model inputs'!I23="","",'Model inputs'!I23=1))),0,IF('Model inputs'!H25="","",'Model inputs'!H25)),-'Model inputs'!I68,0) -> 144 | J25: =MAX(IF(IF(IF(ISERROR('Model inputs'!J23=1),'Model inputs'!J23=1,IF('Model inputs'!J23="","",'Model inputs'!J23=1))="",FALSE,IF(ISERROR('Model inputs'!J23=1),'Model inputs'!J23=1,IF('Model inputs'!J23="","",'Model inputs'!J23=1))),0,IF('Model inputs'!I25="","",'Model inputs'!I25)),-'Model inputs'!J68,0) -> 144 | K25: =MAX(IF(IF(IF(ISERROR('Model inputs'!K23=1),'Model inputs'!K23=1,IF('Model inputs'!K23="","",'Model inputs'!K23=1))="",FALSE,IF(ISERROR('Model inputs'!K23=1),'Model inputs'!K23=1,IF('Model inputs'!K23="","",'Model inputs'!K23=1))),0,IF('Model inputs'!J25="","",'Model inputs'!J25)),-'Model inputs'!K68,0) -> 144 | L25: =MAX(IF(IF(IF(ISERROR('Model inputs'!L23=1),'Model inputs'!L23=1,IF('Model inputs'!L23="","",'Model inputs'!L23=1))="",FALSE,IF(ISERROR('Model inputs'!L23=1),'Model inputs'!L23=1,IF('Model inputs'!L23="","",'Model inputs'!L23=1))),0,IF('Model inputs'!K25="","",'Model inputs'!K25)),-'Model inputs'!L68,0) -> 144 | ... Z25: =MAX(IF(IF(IF(ISERROR('Model inputs'!Z23=1),'Model inputs'!Z23=1,IF('Model inputs'!Z23="","",'Model inputs'!Z23=1))="",FALSE,IF(ISERROR('Model inputs'!Z23=1),'Model inputs'!Z23=1,IF('Model inputs'!Z23="","",'Model inputs'!Z23=1))),0,IF('Model inputs'!Y25="","",'Model inputs'!Y25)),-'Model inputs'!Z68,0) -> 144 | AA25: 0
A26: Founder funding required to date · Upshift — Upside | B26: =MAX(IF(IF(IF(ISERROR('Model inputs'!B24=1),'Model inputs'!B24=1,IF('Model inputs'!B24="","",'Model inputs'!B24=1))="",FALSE,IF(ISERROR('Model inputs'!B24=1),'Model inputs'!B24=1,IF('Model inputs'!B24="","",'Model inputs'!B24=1))),0,IF('Model inputs'!Z26="","",'Model inputs'!Z26)),-'Model inputs'!B69,0) -> 0 | D26: =MAX(IF(IF(IF(ISERROR('Model inputs'!D24=1),'Model inputs'!D24=1,IF('Model inputs'!D24="","",'Model inputs'!D24=1))="",FALSE,IF(ISERROR('Model inputs'!D24=1),'Model inputs'!D24=1,IF('Model inputs'!D24="","",'Model inputs'!D24=1))),0,IF('Model inputs'!AA26="","",'Model inputs'!AA26)),-'Model inputs'!D69,0) -> 0 | E26: =MAX(IF(IF(IF(ISERROR('Model inputs'!E24=1),'Model inputs'!E24=1,IF('Model inputs'!E24="","",'Model inputs'!E24=1))="",FALSE,IF(ISERROR('Model inputs'!E24=1),'Model inputs'!E24=1,IF('Model inputs'!E24="","",'Model inputs'!E24=1))),0,IF('Model inputs'!D26="","",'Model inputs'!D26)),-'Model inputs'!E69,0) -> 0 | F26: =MAX(IF(IF(IF(ISERROR('Model inputs'!F24=1),'Model inputs'!F24=1,IF('Model inputs'!F24="","",'Model inputs'!F24=1))="",FALSE,IF(ISERROR('Model inputs'!F24=1),'Model inputs'!F24=1,IF('Model inputs'!F24="","",'Model inputs'!F24=1))),0,IF('Model inputs'!E26="","",'Model inputs'!E26)),-'Model inputs'!F69,0) -> 0 | G26: =MAX(IF(IF(IF(ISERROR('Model inputs'!G24=1),'Model inputs'!G24=1,IF('Model inputs'!G24="","",'Model inputs'!G24=1))="",FALSE,IF(ISERROR('Model inputs'!G24=1),'Model inputs'!G24=1,IF('Model inputs'!G24="","",'Model inputs'!G24=1))),0,IF('Model inputs'!F26="","",'Model inputs'!F26)),-'Model inputs'!G69,0) -> 0 | H26: =MAX(IF(IF(IF(ISERROR('Model inputs'!H24=1),'Model inputs'!H24=1,IF('Model inputs'!H24="","",'Model inputs'!H24=1))="",FALSE,IF(ISERROR('Model inputs'!H24=1),'Model inputs'!H24=1,IF('Model inputs'!H24="","",'Model inputs'!H24=1))),0,IF('Model inputs'!G26="","",'Model inputs'!G26)),-'Model inputs'!H69,0) -> 0 | I26: =MAX(IF(IF(IF(ISERROR('Model inputs'!I24=1),'Model inputs'!I24=1,IF('Model inputs'!I24="","",'Model inputs'!I24=1))="",FALSE,IF(ISERROR('Model inputs'!I24=1),'Model inputs'!I24=1,IF('Model inputs'!I24="","",'Model inputs'!I24=1))),0,IF('Model inputs'!H26="","",'Model inputs'!H26)),-'Model inputs'!I69,0) -> 0 | J26: =MAX(IF(IF(IF(ISERROR('Model inputs'!J24=1),'Model inputs'!J24=1,IF('Model inputs'!J24="","",'Model inputs'!J24=1))="",FALSE,IF(ISERROR('Model inputs'!J24=1),'Model inputs'!J24=1,IF('Model inputs'!J24="","",'Model inputs'!J24=1))),0,IF('Model inputs'!I26="","",'Model inputs'!I26)),-'Model inputs'!J69,0) -> 0 | K26: =MAX(IF(IF(IF(ISERROR('Model inputs'!K24=1),'Model inputs'!K24=1,IF('Model inputs'!K24="","",'Model inputs'!K24=1))="",FALSE,IF(ISERROR('Model inputs'!K24=1),'Model inputs'!K24=1,IF('Model inputs'!K24="","",'Model inputs'!K24=1))),0,IF('Model inputs'!J26="","",'Model inputs'!J26)),-'Model inputs'!K69,0) -> 0 | L26: =MAX(IF(IF(IF(ISERROR('Model inputs'!L24=1),'Model inputs'!L24=1,IF('Model inputs'!L24="","",'Model inputs'!L24=1))="",FALSE,IF(ISERROR('Model inputs'!L24=1),'Model inputs'!L24=1,IF('Model inputs'!L24="","",'Model inputs'!L24=1))),0,IF('Model inputs'!K26="","",'Model inputs'!K26)),-'Model inputs'!L69,0) -> 0 | ... Z26: =MAX(IF(IF(IF(ISERROR('Model inputs'!Z24=1),'Model inputs'!Z24=1,IF('Model inputs'!Z24="","",'Model inputs'!Z24=1))="",FALSE,IF(ISERROR('Model inputs'!Z24=1),'Model inputs'!Z24=1,IF('Model inputs'!Z24="","",'Model inputs'!Z24=1))),0,IF('Model inputs'!Y26="","",'Model inputs'!Y26)),-'Model inputs'!Z69,0) -> 0 | AA26: 0
A27: Founder monthly salary | C27: 0
A28: Founder monthly salary > Harsh — founder | C28: =0 -> 0
A29: Founder payroll · Main Scenario | B29: =SUM('Model inputs'!B130) -> 0 | D29: =SUM('Model inputs'!D130) -> 0 | E29: =SUM('Model inputs'!E130) -> 0 | F29: =SUM('Model inputs'!F130) -> 0 | G29: =SUM('Model inputs'!G130) -> 0 | H29: =SUM('Model inputs'!H130) -> 0 | I29: =SUM('Model inputs'!I130) -> 0 | J29: =SUM('Model inputs'!J130) -> 0 | K29: =SUM('Model inputs'!K130) -> 0 | ... AA29: =SUM('Model inputs'!AA130) -> 0
A30: Founder payroll · Upshift — Upside | B30: =SUM('Model inputs'!B132) -> 0 | D30: =SUM('Model inputs'!D132) -> 0 | E30: =SUM('Model inputs'!E132) -> 0 | F30: =SUM('Model inputs'!F132) -> 0 | G30: =SUM('Model inputs'!G132) -> 0 | H30: =SUM('Model inputs'!H132) -> 0 | I30: =SUM('Model inputs'!I132) -> 0 | J30: =SUM('Model inputs'!J132) -> 0 | K30: =SUM('Model inputs'!K132) -> 0 | ... AA30: =SUM('Model inputs'!AA132) -> 0
A31: Gross profit · Main Scenario | B31: ='Model inputs'!B61-'Model inputs'!B82 -> 5056.201 | D31: ='Model inputs'!D61-'Model inputs'!D82 -> 156 | E31: ='Model inputs'!E61-'Model inputs'!E82 -> 312 | F31: ='Model inputs'!F61-'Model inputs'!F82 -> 468 | G31: ='Model inputs'!G61-'Model inputs'!G82 -> 524.16 | H31: ='Model inputs'!H61-'Model inputs'!H82 -> 587.0592 | I31: ='Model inputs'!I61-'Model inputs'!I82 -> 657.5063 | J31: ='Model inputs'!J61-'Model inputs'!J82 -> 736.40706 | K31: ='Model inputs'!K61-'Model inputs'!K82 -> 824.77591 | ... Z31: ='Model inputs'!Z61-'Model inputs'!Z82 -> 4514.4652 | AA31: 0
A32: Gross profit · Upshift — Upside | B32: ='Model inputs'!B118-'Model inputs'!B83 -> 76162.696 | D32: ='Model inputs'!D118-'Model inputs'!D83 -> 390 | E32: ='Model inputs'!E118-'Model inputs'!E83 -> 780 | F32: ='Model inputs'!F118-'Model inputs'!F83 -> 1170 | G32: ='Model inputs'!G118-'Model inputs'!G83 -> 1427.4 | H32: ='Model inputs'!H118-'Model inputs'!H83 -> 1741.428 | I32: ='Model inputs'!I118-'Model inputs'!I83 -> 2124.5422 | J32: ='Model inputs'!J118-'Model inputs'!J83 -> 2591.9414 | K32: ='Model inputs'!K118-'Model inputs'!K83 -> 3162.1686 | ... Z32: ='Model inputs'!Z118-'Model inputs'!Z83 -> 62428.439 | AA32: 0
A33: Inference costs · Main Scenario | B33: ='Model inputs'!B72*'Model inputs'!C9 -> 216.07697 | D33: ='Model inputs'!D72*'Model inputs'!C9 -> 6.6666667 | E33: ='Model inputs'!E72*'Model inputs'!C9 -> 13.333333 | F33: ='Model inputs'!F72*'Model inputs'!C9 -> 20 | G33: ='Model inputs'!G72*'Model inputs'!C9 -> 22.4 | H33: ='Model inputs'!H72*'Model inputs'!C9 -> 25.088 | I33: ='Model inputs'!I72*'Model inputs'!C9 -> 28.09856 | J33: ='Model inputs'!J72*'Model inputs'!C9 -> 31.470387 | K33: ='Model inputs'!K72*'Model inputs'!C9 -> 35.246834 | L33: ='Model inputs'!L72*'Model inputs'!C9 -> 39.476454 | M33: ='Model inputs'!M72*'Model inputs'!C9 -> 44.213628 | N33: ='Model inputs'!N72*'Model inputs'!C9 -> 49.519264 | O33: ='Model inputs'!O72*'Model inputs'!C9 -> 55.461575 | P33: ='Model inputs'!P72*'Model inputs'!C9 -> 62.116964 | Q33: ='Model inputs'!Q72*'Model inputs'!C9 -> 69.571 | R33: ='Model inputs'!R72*'Model inputs'!C9 -> 77.91952 | S33: ='Model inputs'!S72*'Model inputs'!C9 -> 87.269862 | T33: ='Model inputs'!T72*'Model inputs'!C9 -> 97.742246 | U33: ='Model inputs'!U72*'Model inputs'!C9 -> 109.47132 | V33: ='Model inputs'!V72*'Model inputs'!C9 -> 122.60787 | W33: ='Model inputs'!W72*'Model inputs'!C9 -> 137.32082 | X33: ='Model inputs'!X72*'Model inputs'!C9 -> 153.79932 | Y33: ='Model inputs'!Y72*'Model inputs'!C9 -> 172.25523 | Z33: ='Model inputs'!Z72*'Model inputs'!C9 -> 192.92586 | AA33: 0
A34: Inference costs · Upshift — Upside | B34: ='Model inputs'!B73*'Model inputs'!AB75 -> 3254.816 | D34: ='Model inputs'!D73*'Model inputs'!AB75 -> 16.666667 | E34: ='Model inputs'!E73*'Model inputs'!AB75 -> 33.333333 | F34: ='Model inputs'!F73*'Model inputs'!AB75 -> 50 | G34: ='Model inputs'!G73*'Model inputs'!AB75 -> 61 | H34: ='Model inputs'!H73*'Model inputs'!AB75 -> 74.42 | I34: ='Model inputs'!I73*'Model inputs'!AB75 -> 90.7924 | J34: ='Model inputs'!J73*'Model inputs'!AB75 -> 110.76673 | K34: ='Model inputs'!K73*'Model inputs'!AB75 -> 135.13541 | L34: ='Model inputs'!L73*'Model inputs'!AB75 -> 164.8652 | M34: ='Model inputs'!M73*'Model inputs'!AB75 -> 201.13554 | N34: ='Model inputs'!N73*'Model inputs'!AB75 -> 245.38536 | O34: ='Model inputs'!O73*'Model inputs'!AB75 -> 299.37014 | P34: ='Model inputs'!P73*'Model inputs'!AB75 -> 365.23157 | Q34: ='Model inputs'!Q73*'Model inputs'!AB75 -> 445.58252 | R34: ='Model inputs'!R73*'Model inputs'!AB75 -> 543.61067 | S34: ='Model inputs'!S73*'Model inputs'!AB75 -> 663.20502 | T34: ='Model inputs'!T73*'Model inputs'!AB75 -> 809.11012 | U34: ='Model inputs'!U73*'Model inputs'!AB75 -> 987.11435 | V34: ='Model inputs'!V73*'Model inputs'!AB75 -> 1204.2795 | W34: ='Model inputs'!W73*'Model inputs'!AB75 -> 1469.221 | X34: ='Model inputs'!X73*'Model inputs'!AB75 -> 1792.4496 | Y34: ='Model inputs'!Y73*'Model inputs'!AB75 -> 2186.7885 | Z34: ='Model inputs'!Z73*'Model inputs'!AB75 -> 2667.882 | AA34: 0
A35: Investment recovered marker | B35: =IF(IF(IF(ISERROR('Model inputs'!B68>='Model inputs'!AB64),'Model inputs'!B68>='Model inputs'!AB64,IF(OR('Model inputs'!B68="",'Model inputs'!AB64=""),"",'Model inputs'!B68>='Model inputs'!AB64))="",FALSE,IF(ISERROR('Model inputs'!B68>='Model inputs'!AB64),'Model inputs'!B68>='Model inputs'!AB64,IF(OR('Model inputs'!B68="",'Model inputs'!AB64=""),"",'Model inputs'!B68>='Model inputs'!AB64))),DATE(2028,9,1),"") -> 46997 | D35: =IF(IF(IF(ISERROR('Model inputs'!D68>='Model inputs'!AB64),'Model inputs'!D68>='Model inputs'!AB64,IF(OR('Model inputs'!D68="",'Model inputs'!AB64=""),"",'Model inputs'!D68>='Model inputs'!AB64))="",FALSE,IF(ISERROR('Model inputs'!D68>='Model inputs'!AB64),'Model inputs'!D68>='Model inputs'!AB64,IF(OR('Model inputs'!D68="",'Model inputs'!AB64=""),"",'Model inputs'!D68>='Model inputs'!AB64))),DATE(2026,10,1),"") | E35: =IF(IF(IF(ISERROR('Model inputs'!E68>='Model inputs'!AB64),'Model inputs'!E68>='Model inputs'!AB64,IF(OR('Model inputs'!E68="",'Model inputs'!AB64=""),"",'Model inputs'!E68>='Model inputs'!AB64))="",FALSE,IF(ISERROR('Model inputs'!E68>='Model inputs'!AB64),'Model inputs'!E68>='Model inputs'!AB64,IF(OR('Model inputs'!E68="",'Model inputs'!AB64=""),"",'Model inputs'!E68>='Model inputs'!AB64))),DATE(2026,11,1),"") | F35: =IF(IF(IF(ISERROR('Model inputs'!F68>='Model inputs'!AB64),'Model inputs'!F68>='Model inputs'!AB64,IF(OR('Model inputs'!F68="",'Model inputs'!AB64=""),"",'Model inputs'!F68>='Model inputs'!AB64))="",FALSE,IF(ISERROR('Model inputs'!F68>='Model inputs'!AB64),'Model inputs'!F68>='Model inputs'!AB64,IF(OR('Model inputs'!F68="",'Model inputs'!AB64=""),"",'Model inputs'!F68>='Model inputs'!AB64))),DATE(2026,12,1),"") -> 46357 | G35: =IF(IF(IF(ISERROR('Model inputs'!G68>='Model inputs'!AB64),'Model inputs'!G68>='Model inputs'!AB64,IF(OR('Model inputs'!G68="",'Model inputs'!AB64=""),"",'Model inputs'!G68>='Model inputs'!AB64))="",FALSE,IF(ISERROR('Model inputs'!G68>='Model inputs'!AB64),'Model inputs'!G68>='Model inputs'!AB64,IF(OR('Model inputs'!G68="",'Model inputs'!AB64=""),"",'Model inputs'!G68>='Model inputs'!AB64))),DATE(2027,1,1),"") -> 46388 | H35: =IF(IF(IF(ISERROR('Model inputs'!H68>='Model inputs'!AB64),'Model inputs'!H68>='Model inputs'!AB64,IF(OR('Model inputs'!H68="",'Model inputs'!AB64=""),"",'Model inputs'!H68>='Model inputs'!AB64))="",FALSE,IF(ISERROR('Model inputs'!H68>='Model inputs'!AB64),'Model inputs'!H68>='Model inputs'!AB64,IF(OR('Model inputs'!H68="",'Model inputs'!AB64=""),"",'Model inputs'!H68>='Model inputs'!AB64))),DATE(2027,2,1),"") -> 46419 | I35: =IF(IF(IF(ISERROR('Model inputs'!I68>='Model inputs'!AB64),'Model inputs'!I68>='Model inputs'!AB64,IF(OR('Model inputs'!I68="",'Model inputs'!AB64=""),"",'Model inputs'!I68>='Model inputs'!AB64))="",FALSE,IF(ISERROR('Model inputs'!I68>='Model inputs'!AB64),'Model inputs'!I68>='Model inputs'!AB64,IF(OR('Model inputs'!I68="",'Model inputs'!AB64=""),"",'Model inputs'!I68>='Model inputs'!AB64))),DATE(2027,3,1),"") -> 46447 | J35: =IF(IF(IF(ISERROR('Model inputs'!J68>='Model inputs'!AB64),'Model inputs'!J68>='Model inputs'!AB64,IF(OR('Model inputs'!J68="",'Model inputs'!AB64=""),"",'Model inputs'!J68>='Model inputs'!AB64))="",FALSE,IF(ISERROR('Model inputs'!J68>='Model inputs'!AB64),'Model inputs'!J68>='Model inputs'!AB64,IF(OR('Model inputs'!J68="",'Model inputs'!AB64=""),"",'Model inputs'!J68>='Model inputs'!AB64))),DATE(2027,4,1),"") -> 46478 | K35: =IF(IF(IF(ISERROR('Model inputs'!K68>='Model inputs'!AB64),'Model inputs'!K68>='Model inputs'!AB64,IF(OR('Model inputs'!K68="",'Model inputs'!AB64=""),"",'Model inputs'!K68>='Model inputs'!AB64))="",FALSE,IF(ISERROR('Model inputs'!K68>='Model inputs'!AB64),'Model inputs'!K68>='Model inputs'!AB64,IF(OR('Model inputs'!K68="",'Model inputs'!AB64=""),"",'Model inputs'!K68>='Model inputs'!AB64))),DATE(2027,5,1),"") -> 46508 | L35: =IF(IF(IF(ISERROR('Model inputs'!L68>='Model inputs'!AB64),'Model inputs'!L68>='Model inputs'!AB64,IF(OR('Model inputs'!L68="",'Model inputs'!AB64=""),"",'Model inputs'!L68>='Model inputs'!AB64))="",FALSE,IF(ISERROR('Model inputs'!L68>='Model inputs'!AB64),'Model inputs'!L68>='Model inputs'!AB64,IF(OR('Model inputs'!L68="",'Model inputs'!AB64=""),"",'Model inputs'!L68>='Model inputs'!AB64))),DATE(2027,6,1),"") -> 46539 | M35: =IF(IF(IF(ISERROR('Model inputs'!M68>='Model inputs'!AB64),'Model inputs'!M68>='Model inputs'!AB64,IF(OR('Model inputs'!M68="",'Model inputs'!AB64=""),"",'Model inputs'!M68>='Model inputs'!AB64))="",FALSE,IF(ISERROR('Model inputs'!M68>='Model inputs'!AB64),'Model inputs'!M68>='Model inputs'!AB64,IF(OR('Model inputs'!M68="",'Model inputs'!AB64=""),"",'Model inputs'!M68>='Model inputs'!AB64))),DATE(2027,7,1),"") -> 46569 | N35: =IF(IF(IF(ISERROR('Model inputs'!N68>='Model inputs'!AB64),'Model inputs'!N68>='Model inputs'!AB64,IF(OR('Model inputs'!N68="",'Model inputs'!AB64=""),"",'Model inputs'!N68>='Model inputs'!AB64))="",FALSE,IF(ISERROR('Model inputs'!N68>='Model inputs'!AB64),'Model inputs'!N68>='Model inputs'!AB64,IF(OR('Model inputs'!N68="",'Model inputs'!AB64=""),"",'Model inputs'!N68>='Model inputs'!AB64))),DATE(2027,8,1),"") -> 46600 | O35: =IF(IF(IF(ISERROR('Model inputs'!O68>='Model inputs'!AB64),'Model inputs'!O68>='Model inputs'!AB64,IF(OR('Model inputs'!O68="",'Model inputs'!AB64=""),"",'Model inputs'!O68>='Model inputs'!AB64))="",FALSE,IF(ISERROR('Model inputs'!O68>='Model inputs'!AB64),'Model inputs'!O68>='Model inputs'!AB64,IF(OR('Model inputs'!O68="",'Model inputs'!AB64=""),"",'Model inputs'!O68>='Model inputs'!AB64))),DATE(2027,9,1),"") -> 46631 | P35: =IF(IF(IF(ISERROR('Model inputs'!P68>='Model inputs'!AB64),'Model inputs'!P68>='Model inputs'!AB64,IF(OR('Model inputs'!P68="",'Model inputs'!AB64=""),"",'Model inputs'!P68>='Model inputs'!AB64))="",FALSE,IF(ISERROR('Model inputs'!P68>='Model inputs'!AB64),'Model inputs'!P68>='Model inputs'!AB64,IF(OR('Model inputs'!P68="",'Model inputs'!AB64=""),"",'Model inputs'!P68>='Model inputs'!AB64))),DATE(2027,10,1),"") -> 46661 | Q35: =IF(IF(IF(ISERROR('Model inputs'!Q68>='Model inputs'!AB64),'Model inputs'!Q68>='Model inputs'!AB64,IF(OR('Model inputs'!Q68="",'Model inputs'!AB64=""),"",'Model inputs'!Q68>='Model inputs'!AB64))="",FALSE,IF(ISERROR('Model inputs'!Q68>='Model inputs'!AB64),'Model inputs'!Q68>='Model inputs'!AB64,IF(OR('Model inputs'!Q68="",'Model inputs'!AB64=""),"",'Model inputs'!Q68>='Model inputs'!AB64))),DATE(2027,11,1),"") -> 46692 | R35: =IF(IF(IF(ISERROR('Model inputs'!R68>='Model inputs'!AB64),'Model inputs'!R68>='Model inputs'!AB64,IF(OR('Model inputs'!R68="",'Model inputs'!AB64=""),"",'Model inputs'!R68>='Model inputs'!AB64))="",FALSE,IF(ISERROR('Model inputs'!R68>='Model inputs'!AB64),'Model inputs'!R68>='Model inputs'!AB64,IF(OR('Model inputs'!R68="",'Model inputs'!AB64=""),"",'Model inputs'!R68>='Model inputs'!AB64))),DATE(2027,12,1),"") -> 46722 | S35: =IF(IF(IF(ISERROR('Model inputs'!S68>='Model inputs'!AB64),'Model inputs'!S68>='Model inputs'!AB64,IF(OR('Model inputs'!S68="",'Model inputs'!AB64=""),"",'Model inputs'!S68>='Model inputs'!AB64))="",FALSE,IF(ISERROR('Model inputs'!S68>='Model inputs'!AB64),'Model inputs'!S68>='Model inputs'!AB64,IF(OR('Model inputs'!S68="",'Model inputs'!AB64=""),"",'Model inputs'!S68>='Model inputs'!AB64))),DATE(2028,1,1),"") -> 46753 | T35: =IF(IF(IF(ISERROR('Model inputs'!T68>='Model inputs'!AB64),'Model inputs'!T68>='Model inputs'!AB64,IF(OR('Model inputs'!T68="",'Model inputs'!AB64=""),"",'Model inputs'!T68>='Model inputs'!AB64))="",FALSE,IF(ISERROR('Model inputs'!T68>='Model inputs'!AB64),'Model inputs'!T68>='Model inputs'!AB64,IF(OR('Model inputs'!T68="",'Model inputs'!AB64=""),"",'Model inputs'!T68>='Model inputs'!AB64))),DATE(2028,2,1),"") -> 46784 | U35: =IF(IF(IF(ISERROR('Model inputs'!U68>='Model inputs'!AB64),'Model inputs'!U68>='Model inputs'!AB64,IF(OR('Model inputs'!U68="",'Model inputs'!AB64=""),"",'Model inputs'!U68>='Model inputs'!AB64))="",FALSE,IF(ISERROR('Model inputs'!U68>='Model inputs'!AB64),'Model inputs'!U68>='Model inputs'!AB64,IF(OR('Model inputs'!U68="",'Model inputs'!AB64=""),"",'Model inputs'!U68>='Model inputs'!AB64))),DATE(2028,3,1),"") -> 46813 | V35: =IF(IF(IF(ISERROR('Model inputs'!V68>='Model inputs'!AB64),'Model inputs'!V68>='Model inputs'!AB64,IF(OR('Model inputs'!V68="",'Model inputs'!AB64=""),"",'Model inputs'!V68>='Model inputs'!AB64))="",FALSE,IF(ISERROR('Model inputs'!V68>='Model inputs'!AB64),'Model inputs'!V68>='Model inputs'!AB64,IF(OR('Model inputs'!V68="",'Model inputs'!AB64=""),"",'Model inputs'!V68>='Model inputs'!AB64))),DATE(2028,4,1),"") -> 46844 | W35: =IF(IF(IF(ISERROR('Model inputs'!W68>='Model inputs'!AB64),'Model inputs'!W68>='Model inputs'!AB64,IF(OR('Model inputs'!W68="",'Model inputs'!AB64=""),"",'Model inputs'!W68>='Model inputs'!AB64))="",FALSE,IF(ISERROR('Model inputs'!W68>='Model inputs'!AB64),'Model inputs'!W68>='Model inputs'!AB64,IF(OR('Model inputs'!W68="",'Model inputs'!AB64=""),"",'Model inputs'!W68>='Model inputs'!AB64))),DATE(2028,5,1),"") -> 46874 | X35: =IF(IF(IF(ISERROR('Model inputs'!X68>='Model inputs'!AB64),'Model inputs'!X68>='Model inputs'!AB64,IF(OR('Model inputs'!X68="",'Model inputs'!AB64=""),"",'Model inputs'!X68>='Model inputs'!AB64))="",FALSE,IF(ISERROR('Model inputs'!X68>='Model inputs'!AB64),'Model inputs'!X68>='Model inputs'!AB64,IF(OR('Model inputs'!X68="",'Model inputs'!AB64=""),"",'Model inputs'!X68>='Model inputs'!AB64))),DATE(2028,6,1),"") -> 46905 | Y35: =IF(IF(IF(ISERROR('Model inputs'!Y68>='Model inputs'!AB64),'Model inputs'!Y68>='Model inputs'!AB64,IF(OR('Model inputs'!Y68="",'Model inputs'!AB64=""),"",'Model inputs'!Y68>='Model inputs'!AB64))="",FALSE,IF(ISERROR('Model inputs'!Y68>='Model inputs'!AB64),'Model inputs'!Y68>='Model inputs'!AB64,IF(OR('Model inputs'!Y68="",'Model inputs'!AB64=""),"",'Model inputs'!Y68>='Model inputs'!AB64))),DATE(2028,7,1),"") -> 46935 | Z35: =IF(IF(IF(ISERROR('Model inputs'!Z68>='Model inputs'!AB64),'Model inputs'!Z68>='Model inputs'!AB64,IF(OR('Model inputs'!Z68="",'Model inputs'!AB64=""),"",'Model inputs'!Z68>='Model inputs'!AB64))="",FALSE,IF(ISERROR('Model inputs'!Z68>='Model inputs'!AB64),'Model inputs'!Z68>='Model inputs'!AB64,IF(OR('Model inputs'!Z68="",'Model inputs'!AB64=""),"",'Model inputs'!Z68>='Model inputs'!AB64))),DATE(2028,8,1),"") -> 46966
A36: Migration stress break-even marker | B36: =IF(IF(IF(ISERROR('Model inputs'!B116>=0),'Model inputs'!B116>=0,IF('Model inputs'!B116="","",'Model inputs'!B116>=0))="",FALSE,IF(ISERROR('Model inputs'!B116>=0),'Model inputs'!B116>=0,IF('Model inputs'!B116="","",'Model inputs'!B116>=0))),DATE(2028,9,1),"") -> 46997 | D36: =IF(IF(IF(ISERROR('Model inputs'!D116>=0),'Model inputs'!D116>=0,IF('Model inputs'!D116="","",'Model inputs'!D116>=0))="",FALSE,IF(ISERROR('Model inputs'!D116>=0),'Model inputs'!D116>=0,IF('Model inputs'!D116="","",'Model inputs'!D116>=0))),DATE(2026,10,1),"") | E36: =IF(IF(IF(ISERROR('Model inputs'!E116>=0),'Model inputs'!E116>=0,IF('Model inputs'!E116="","",'Model inputs'!E116>=0))="",FALSE,IF(ISERROR('Model inputs'!E116>=0),'Model inputs'!E116>=0,IF('Model inputs'!E116="","",'Model inputs'!E116>=0))),DATE(2026,11,1),"") | F36: =IF(IF(IF(ISERROR('Model inputs'!F116>=0),'Model inputs'!F116>=0,IF('Model inputs'!F116="","",'Model inputs'!F116>=0))="",FALSE,IF(ISERROR('Model inputs'!F116>=0),'Model inputs'!F116>=0,IF('Model inputs'!F116="","",'Model inputs'!F116>=0))),DATE(2026,12,1),"") -> 46357 | G36: =IF(IF(IF(ISERROR('Model inputs'!G116>=0),'Model inputs'!G116>=0,IF('Model inputs'!G116="","",'Model inputs'!G116>=0))="",FALSE,IF(ISERROR('Model inputs'!G116>=0),'Model inputs'!G116>=0,IF('Model inputs'!G116="","",'Model inputs'!G116>=0))),DATE(2027,1,1),"") -> 46388 | H36: =IF(IF(IF(ISERROR('Model inputs'!H116>=0),'Model inputs'!H116>=0,IF('Model inputs'!H116="","",'Model inputs'!H116>=0))="",FALSE,IF(ISERROR('Model inputs'!H116>=0),'Model inputs'!H116>=0,IF('Model inputs'!H116="","",'Model inputs'!H116>=0))),DATE(2027,2,1),"") -> 46419 | I36: =IF(IF(IF(ISERROR('Model inputs'!I116>=0),'Model inputs'!I116>=0,IF('Model inputs'!I116="","",'Model inputs'!I116>=0))="",FALSE,IF(ISERROR('Model inputs'!I116>=0),'Model inputs'!I116>=0,IF('Model inputs'!I116="","",'Model inputs'!I116>=0))),DATE(2027,3,1),"") -> 46447 | J36: =IF(IF(IF(ISERROR('Model inputs'!J116>=0),'Model inputs'!J116>=0,IF('Model inputs'!J116="","",'Model inputs'!J116>=0))="",FALSE,IF(ISERROR('Model inputs'!J116>=0),'Model inputs'!J116>=0,IF('Model inputs'!J116="","",'Model inputs'!J116>=0))),DATE(2027,4,1),"") -> 46478 | K36: =IF(IF(IF(ISERROR('Model inputs'!K116>=0),'Model inputs'!K116>=0,IF('Model inputs'!K116="","",'Model inputs'!K116>=0))="",FALSE,IF(ISERROR('Model inputs'!K116>=0),'Model inputs'!K116>=0,IF('Model inputs'!K116="","",'Model inputs'!K116>=0))),DATE(2027,5,1),"") -> 46508 | L36: =IF(IF(IF(ISERROR('Model inputs'!L116>=0),'Model inputs'!L116>=0,IF('Model inputs'!L116="","",'Model inputs'!L116>=0))="",FALSE,IF(ISERROR('Model inputs'!L116>=0),'Model inputs'!L116>=0,IF('Model inputs'!L116="","",'Model inputs'!L116>=0))),DATE(2027,6,1),"") -> 46539 | M36: =IF(IF(IF(ISERROR('Model inputs'!M116>=0),'Model inputs'!M116>=0,IF('Model inputs'!M116="","",'Model inputs'!M116>=0))="",FALSE,IF(ISERROR('Model inputs'!M116>=0),'Model inputs'!M116>=0,IF('Model inputs'!M116="","",'Model inputs'!M116>=0))),DATE(2027,7,1),"") -> 46569 | N36: =IF(IF(IF(ISERROR('Model inputs'!N116>=0),'Model inputs'!N116>=0,IF('Model inputs'!N116="","",'Model inputs'!N116>=0))="",FALSE,IF(ISERROR('Model inputs'!N116>=0),'Model inputs'!N116>=0,IF('Model inputs'!N116="","",'Model inputs'!N116>=0))),DATE(2027,8,1),"") -> 46600 | O36: =IF(IF(IF(ISERROR('Model inputs'!O116>=0),'Model inputs'!O116>=0,IF('Model inputs'!O116="","",'Model inputs'!O116>=0))="",FALSE,IF(ISERROR('Model inputs'!O116>=0),'Model inputs'!O116>=0,IF('Model inputs'!O116="","",'Model inputs'!O116>=0))),DATE(2027,9,1),"") -> 46631 | P36: =IF(IF(IF(ISERROR('Model inputs'!P116>=0),'Model inputs'!P116>=0,IF('Model inputs'!P116="","",'Model inputs'!P116>=0))="",FALSE,IF(ISERROR('Model inputs'!P116>=0),'Model inputs'!P116>=0,IF('Model inputs'!P116="","",'Model inputs'!P116>=0))),DATE(2027,10,1),"") -> 46661 | Q36: =IF(IF(IF(ISERROR('Model inputs'!Q116>=0),'Model inputs'!Q116>=0,IF('Model inputs'!Q116="","",'Model inputs'!Q116>=0))="",FALSE,IF(ISERROR('Model inputs'!Q116>=0),'Model inputs'!Q116>=0,IF('Model inputs'!Q116="","",'Model inputs'!Q116>=0))),DATE(2027,11,1),"") -> 46692 | R36: =IF(IF(IF(ISERROR('Model inputs'!R116>=0),'Model inputs'!R116>=0,IF('Model inputs'!R116="","",'Model inputs'!R116>=0))="",FALSE,IF(ISERROR('Model inputs'!R116>=0),'Model inputs'!R116>=0,IF('Model inputs'!R116="","",'Model inputs'!R116>=0))),DATE(2027,12,1),"") -> 46722 | S36: =IF(IF(IF(ISERROR('Model inputs'!S116>=0),'Model inputs'!S116>=0,IF('Model inputs'!S116="","",'Model inputs'!S116>=0))="",FALSE,IF(ISERROR('Model inputs'!S116>=0),'Model inputs'!S116>=0,IF('Model inputs'!S116="","",'Model inputs'!S116>=0))),DATE(2028,1,1),"") -> 46753 | T36: =IF(IF(IF(ISERROR('Model inputs'!T116>=0),'Model inputs'!T116>=0,IF('Model inputs'!T116="","",'Model inputs'!T116>=0))="",FALSE,IF(ISERROR('Model inputs'!T116>=0),'Model inputs'!T116>=0,IF('Model inputs'!T116="","",'Model inputs'!T116>=0))),DATE(2028,2,1),"") -> 46784 | U36: =IF(IF(IF(ISERROR('Model inputs'!U116>=0),'Model inputs'!U116>=0,IF('Model inputs'!U116="","",'Model inputs'!U116>=0))="",FALSE,IF(ISERROR('Model inputs'!U116>=0),'Model inputs'!U116>=0,IF('Model inputs'!U116="","",'Model inputs'!U116>=0))),DATE(2028,3,1),"") -> 46813 | V36: =IF(IF(IF(ISERROR('Model inputs'!V116>=0),'Model inputs'!V116>=0,IF('Model inputs'!V116="","",'Model inputs'!V116>=0))="",FALSE,IF(ISERROR('Model inputs'!V116>=0),'Model inputs'!V116>=0,IF('Model inputs'!V116="","",'Model inputs'!V116>=0))),DATE(2028,4,1),"") -> 46844 | W36: =IF(IF(IF(ISERROR('Model inputs'!W116>=0),'Model inputs'!W116>=0,IF('Model inputs'!W116="","",'Model inputs'!W116>=0))="",FALSE,IF(ISERROR('Model inputs'!W116>=0),'Model inputs'!W116>=0,IF('Model inputs'!W116="","",'Model inputs'!W116>=0))),DATE(2028,5,1),"") -> 46874 | X36: =IF(IF(IF(ISERROR('Model inputs'!X116>=0),'Model inputs'!X116>=0,IF('Model inputs'!X116="","",'Model inputs'!X116>=0))="",FALSE,IF(ISERROR('Model inputs'!X116>=0),'Model inputs'!X116>=0,IF('Model inputs'!X116="","",'Model inputs'!X116>=0))),DATE(2028,6,1),"") -> 46905 | Y36: =IF(IF(IF(ISERROR('Model inputs'!Y116>=0),'Model inputs'!Y116>=0,IF('Model inputs'!Y116="","",'Model inputs'!Y116>=0))="",FALSE,IF(ISERROR('Model inputs'!Y116>=0),'Model inputs'!Y116>=0,IF('Model inputs'!Y116="","",'Model inputs'!Y116>=0))),DATE(2028,7,1),"") -> 46935 | Z36: =IF(IF(IF(ISERROR('Model inputs'!Z116>=0),'Model inputs'!Z116>=0,IF('Model inputs'!Z116="","",'Model inputs'!Z116>=0))="",FALSE,IF(ISERROR('Model inputs'!Z116>=0),'Model inputs'!Z116>=0,IF('Model inputs'!Z116="","",'Model inputs'!Z116>=0))),DATE(2028,8,1),"") -> 46966
A37: Monthly capital spending | C37: =0 -> 0
A38: Monthly fixed cost | C38: 0
A39: Monthly fixed cost > Hosting and runners | C39: =150 -> 150
A40: Monthly fixed cost > Observability — neatlogs | C40: =50 -> 50
A41: Monthly fixed cost > Other tools | C41: =100 -> 100
A42: Net cash flow · Base and upside comparison · Main Scenario | B42: ='Model inputs'!B108-'Model inputs'!C37 -> 4756.201 | D42: ='Model inputs'!D108-'Model inputs'!C37 -> -144 | E42: ='Model inputs'!E108-'Model inputs'!C37 -> 12 | F42: ='Model inputs'!F108-'Model inputs'!C37 -> 168 | G42: ='Model inputs'!G108-'Model inputs'!C37 -> 224.16 | H42: ='Model inputs'!H108-'Model inputs'!C37 -> 287.0592 | I42: ='Model inputs'!I108-'Model inputs'!C37 -> 357.5063 | J42: ='Model inputs'!J108-'Model inputs'!C37 -> 436.40706 | K42: ='Model inputs'!K108-'Model inputs'!C37 -> 524.77591 | L42: ='Model inputs'!L108-'Model inputs'!C37 -> 623.74902 | M42: ='Model inputs'!M108-'Model inputs'!C37 -> 734.5989 | N42: ='Model inputs'!N108-'Model inputs'!C37 -> 858.75077 | O42: ='Model inputs'!O108-'Model inputs'!C37 -> 997.80086 | P42: ='Model inputs'!P108-'Model inputs'!C37 -> 1153.537 | Q42: ='Model inputs'!Q108-'Model inputs'!C37 -> 1327.9614 | R42: ='Model inputs'!R108-'Model inputs'!C37 -> 1523.3168 | S42: ='Model inputs'!S108-'Model inputs'!C37 -> 1742.1148 | T42: ='Model inputs'!T108-'Model inputs'!C37 -> 1987.1685 | U42: ='Model inputs'!U108-'Model inputs'!C37 -> 2261.6288 | V42: ='Model inputs'!V108-'Model inputs'!C37 -> 2569.0242 | W42: ='Model inputs'!W108-'Model inputs'!C37 -> 2913.3071 | X42: ='Model inputs'!X108-'Model inputs'!C37 -> 3298.904 | Y42: ='Model inputs'!Y108-'Model inputs'!C37 -> 3730.7725 | Z42: ='Model inputs'!Z108-'Model inputs'!C37 -> 4214.4652 | AA42: 0
